{"9vmdg5": " LA Cameron", "9vmu25": " LA Calcasieu", "9vmt5b": " LA Beauregard", "9vmy3y": " LA Beauregard", "9vmxp6": " LA Beauregard", "9vms0n": " LA Calcasieu", "9vmsrh": " LA Calcasieu", "9vmzt6": " LA Allen", "9vmkeb": " LA Calcasieu", "9vmvcd": " LA Allen", "9vm9t4": " LA Cameron", "9vmd12": " LA Cameron", "9vmsn5": " LA Calcasieu", "9vmmuh": " LA Beauregard", "9vm6y9": " LA Cameron", "9vmwqe": " LA Beauregard", "9vmy2c": " LA Beauregard", "9vmev1": " LA Calcasieu", "9vmu3z": " LA Jefferson Davis", "9vmgqp": " LA Jefferson Davis", "9vmkfv": " LA Beauregard", "9vmekk": " LA Calcasieu", "9vmfr4": " LA Cameron", "9vmevq": " LA Calcasieu", "9vm3rd": " LA Cameron", "9vmbvw": " LA Cameron", "9vmttu": " LA Beauregard", "9vmv6d": " LA Allen", "9vmsqd": " LA Calcasieu", "9vmz6k": " LA Beauregard", "9vmt7g": " LA Beauregard", "9vm7sq": " LA Calcasieu", "9vmt0d": " LA Beauregard", "9vmxpc": " LA Beauregard", "9vmxm9": " LA Beauregard", "9vmfsw": " LA Cameron", "9vmg7x": " LA Calcasieu", "9vmknn": " LA Calcasieu", "9vmejp": " LA Calcasieu", "9vmk77": " LA Calcasieu", "9vmvxr": " LA Allen", "9vmx24": " LA Beauregard", "9vm7kp": " LA Calcasieu", "9vmvd3": " LA Allen", "9vmz05": " LA Beauregard", "9vmtue": " LA Beauregard", "9vm7jj": " LA Calcasieu", "9vmcw0": " LA Cameron", "9vmqh3": " TX Newton", "9vmsn8": " LA Calcasieu", "9vmv5h": " LA Jefferson Davis", "9vm6y1": " LA Cameron", "9vmsrd": " LA Calcasieu", "9vmu85": " LA Calcasieu", "9vmu8w": " LA Calcasieu", "9vmwtq": " LA Beauregard", "9vmqmd": " LA Beauregard", "9vmqr1": " LA Beauregard", "9vm6s0": " LA Cameron", "9vmejh": " LA Calcasieu", "9vm6vd": " LA Cameron", "9vmw92": " LA Beauregard", "9vmzpv": " LA Allen", "9vmfmd": " LA Cameron", "9vmz5m": " LA Beauregard", "9vmu90": " LA Calcasieu", "9vmetd": " LA Calcasieu", "9vm1rp": " LA Cameron", "9vmfm7": " LA Cameron", "9vm6ks": " LA Cameron", "9vmxdn": " LA Beauregard", "9vmwb8": " LA Beauregard", "9vmv2v": " LA Allen", "9vm7s7": " LA Calcasieu", "9vmxr8": " LA Beauregard", "9vmezr": " LA Calcasieu", "9vmu27": " LA Calcasieu", "9vm7sn": " LA Calcasieu", "9vm643": " LA Cameron", "9vmrnt": " LA Beauregard", "9vmgtw": " LA Jefferson Davis", "9vmey7": " LA Calcasieu", "9vmyub": " LA Allen", "9vmv8h": " LA Beauregard", "9vmv6q": " LA Allen", "9vmmed": " LA Beauregard", "9vmw6v": " LA Beauregard", "9vmtbm": " LA Beauregard", "9vmqhu": " LA Beauregard", "9vmtup": " LA Beauregard", "9vmug6": " LA Jefferson Davis", "9vmvk5": " LA Allen", "9vmetk": " LA Calcasieu", "9vmu2j": " LA Calcasieu", "9vm6gk": " LA Cameron", "9vm97v": " LA Cameron", "9vm9kn": " LA Cameron", "9vmdk0": " LA Cameron", "9vmz0e": " LA Beauregard", "9vmx2p": " LA Beauregard", "9vm6z3": " LA Cameron", "9vmy93": " LA Beauregard", "9vmv3k": " LA Allen", "9vmvew": " LA Allen", "9vmfyc": " LA Cameron", "9vmmtk": " LA Beauregard", "9vmmee": " LA Beauregard", "9vmwp9": " LA Beauregard", "9vmyjm": " LA Allen", "9vmzqw": " LA Allen", "9vmkux": " LA Beauregard", "9vmm79": " LA Beauregard", "9vmcz7": " LA Cameron", "9vmczh": " LA Cameron", "9vmeyy": " LA Calcasieu", "9vmct7": " LA Cameron", "9vmycb": " LA Beauregard", "9vmyv2": " LA Allen", "9vmu11": " LA Calcasieu", "9vme3y": " LA Calcasieu", "9vmeh5": " LA Calcasieu", "9vmeht": " LA Calcasieu", "9vmxq1": " LA Beauregard", "9vmcpq": " LA Cameron", "9vmmp0": " LA Beauregard", "9vmv6s": " LA Allen", "9vmvb6": " LA Beauregard", "9vmevy": " LA Calcasieu", "9vmcjd": " LA Cameron", "9vm66r": " LA Cameron", "9vmwjt": " LA Beauregard", "9vmy7c": " LA Beauregard", "9vm7kw": " LA Calcasieu", "9vmdt2": " LA Cameron", "9vmt37": " LA Calcasieu", "9vm75c": " LA Calcasieu", "9vmqhy": " LA Beauregard", "9vmspy": " LA Calcasieu", "9vm7wu": " LA Calcasieu", "9vmevk": " LA Calcasieu", "9vm7gg": " LA Calcasieu", "9vmx3w": " LA Beauregard", "9vmfz3": " LA Cameron", "9vmejg": " LA Calcasieu", "9vmspk": " LA Calcasieu", "9vmvh8": " LA Jefferson Davis", "9vmcpt": " LA Cameron", "9vms9r": " LA Calcasieu", "9vmyhp": " LA Allen", "9vmwen": " LA Beauregard", "9vmdu5": " LA Cameron", "9vmcj9": " LA Cameron", "9vmwb3": " LA Beauregard", "9vmwg2": " LA Beauregard", "9vmv37": " LA Allen", "9vm9xf": " LA Cameron", "9vmy3x": " LA Beauregard", "9vmk5b": " LA Calcasieu", "9vmdr2": " LA Cameron", "9vm7v1": " LA Calcasieu", "9vmxp7": " LA Beauregard", "9vmcrq": " LA Cameron", "9vmk78": " LA Calcasieu", "9vm752": " LA Calcasieu", "9vmduq": " LA Cameron", "9vmqw0": " LA Beauregard", "9vmxf8": " LA Vernon", "9vmxgf": " LA Vernon", "9vmfrb": " LA Cameron", "9vmfp8": " LA Cameron", "9vmu2u": " LA Calcasieu", "9vmu2e": " LA Calcasieu", "9vmv48": " LA Jefferson Davis", "9vmxpf": " LA Beauregard", "9vm6y2": " LA Cameron", "9vmehx": " LA Calcasieu", "9vmews": " LA Calcasieu", "9vmkkk": " LA Calcasieu", "9vme8w": " LA Calcasieu", "9vmyck": " LA Beauregard", "9vmrxv": " LA Vernon", "9vmtd3": " LA Beauregard", "9vmmet": " LA Beauregard", "9vme5z": " LA Calcasieu", "9vm7um": " LA Calcasieu", "9vmgw4": " LA Jefferson Davis", "9vmydq": " LA Beauregard", "9vm9sn": " LA Cameron", "9vmu12": " LA Calcasieu", "9vmtvw": " LA Beauregard", "9vmeku": " LA Calcasieu", "9vm69f": " LA Cameron", "9vmeh8": " LA Calcasieu", "9vm9ze": " LA Cameron", "9vmvn3": " LA Jefferson Davis", "9vme58": " LA Calcasieu", "9vmsp7": " LA Calcasieu", "9vmspq": " LA Calcasieu", "9vmesh": " LA Calcasieu", "9vmych": " LA Beauregard", "9vmuv8": " LA Jefferson Davis", "9vm98c": " LA Cameron", "9vmymt": " LA Allen", "9vmxq7": " LA Beauregard", "9vmgxk": " LA Jefferson Davis", "9vmkem": " LA Calcasieu", "9vmeys": " LA Calcasieu", "9vmv5k": " LA Jefferson Davis", "9vmqmb": " LA Beauregard", "9vmefz": " LA Calcasieu", "9vm9rq": " LA Cameron", "9vmwpy": " LA Beauregard", "9vme0b": " LA Calcasieu", "9vm6mn": " LA Cameron", "9vmv5q": " LA Allen", "9vmtmm": " LA Beauregard", "9vmsz1": " LA Calcasieu", "9vmsxd": " LA Calcasieu", "9vmsp5": " LA Calcasieu", "9vmfzc": " LA Cameron", "9vmsps": " LA Calcasieu", "9vmsp4": " LA Calcasieu", "9vmted": " LA Beauregard", "9vmu2k": " LA Calcasieu", "9vmgd0": " LA Calcasieu", "9vm9ye": " LA Cameron", "9vmcpm": " LA Cameron", "9vmc7g": " LA Cameron", "9vmdqp": " LA Cameron", "9vmdwc": " LA Cameron", "9vm7vr": " LA Calcasieu", "9vm7mb": " LA Calcasieu", "9vmv4c": " LA Jefferson Davis", "9vmvxk": " LA Allen", "9vmwj9": " LA Beauregard", "9vm6km": " LA Cameron", "9vm6k0": " LA Cameron", "9vmdrj": " LA Cameron", "9vmuyx": " LA Jefferson Davis", "9vm6zz": " LA Calcasieu", "9vm6xr": " LA Cameron", "9vm7pd": " LA Calcasieu", "9vm7mx": " LA Calcasieu", "9vmw15": " LA Beauregard", "9vmcqb": " LA Cameron", "9vmzhd": " LA Allen", "9vmezj": " LA Calcasieu", "9vm7wy": " LA Calcasieu", "9vmt7p": " LA Beauregard", "9vmt3m": " LA Calcasieu", "9vmyn7": " LA Allen", "9vmw7m": " LA Beauregard", "9vmgjs": " LA Calcasieu", "9vmekq": " LA Calcasieu", "9vmdwx": " LA Cameron", "9vmyp9": " LA Allen", "9vmetx": " LA Calcasieu", "9vmrph": " LA Beauregard", "9vmuen": " LA Jefferson Davis", "9vm9qx": " LA Cameron", "9vmsym": " LA Calcasieu", "9vmuct": " LA Jefferson Davis", "9vmyd7": " LA Beauregard", "9vmz2h": " LA Beauregard", "9vmvs2": " LA Allen", "9vmexd": " LA Calcasieu", "9vmewb": " LA Calcasieu", "9vmc5f": " LA Cameron", "9vmd55": " LA Cameron", "9vm9fz": " LA Cameron", "9vmsth": " LA Calcasieu", "9vmwd8": " LA Beauregard", "9vmg3u": " LA Calcasieu", "9vmfzn": " LA Jefferson Davis", "9vmqw7": " LA Beauregard", "9vmwku": " LA Beauregard", "9vmztb": " LA Allen", "9vmty1": " LA Beauregard", "9vmy1z": " LA Beauregard", "9vmzn1": " LA Allen", "9vms79": " LA Calcasieu", "9vmte4": " LA Beauregard", "9vmz4n": " LA Beauregard", "9vmmjq": " LA Beauregard", "9vmvb5": " LA Beauregard", "9vmwpc": " LA Beauregard", "9vmmw8": " LA Beauregard", "9vmfvs": " LA Cameron", "9vmev8": " LA Calcasieu", "9vmg7r": " LA Calcasieu", "9vmsq5": " LA Calcasieu", "9vmg68": " LA Calcasieu", "9vmz6b": " LA Beauregard", "9vmzh4": " LA Beauregard", "9vmmjz": " LA Beauregard", "9vmv5z": " LA Allen", "9vmes7": " LA Calcasieu", "9vmcmd": " LA Cameron", "9vmu52": " LA Calcasieu", "9vmu4z": " LA Calcasieu", "9vm7g8": " TX Orange", "9vmg5y": " LA Calcasieu", "9vmyde": " LA Beauregard", "9vmft5": " LA Cameron", "9vmucd": " LA Jefferson Davis", "9vmqwm": " LA Beauregard", "9vmu1m": " LA Calcasieu", "9vmdte": " LA Cameron", "9vmz54": " LA Beauregard", "9vmx2j": " LA Beauregard", "9vmspv": " LA Calcasieu", "9vmy7h": " LA Beauregard", "9vmvrj": " LA Allen", "9vmvpt": " LA Allen", "9vmvx5": " LA Allen", "9vmvny": " LA Allen", "9vmvx3": " LA Allen", "9vmv6e": " LA Allen", "9vmu0f": " LA Calcasieu", "9vmshv": " LA Calcasieu", "9vmu7r": " LA Jefferson Davis", "9vmez0": " LA Calcasieu", "9vmey8": " LA Calcasieu", "9vmuyc": " LA Jefferson Davis", "9vmfre": " LA Cameron", "9vmg8m": " LA Calcasieu", "9vm9tr": " LA Cameron", "9vm9yf": " LA Cameron", "9vme5n": " LA Calcasieu", "9vmfr9": " LA Cameron", "9vmvsf": " LA Allen", "9vmvv4": " LA Allen", "9vmvu9": " LA Allen", "9vmu1z": " LA Calcasieu", "9vm7vp": " LA Calcasieu", "9vm30d": " LA Cameron", "9vmcme": " LA Cameron", "9vmww3": " LA Beauregard", "9vmugb": " LA Jefferson Davis", "9vmegc": " LA Calcasieu", "9vmwpj": " LA Beauregard", "9vmczc": " LA Cameron", "9vmctv": " LA Cameron", "9vmcsr": " LA Cameron", "9vmtj3": " LA Beauregard", "9vmt84": " LA Beauregard", "9vmy6k": " LA Beauregard", "9vmstg": " LA Calcasieu", "9vmfhy": " LA Cameron", "9vmucm": " LA Jefferson Davis", "9vmvmy": " LA Allen", "9vmcx8": " LA Cameron", "9vmskz": " LA Calcasieu", "9vmeyv": " LA Calcasieu", "9vmetr": " LA Calcasieu", "9vmeuf": " LA Calcasieu", "9vmcz1": " LA Cameron", "9vmcz0": " LA Cameron", "9vmqwg": " LA Beauregard", "9vmwyb": " LA Beauregard", "9vmfx9": " LA Cameron", "9vmwwb": " LA Beauregard", "9vmypw": " LA Allen", "9vmkvg": " LA Beauregard", "9vmdhq": " LA Cameron", "9vmwb6": " LA Beauregard", "9vmwn7": " LA Beauregard", "9vmtvv": " LA Beauregard", "9vmtun": " LA Beauregard", "9vmvm5": " LA Allen", "9vmgmw": " LA Calcasieu", "9vmfk7": " LA Cameron", "9vmu75": " LA Jefferson Davis", "9vm2bt": " LA Cameron", "9vmy7d": " LA Beauregard", "9vm7u7": " LA Calcasieu", "9vmv3g": " LA Allen", "9vmwkv": " LA Beauregard", "9vmtxy": " LA Beauregard", "9vmu00": " LA Calcasieu", "9vmfkp": " LA Cameron", "9vmdn6": " LA Cameron", "9vmeus": " LA Calcasieu", "9vm64e": " LA Cameron", "9vmspg": " LA Calcasieu", "9vmcwx": " LA Cameron", "9vmzt3": " LA Allen", "9vmwj8": " LA Beauregard", "9vmvqw": " LA Allen", "9vmqzq": " LA Beauregard", "9vmrny": " LA Beauregard", "9vmwjv": " LA Beauregard", "9vm69g": " LA Cameron", "9vmy64": " LA Beauregard", "9vmkks": " LA Calcasieu", "9vmy62": " LA Beauregard", "9vmee3": " LA Calcasieu", "9vmfnj": " LA Cameron", "9vmc2q": " LA Cameron", "9vmgjx": " LA Calcasieu", "9vmsre": " LA Calcasieu", "9vmsrp": " LA Calcasieu", "9vme61": " LA Calcasieu", "9vmsr4": " LA Calcasieu", "9vmshd": " LA Calcasieu", "9vmskt": " LA Calcasieu", "9vmykb": " LA Allen", "9vmrzs": " LA Vernon", "9vm9dv": " LA Cameron", "9vmvde": " LA Allen", "9vm96p": " LA Cameron", "9vmy7r": " LA Beauregard", "9vmmjy": " LA Beauregard", "9vmx0c": " LA Beauregard", "9vmvhn": " LA Allen", "9vmvkd": " LA Allen", "9vmv5s": " LA Jefferson Davis", "9vmz7e": " LA Beauregard", "9vmscc": " LA Calcasieu", "9vmwd9": " LA Beauregard", "9vmsrn": " LA Calcasieu", "9vmdqq": " LA Cameron", "9vmdqm": " LA Cameron", "9vmdqs": " LA Cameron", "9vmqht": " LA Beauregard", "9vmqqg": " LA Beauregard", "9vmfe0": " LA Cameron", "9vmscr": " LA Calcasieu", "9vmgkv": " LA Calcasieu", "9vmdp8": " LA Cameron", "9vmkuw": " LA Calcasieu", "9vmur0": " LA Jefferson Davis", "9vmrzu": " LA Vernon", "9vmgnx": " LA Jefferson Davis", "9vm3mb": " LA Cameron", "9vmv4g": " LA Jefferson Davis", "9vmeh1": " LA Calcasieu", "9vm7eg": " LA Calcasieu", "9vmqk1": " LA Beauregard", "9vmufr": " LA Jefferson Davis", "9vmu2d": " LA Calcasieu", "9vm75h": " LA Calcasieu", "9vmt9q": " LA Beauregard", "9vm96y": " LA Cameron", "9vmzj1": " LA Allen", "9vmxq2": " LA Beauregard", "9vmk7m": " LA Calcasieu", "9vmvjt": " LA Allen", "9vmt4k": " LA Calcasieu", "9vmsjf": " LA Calcasieu", "9vmsny": " LA Calcasieu", "9vmscy": " LA Calcasieu", "9vm6ux": " LA Calcasieu", "9vmu8s": " LA Calcasieu", "9vmte1": " LA Beauregard", "9vmwfb": " LA Beauregard", "9vmvmq": " LA Allen", "9vmdpu": " LA Cameron", "9vmwm1": " LA Beauregard", "9vmzxx": " LA Vernon", "9vmuhs": " LA Jefferson Davis", "9vme93": " LA Calcasieu", "9vmgns": " LA Jefferson Davis", "9vm7sm": " LA Calcasieu", "9vm66g": " LA Cameron", "9vmfp3": " LA Cameron", "9vmf4n": " LA Cameron", "9vmg1h": " LA Calcasieu", "9vmxnp": " LA Beauregard", "9vmu3n": " LA Calcasieu", "9vm1px": " LA Cameron", "9vmw5j": " LA Beauregard", "9vmevu": " LA Calcasieu", "9vmcm7": " LA Cameron", "9vmyhw": " LA Allen", "9vmeqc": " LA Calcasieu", "9vmbvy": " LA Cameron", "9vmetw": " LA Calcasieu", "9vmetu": " LA Calcasieu", "9vm7g3": " LA Calcasieu", "9vmdve": " LA Cameron", "9vmqy9": " LA Beauregard", "9vmckh": " LA Cameron", "9vmycj": " LA Beauregard", "9vm7kc": " LA Calcasieu", "9vm9g1": " LA Cameron", "9vmw2f": " LA Beauregard", "9vmwqw": " LA Beauregard", "9vm7tq": " LA Calcasieu", "9vmyp1": " LA Allen", "9vm6t1": " LA Cameron", "9vmvbu": " LA Allen", "9vmv8k": " LA Beauregard", "9vmt4h": " LA Calcasieu", "9vmsq7": " LA Calcasieu", "9vmesw": " LA Calcasieu", "9vmeub": " LA Calcasieu", "9vm9mv": " LA Cameron", "9vmegh": " LA Calcasieu", "9vmxvk": " LA Vernon", "9vmezq": " LA Calcasieu", "9vmfz7": " LA Cameron", "9vms7e": " LA Calcasieu", "9vm7z7": " LA Calcasieu", "9vm305": " TX Jefferson", "9vmsp9": " LA Calcasieu", "9vmv5v": " LA Allen", "9vmezp": " LA Calcasieu", "9vmeq9": " LA Calcasieu", "9vm9ew": " LA Cameron", "9vmete": " LA Calcasieu", "9vmfc9": " LA Cameron", "9vmez5": " LA Calcasieu", "9vmdwp": " LA Cameron", "9vmvz9": " LA Allen", "9vm9rn": " LA Cameron", "9vmee8": " LA Calcasieu", "9vmsms": " LA Calcasieu", "9vm7hw": " LA Calcasieu", "9vmf3t": " LA Cameron", "9vm995": " LA Cameron", "9vmsnb": " LA Calcasieu", "9vmx72": " LA Beauregard", "9vmyfu": " LA Beauregard", "9vmwkg": " LA Beauregard", "9vmm5u": " LA Beauregard", "9vmfrq": " LA Cameron", "9vmz12": " LA Beauregard", "9vmyw1": " LA Allen", "9vmw6k": " LA Beauregard", "9vmzwh": " LA Allen", "9vmye0": " LA Beauregard", "9vmmh1": " LA Beauregard", "9vmtzt": " LA Beauregard", "9vmw47": " LA Beauregard", "9vmghn": " LA Calcasieu", "9vmdy4": " LA Cameron", "9vmcjq": " LA Cameron", "9vmer1": " LA Calcasieu", "9vm9z0": " LA Cameron", "9vmgcz": " LA Calcasieu", "9vmgpt": " LA Jefferson Davis", "9vmeyz": " LA Calcasieu", "9vmxt1": " LA Beauregard", "9vmmgg": " LA Beauregard", "9vmz98": " LA Beauregard", "9vmw75": " LA Beauregard", "9vmz0v": " LA Beauregard", "9vmw2b": " LA Beauregard", "9vmz2c": " LA Beauregard", "9vme6j": " LA Calcasieu", "9vmu9x": " LA Calcasieu", "9vmvqp": " LA Allen", "9vmkkw": " LA Calcasieu", "9vmvxv": " LA Allen", "9vmzzd": " LA Vernon", "9vmkd8": " LA Calcasieu", "9vmyp7": " LA Allen", "9vmz1z": " LA Beauregard", "9vm7pb": " LA Calcasieu", "9vmdqf": " LA Cameron", "9vmfcs": " LA Calcasieu", "9vmg13": " LA Calcasieu", "9vmczg": " LA Cameron", "9vm3uz": " LA Cameron", "9vmt7v": " LA Beauregard", "9vmfjn": " LA Cameron", "9vmtzr": " LA Beauregard", "9vmuuj": " LA Jefferson Davis", "9vmv59": " LA Jefferson Davis", "9vm64m": " LA Cameron", "9vmthu": " LA Beauregard", "9vmufj": " LA Jefferson Davis", "9vmufn": " LA Jefferson Davis", "9vmubz": " LA Jefferson Davis", "9vm9sz": " LA Cameron", "9vmrr0": " LA Beauregard", "9vmrpw": " LA Beauregard", "9vmxnt": " LA Beauregard", "9vm7kh": " LA Calcasieu", "9vmeh9": " LA Calcasieu", "9vmzns": " LA Allen", "9vm7ef": " LA Calcasieu", "9vmsng": " LA Calcasieu", "9vmgt3": " LA Calcasieu", "9vmdd4": " LA Cameron", "9vm7y8": " LA Calcasieu", "9vm7qg": " LA Calcasieu", "9vmxgk": " LA Vernon", "9vmt1x": " LA Calcasieu", "9vmsp3": " LA Calcasieu", "9vmsrg": " LA Calcasieu", "9vm7u0": " LA Calcasieu", "9vm7jc": " LA Calcasieu", "9vmydv": " LA Beauregard", "9vmun9": " LA Jefferson Davis", "9vmydp": " LA Beauregard", "9vmzz8": " LA Vernon", "9vmd5d": " LA Cameron", "9vmsnv": " LA Calcasieu", "9vmsq6": " LA Calcasieu", "9vmduw": " LA Calcasieu", "9vm64r": " LA Cameron", "9vmxr1": " LA Beauregard", "9vmwgg": " LA Beauregard", "9vmfu2": " LA Cameron", "9vm7nf": " LA Calcasieu", "9vmwe4": " LA Beauregard", "9vmfzt": " LA Jefferson Davis", "9vm3gx": " LA Cameron", "9vmfxm": " LA Cameron", "9vmfxk": " LA Cameron", "9vmfy7": " LA Cameron", "9vmskw": " LA Calcasieu", "9vmmqy": " LA Beauregard", "9vme9z": " LA Calcasieu", "9vmxnu": " LA Beauregard", "9vmukd": " LA Jefferson Davis", "9vmum3": " LA Jefferson Davis", "9vmwfs": " LA Beauregard", "9vmfw2": " LA Cameron", "9vmsx5": " LA Calcasieu", "9vmgtr": " LA Jefferson Davis", "9vmgbq": " LA Calcasieu", "9vmx16": " LA Beauregard", "9vmgr0": " LA Jefferson Davis", "9vm3r1": " LA Cameron", "9vmtcg": " LA Beauregard", "9vmtp1": " LA Beauregard", "9vm7t1": " LA Calcasieu", "9vm7wm": " LA Calcasieu", "9vmegs": " LA Calcasieu", "9vmeuk": " LA Calcasieu", "9vmeuy": " LA Calcasieu", "9vmsj2": " LA Calcasieu", "9vmsjb": " LA Calcasieu", "9vmsp0": " LA Calcasieu", "9vmsp2": " LA Calcasieu", "9vmspd": " LA Calcasieu", "9vmu04": " LA Calcasieu", "9vmu0c": " LA Calcasieu", "9vmu56": " LA Calcasieu", "9vmuh4": " LA Jefferson Davis", "9vmuj6": " LA Jefferson Davis", "9vmupf": " LA Jefferson Davis", "9vmey1": " LA Calcasieu", "9vmey3": " LA Calcasieu", "9vmeyc": " LA Calcasieu", "9vmez1": " LA Calcasieu", "9vmez9": " LA Calcasieu", "9vmezu": " LA Calcasieu", "9vmezy": " LA Calcasieu", "9vmspb": " LA Calcasieu", "9vmwyr": " LA Beauregard", "9vmz26": " LA Beauregard", "9vmx4t": " LA Beauregard", "9vmm7z": " LA Beauregard", "9vmqw6": " LA Beauregard", "9vmqhs": " LA Beauregard", "9vmmus": " LA Beauregard", "9vmqw3": " LA Beauregard", "9vmqtz": " LA Beauregard", "9vmt09": " LA Beauregard", "9vmqwn": " LA Beauregard", "9vmmuk": " LA Beauregard", "9vmkyw": " LA Beauregard", "9vmmws": " LA Beauregard", "9vmw0h": " LA Beauregard", "9vmmuy": " LA Beauregard", "9vmmzt": " LA Beauregard", "9vmm7b": " LA Beauregard", "9vmwdr": " LA Beauregard", "9vmmzb": " LA Beauregard", "9vmmp3": " LA Beauregard", "9vmmzk": " LA Beauregard", "9vmmrn": " LA Beauregard", "9vmw28": " LA Beauregard", "9vmmqv": " LA Beauregard", "9vmker": " LA Calcasieu", "9vmkqf": " LA Calcasieu", "9vmkvs": " LA Calcasieu", "9vmkry": " LA Calcasieu", "9vm7gu": " LA Calcasieu", "9vmkmn": " LA Calcasieu", "9vmkmp": " LA Calcasieu", "9vmkzh": " LA Calcasieu", "9vmvfz": " LA Allen", "9vmv9u": " LA Allen", "9vmv85": " LA Beauregard", "9vmvxs": " LA Allen", "9vmbwk": " LA Cameron", "9vm9bx": " LA Cameron", "9vm6mp": " LA Cameron", "9vm6nu": " LA Cameron", "9vm3zx": " LA Cameron", "9vm6t0": " LA Cameron", "9vm6r2": " LA Cameron", "9vmd2y": " LA Cameron", "9vm6p6": " LA Cameron", "9vmv9g": " LA Allen", "9vmgcb": " LA Calcasieu", "9vmkqc": " LA Calcasieu", "9vmgg0": " LA Calcasieu", "9vmspj": " LA Calcasieu", "9vmse3": " LA Calcasieu", "9vmehp": " LA Calcasieu", "9vmeeh": " LA Calcasieu", "9vmg99": " LA Calcasieu", "9vmvnt": " LA Jefferson Davis", "9vm7qn": " LA Calcasieu", "9vmtkm": " LA Beauregard", "9vmu2m": " LA Calcasieu", "9vmzhu": " LA Allen", "9vmez8": " LA Calcasieu", "9vmdeu": " LA Cameron", "9vmt3k": " LA Calcasieu", "9vmyj9": " LA Allen", "9vmu9t": " LA Calcasieu", "9vmkge": " LA Beauregard", "9vmxk7": " LA Beauregard", "9vm937": " LA Cameron", "9vmeuq": " LA Calcasieu", "9vmxwu": " LA Beauregard", "9vmvhr": " LA Allen", "9vmw4j": " LA Beauregard", "9vmxce": " LA Vernon", "9vmfpq": " LA Cameron", "9vmsj0": " LA Calcasieu", "9vm6tk": " LA Cameron", "9vmkyc": " LA Calcasieu", "9vmxth": " LA Beauregard", "9vmeux": " LA Calcasieu", "9vmyty": " LA Allen", "9vmsrk": " LA Calcasieu", "9vme7f": " LA Calcasieu", "9vm7u3": " LA Calcasieu", "9vmfrh": " LA Cameron", "9vmt9v": " LA Beauregard", "9vmsfk": " LA Calcasieu", "9vmg7f": " LA Calcasieu", "9vmes1": " LA Calcasieu", "9vmdtt": " LA Cameron", "9vmx84": " LA Beauregard", "9vmmes": " TX Newton", "9vmmsx": " LA Beauregard", "9vmmg6": " LA Beauregard", "9vmmgh": " LA Beauregard", "9vmmvf": " LA Beauregard", "9vmmwv": " LA Beauregard", "9vmmy9": " LA Beauregard", "9vmmyf": " LA Beauregard", "9vmmxe": " LA Beauregard", "9vmmzu": " LA Beauregard", "9vmt9n": " LA Beauregard", "9vmtcx": " LA Beauregard", "9vmw1u": " LA Beauregard", "9vmtev": " LA Beauregard", "9vmttc": " LA Beauregard", "9vmt92": " LA Beauregard", "9vmtw6": " LA Beauregard", "9vmtwm": " LA Beauregard", "9vmtz0": " LA Beauregard", "9vmtz5": " LA Beauregard", "9vmtyk": " LA Beauregard", "9vmwnd": " LA Beauregard", "9vmtxw": " LA Beauregard", "9vmvbw": " LA Beauregard", "9vmwne": " LA Beauregard", "9vmm7d": " TX Newton", "9vmm7s": " LA Beauregard", "9vmmkw": " LA Beauregard", "9vmmr5": " LA Beauregard", "9vmmpd": " LA Beauregard", "9vmt28": " LA Beauregard", "9vmt7e": " LA Beauregard", "9vmtkh": " LA Beauregard", "9vmth6": " LA Beauregard", "9vmtky": " LA Beauregard", "9vmtr5": " LA Beauregard", "9vmqzt": " LA Beauregard", "9vmwb0": " LA Beauregard", "9vmqrz": " LA Beauregard", "9vmqx5": " LA Beauregard", "9vmqw9": " LA Beauregard", "9vmqjz": " LA Beauregard", "9vmw8u": " LA Beauregard", "9vmwtr": " LA Beauregard", "9vmwq1": " LA Beauregard", "9vmwqn": " LA Beauregard", "9vmwqs": " LA Beauregard", "9vmww2": " LA Beauregard", "9vmww0": " LA Beauregard", "9vmwwn": " LA Beauregard", "9vmwzf": " LA Beauregard", "9vmwpx": " LA Beauregard", "9vmy0x": " LA Beauregard", "9vmy8s": " LA Beauregard", "9vmygj": " LA Beauregard", "9vmyf6": " LA Beauregard", "9vmydx": " LA Beauregard", "9vmy6x": " LA Beauregard", "9vmy6z": " LA Beauregard", "9vmx78": " LA Beauregard", "9vmxk4": " LA Beauregard", "9vmxkm": " LA Beauregard", "9vmxkq": " LA Beauregard", "9vmxkw": " LA Beauregard", "9vmxs9": " LA Beauregard", "9vmxsb": " LA Beauregard", "9vmxky": " LA Beauregard", "9vmxmp": " LA Beauregard", "9vmxsc": " LA Beauregard", "9vmxt4": " LA Beauregard", "9vmxt0": " LA Beauregard", "9vmxmq": " LA Beauregard", "9vmxmn": " LA Beauregard", "9vmxmr": " LA Beauregard", "9vm6d5": " LA Cameron", "9vmvx8": " LA Allen", "9vmve4": " LA Allen", "9vmyvr": " LA Allen", "9vmmw5": " LA Beauregard", "9vmx04": " LA Beauregard", "9vmwq2": " LA Beauregard", "9vmw60": " LA Beauregard", "9vmtqn": " LA Beauregard", "9vmz4r": " LA Beauregard", "9vmy9u": " LA Beauregard", "9vmgk4": " LA Calcasieu", "9vmez4": " LA Calcasieu", "9vmeup": " LA Calcasieu", "9vmks8": " LA Calcasieu", "9vmt1u": " LA Calcasieu", "9vm7y2": " LA Calcasieu", "9vmu48": " LA Calcasieu", "9vmcew": " LA Cameron", "9vm9tc": " LA Cameron", "9vm3vd": " LA Cameron", "9vmde6": " LA Cameron", "9vmuwv": " LA Jefferson Davis", "9vmgx5": " LA Jefferson Davis", "9vmuj0": " LA Jefferson Davis", "9vmug2": " LA Jefferson Davis", "9vmxvs": " LA Vernon", "9vmxmw": " LA Beauregard", "9vmxmt": " LA Beauregard", "9vmxmx": " LA Beauregard", "9vmxmz": " LA Beauregard", "9vmwvz": " LA Beauregard", "9vmxnn": " LA Beauregard", "9vmxw6": " LA Beauregard", "9vmrxf": " LA Beauregard", "9vmrn6": " LA Beauregard", "9vmqyy": " LA Beauregard", "9vmrp5": " LA Beauregard", "9vmx49": " LA Beauregard", "9vmxds": " LA Beauregard", "9vmxd4": " LA Beauregard", "9vmx2z": " LA Beauregard", "9vmybz": " LA Beauregard", "9vmycw": " LA Beauregard", "9vmzd4": " LA Beauregard", "9vmz58": " LA Beauregard", "9vmz7q": " LA Beauregard", "9vmz7g": " LA Beauregard", "9vmv2f": " LA Allen", "9vmvs1": " LA Allen", "9vmvtb": " LA Allen", "9vmyz9": " LA Allen", "9vmzxu": " LA Allen", "9vmvwc": " LA Allen", "9vmvrq": " LA Allen", "9vmvqu": " LA Allen", "9vmzkf": " LA Allen", "9vmvfm": " LA Allen", "9vmvkf": " LA Allen", "9vmyve": " LA Allen", "9vmvzr": " LA Allen", "9vmvds": " LA Allen", "9vmv7r": " LA Allen", "9vmzw0": " LA Allen", "9vmvjw": " LA Allen", "9vmzjb": " LA Allen", "9vmvqb": " LA Allen", "9vmvv3": " LA Allen", "9vmuv2": " LA Jefferson Davis", "9vmutx": " LA Jefferson Davis", "9vmvht": " LA Jefferson Davis", "9vmv53": " LA Jefferson Davis", "9vmujh": " LA Jefferson Davis", "9vmuj8": " LA Jefferson Davis", "9vmgx9": " LA Jefferson Davis", "9vmguz": " LA Jefferson Davis", "9vmfvj": " LA Jefferson Davis", "9vmgup": " LA Jefferson Davis", "9vmufx": " LA Jefferson Davis", "9vmupb": " LA Jefferson Davis", "9vmgzz": " LA Jefferson Davis", "9vmuzn": " LA Jefferson Davis", "9vmut1": " LA Jefferson Davis", "9vmc4h": " LA Cameron", "9vm1x9": " LA Cameron", "9vm33f": " LA Cameron", "9vmcdc": " LA Cameron", "9vm33q": " LA Cameron", "9vm37y": " LA Cameron", "9vmc90": " LA Cameron", "9vmc86": " LA Cameron", "9vmc4x": " LA Cameron", "9vm3ej": " LA Cameron", "9vm3fc": " LA Cameron", "9vm3en": " LA Cameron", "9vmcrm": " LA Cameron", "9vmcsc": " LA Cameron", "9vm3dt": " LA Cameron", "9vmc3d": " LA Cameron", "9vm33c": " LA Cameron", "9vm380": " LA Cameron", "9vm646": " LA Cameron", "9vm38f": " LA Cameron", "9vmc4t": " LA Cameron", "9vm362": " LA Cameron", "9vmc95": " LA Cameron", "9vm3ew": " LA Cameron", "9vm3d6": " LA Cameron", "9vm3d9": " LA Cameron", "9vm3sj": " LA Cameron", "9vmc5w": " LA Cameron", "9vmc7k": " LA Cameron", "9vmcsp": " LA Cameron", "9vm39y": " LA Cameron", "9vm3tr": " LA Cameron", "9vmc31": " LA Cameron", "9vmc60": " LA Cameron", "9vm3kz": " LA Cameron", "9vm927": " LA Cameron", "9vm3m5": " LA Cameron", "9vm37q": " LA Cameron", "9vmcs0": " LA Cameron", "9vm363": " LA Cameron", "9vm337": " LA Cameron", "9vm34v": " LA Cameron", "9vm37n": " LA Cameron", "9vm3ex": " LA Cameron", "9vm3fj": " LA Cameron", "9vm3k9": " LA Cameron", "9vmzd1": " LA Beauregard", "9vmxwd": " LA Beauregard", "9vmzvs": " LA Vernon", "9vmzmn": " LA Allen", "9vmxy4": " LA Vernon", "9vmzcw": " LA Vernon", "9vmzf5": " LA Vernon", "9vmz8n": " LA Vernon", "9vmzt7": " LA Allen", "9vmzcu": " LA Vernon", "9vmz8c": " LA Beauregard", "9vmzf0": " LA Vernon", "9vmxy2": " LA Vernon", "9vmxvy": " LA Vernon", "9vmzsg": " LA Allen", "9vmzc4": " LA Vernon", "9vmzcn": " LA Vernon", "9vmzvx": " LA Vernon", "9vmzvf": " LA Vernon", "9vmz3y": " LA Beauregard", "9vmzwc": " LA Allen", "9vmztm": " LA Vernon", "9vmzt0": " LA Allen", "9vmz5v": " LA Beauregard", "9vmzfk": " LA Vernon", "9vm66s": " LA Cameron", "9vmxzb": " LA Vernon", "9vmxy8": " LA Vernon", "9vmzdx": " LA Vernon", "9vmzvp": " LA Vernon", "9vmxvm": " LA Vernon", "9vmxvn": " LA Vernon", "9vmxb6": " LA Vernon", "9vmxxq": " LA Vernon", "9vm303": " TX Jefferson", "9vm3zw": " LA Cameron", "9vm1rx": " LA Cameron", "9vm6my": " LA Cameron", "9vmdj3": " LA Cameron", "9vm9kh": " LA Cameron", "9vm9s2": " LA Cameron", "9vm3tm": " LA Cameron", "9vm9s9": " LA Cameron", "9vmd6t": " LA Cameron", "9vm3q9": " LA Cameron", "9vm9cm": " LA Cameron", "9vm3df": " LA Cameron", "9vm6q3": " LA Cameron", "9vmc8t": " LA Cameron", "9vm3mt": " LA Cameron", "9vm9yh": " LA Cameron", "9vm96u": " LA Cameron", "9vm99y": " LA Cameron", "9vm6xk": " LA Cameron", "9vm9qq": " LA Cameron", "9vmf3c": " LA Cameron", "9vmcry": " LA Cameron", "9vmcqg": " LA Cameron", "9vmfd7": " LA Cameron", "9vmddf": " LA Cameron", "9vmf9x": " LA Cameron", "9vm3k4": " LA Cameron", "9vm371": " LA Cameron", "9vm9kx": " LA Cameron", "9vmc83": " LA Cameron", "9vmfvd": " LA Cameron", "9vmfsy": " LA Cameron", "9vmfxu": " LA Cameron", "9vmd1x": " LA Cameron", "9vm9qn": " LA Cameron", "9vm9kp": " LA Cameron", "9vmdrc": " LA Cameron", "9vm988": " LA Cameron", "9vm9wd": " LA Cameron", "9vmf8v": " LA Cameron", "9vm36k": " LA Cameron", "9vm3qd": " LA Cameron", "9vm9kz": " LA Cameron", "9vm37d": " LA Cameron", "9vmcp3": " LA Cameron", "9vmc84": " LA Cameron", "9vm986": " LA Cameron", "9vmcne": " LA Cameron", "9vmd42": " LA Cameron", "9vm36z": " LA Cameron", "9vm6wc": " LA Cameron", "9vmfg3": " LA Cameron", "9vmfn2": " LA Cameron", "9vmfz0": " LA Cameron", "9vmf2d": " LA Cameron", "9vmfcc": " LA Cameron", "9vm6r6": " LA Cameron", "9vm9es": " LA Cameron", "9vmddk": " LA Cameron", "9vmd3s": " LA Cameron", "9vm9s8": " LA Cameron", "9vm9fu": " LA Cameron", "9vm9qp": " LA Cameron", "9vm330": " LA Cameron", "9vmyrk": " LA Allen", "9vmew7": " LA Calcasieu", "9vmexp": " LA Calcasieu", "9vmeyf": " LA Calcasieu", "9vmezm": " LA Calcasieu", "9vmexr": " LA Calcasieu", "9vmezx": " LA Calcasieu", "9vmewu": " LA Calcasieu", "9vmspm": " LA Calcasieu", "9vmexw": " LA Calcasieu", "9vmezh": " LA Calcasieu", "9vmexj": " LA Calcasieu", "9vmu01": " LA Calcasieu", "9vmsz3": " LA Calcasieu", "9vmsp6": " LA Calcasieu", "9vmewt": " LA Calcasieu", "9vmez7": " LA Calcasieu", "9vmezs": " LA Calcasieu", "9vmsn0": " LA Calcasieu", "9vmewc": " LA Calcasieu", "9vmgb5": " LA Calcasieu", "9vmsr5": " LA Calcasieu", "9vmsqs": " LA Calcasieu", "9vmsp1": " LA Calcasieu", "9vmsn2": " LA Calcasieu", "9vmez6": " LA Calcasieu", "9vmewp": " LA Calcasieu", "9vmez3": " LA Calcasieu", "9vmewj": " LA Calcasieu", "9vmezw": " LA Calcasieu", "9vmsqu": " LA Calcasieu", "9vmeyk": " LA Calcasieu", "9vmgbj": " LA Calcasieu", "9vmeze": " LA Calcasieu", "9vmspc": " LA Calcasieu", "9vmetv": " LA Calcasieu", "9vmt1y": " LA Calcasieu", "9vmsu8": " LA Calcasieu", "9vmgkd": " LA Calcasieu", "9vmsnj": " LA Calcasieu", "9vmsjs": " LA Calcasieu", "9vmey6": " LA Calcasieu", "9vmse8": " LA Calcasieu", "9vms57": " LA Calcasieu", "9vmgdj": " LA Calcasieu", "9vmeuw": " LA Calcasieu", "9vmegy": " LA Calcasieu", "9vmgbk": " LA Calcasieu", "9vmgcq": " LA Calcasieu", "9vmgcm": " LA Calcasieu", "9vme9u": " LA Calcasieu", "9vme39": " LA Calcasieu", "9vmsju": " LA Calcasieu", "9vms50": " LA Calcasieu", "9vms52": " LA Calcasieu", "9vmt1z": " LA Calcasieu", "9vmt1q": " LA Calcasieu", "9vm7v8": " LA Calcasieu", "9vmgkx": " LA Calcasieu", "9vmgf3": " LA Calcasieu", "9vmt4r": " LA Calcasieu", "9vmeyb": " LA Calcasieu", "9vmsjc": " LA Calcasieu", "9vmegj": " LA Calcasieu", "9vmegk": " LA Calcasieu", "9vmeyu": " LA Calcasieu", "9vmg8z": " LA Calcasieu", "9vmt60": " LA Calcasieu", "9vmewn": " LA Calcasieu", "9vmu53": " LA Calcasieu", "9vmegn": " LA Calcasieu", "9vmewm": " LA Calcasieu", "9vms54": " LA Calcasieu", "9vmeen": " LA Calcasieu", "9vmey9": " LA Calcasieu", "9vmeur": " LA Calcasieu", "9vmegw": " LA Calcasieu", "9vmt4n": " LA Calcasieu", "9vmt4p": " LA Calcasieu", "9vmkf7": " TX Newton", "9vmfgy": " LA Calcasieu", "9vme8x": " LA Calcasieu", "9vmspe": " LA Calcasieu", "9vmffx": " LA Calcasieu", "9vmke4": " LA Calcasieu", "9vms4c": " LA Calcasieu", "9vmewx": " LA Calcasieu", "9vmefy": " LA Calcasieu", "9vmsjt": " LA Calcasieu", "9vm7h6": " LA Calcasieu", "9vmt1s": " LA Calcasieu", "9vmezk": " LA Calcasieu", "9vmeyg": " LA Calcasieu", "9vmeut": " LA Calcasieu", "9vm7w7": " LA Calcasieu", "9vmewy": " LA Calcasieu", "9vmeww": " LA Calcasieu", "9vmfcm": " LA Calcasieu", "9vmggf": " LA Calcasieu", "9vmg23": " LA Calcasieu", "9vmeyd": " LA Calcasieu", "9vms51": " LA Calcasieu", "9vmegp": " LA Calcasieu", "9vms59": " LA Calcasieu", "9vmewz": " LA Calcasieu", "9vmsh2": " LA Calcasieu", "9vm7wq": " LA Calcasieu", "9vm7y3": " LA Calcasieu", "9vmegx": " LA Calcasieu", "9vmegr": " LA Calcasieu", "9vmg3m": " LA Calcasieu", "9vmsje": " LA Calcasieu", "9vmt38": " LA Calcasieu", "9vmsn1": " LA Calcasieu", "9vmt32": " LA Calcasieu", "9vmsjv": " LA Calcasieu", "9vmsjg": " LA Calcasieu", "9vm6zd": " LA Cameron", "9vmbzc": " LA Cameron", "9vmqvc": " LA Beauregard", "9vmmsp": " LA Beauregard", "9vmv51": " LA Jefferson Davis", "9vmrx5": " LA Beauregard", "9vmdpj": " LA Cameron", "9vme4x": " LA Calcasieu", "9vmevg": " LA Calcasieu", "9vmu3j": " LA Jefferson Davis", "9vmbvr": " LA Cameron", "9vmkw0": " LA Calcasieu", "9vmtb0": " LA Beauregard", "9vmw3r": " LA Beauregard", "9vmtt5": " LA Beauregard", "9vmwg1": " LA Beauregard", "9vmssz": " LA Calcasieu", "9vmw7j": " LA Beauregard", "9vmgk9": " LA Calcasieu", "9vmzy4": " LA Vernon", "9vmm51": " LA Beauregard", "9vmdy1": " LA Cameron", "9vmym4": " LA Allen", "9vmvtu": " LA Allen", "9vmdf2": " LA Cameron", "9vmdsn": " LA Cameron", "9vmf22": " LA Cameron", "9vm7k9": " LA Calcasieu", "9vmm5y": " LA Beauregard", "9vmgsm": " LA Jefferson Davis", "9vmxm0": " LA Beauregard", "9vmf1s": " LA Cameron", "9vms4d": " LA Calcasieu", "9vmdgk": " LA Cameron", "9vmd62": " LA Cameron", "9vmx5s": " LA Beauregard", "9vmxpx": " LA Beauregard", "9vmmsj": " LA Beauregard", "9vmyhf": " LA Allen", "9vmycm": " LA Beauregard", "9vms3q": " LA Calcasieu", "9vmejj": " LA Calcasieu", "9vmduz": " LA Calcasieu", "9vmqmv": " LA Beauregard", "9vmm50": " LA Beauregard", "9vmyjr": " LA Allen", "9vmwuw": " LA Beauregard", "9vmm7t": " LA Beauregard", "9vmcz9": " LA Cameron", "9vm3yx": " LA Cameron", "9vmfsn": " LA Cameron", "9vmexn": " LA Calcasieu", "9vmeyq": " LA Calcasieu", "9vmxp1": " LA Beauregard", "9vmbzk": " LA Cameron", "9vmmhg": " LA Beauregard", "9vmxfe": " LA Vernon", "9vmm5d": " LA Beauregard", "9vme11": " LA Calcasieu", "9vmz9u": " LA Beauregard", "9vmz9v": " LA Vernon", "9vmtt3": " LA Beauregard", "9vm7gw": " LA Calcasieu", "9vmtm4": " LA Beauregard", "9vmtv6": " LA Beauregard", "9vmchb": " LA Cameron", "9vmy61": " LA Beauregard", "9vmyhd": " LA Allen", "9vmsg7": " LA Calcasieu", "9vmxg0": " LA Vernon", "9vmscm": " LA Calcasieu", "9vmzy5": " LA Vernon", "9vmmgx": " LA Beauregard", "9vmy7j": " LA Beauregard", "9vmy6v": " LA Beauregard", "9vmqh7": " LA Beauregard", "9vmm5e": " LA Beauregard", "9vmdsp": " LA Cameron", "9vm2bc": " TX Jefferson", "9vmsgr": " LA Beauregard", "9vmrr1": " LA Beauregard", "9vmebp": " LA Calcasieu", "9vms07": " LA Calcasieu", "9vmmwt": " LA Beauregard", "9vmbyx": " LA Cameron", "9vmfp5": " LA Cameron", "9vmtx4": " LA Beauregard", "9vmmh4": " LA Beauregard", "9vmtpn": " LA Beauregard", "9vmw1s": " LA Beauregard", "9vme08": " LA Calcasieu", "9vmck6": " LA Cameron", "9vmdvd": " LA Cameron", "9vmkv1": " LA Calcasieu", "9vmde4": " LA Cameron", "9vm3ke": " LA Cameron", "9vmyn2": " LA Allen", "9vmvtq": " LA Allen", "9vmgm9": " LA Calcasieu", "9vmt02": " LA Beauregard", "9vmxt9": " LA Beauregard", "9vmsub": " LA Calcasieu", "9vmch7": " LA Cameron", "9vmg6x": " LA Calcasieu", "9vm7eu": " LA Calcasieu", "9vmqvg": " LA Beauregard", "9vmrnw": " LA Beauregard", "9vmsm6": " LA Calcasieu", "9vms4r": " LA Calcasieu", "9vmywj": " LA Allen", "9vmtje": " LA Beauregard", "9vmyy0": " LA Allen", "9vmmxz": " LA Beauregard", "9vm37f": " LA Cameron", "9vm9y9": " LA Cameron", "9vmfpr": " LA Cameron", "9vmu0d": " LA Calcasieu", "9vmy6n": " LA Beauregard", "9vmczf": " LA Cameron", "9vmm57": " TX Newton", "9vmcw8": " LA Cameron", "9vmqhq": " LA Beauregard", "9vmd5x": " LA Cameron", "9vmd5z": " LA Cameron", "9vmwnk": " LA Beauregard", "9vm7k7": " LA Calcasieu", "9vm7gd": " LA Calcasieu", "9vmt3z": " LA Beauregard", "9vmmem": " LA Beauregard", "9vmc70": " LA Cameron", "9vmkwn": " LA Calcasieu", "9vm397": " LA Cameron", "9vmtxt": " LA Beauregard", "9vmgc8": " LA Calcasieu", "9vmucg": " LA Jefferson Davis", "9vmqw2": " LA Beauregard", "9vmqm4": " LA Beauregard", "9vmek5": " LA Calcasieu", "9vm993": " LA Cameron", "9vmeh3": " LA Calcasieu", "9vms53": " LA Calcasieu", "9vmkd3": " TX Newton", "9vm9db": " LA Cameron", "9vmrqz": " LA Beauregard", "9vmzm3": " LA Allen", "9vm757": " LA Calcasieu", "9vm75s": " LA Calcasieu", "9vmt5z": " LA Beauregard", "9vmx5u": " LA Beauregard", "9vm6vt": " LA Cameron", "9vmdem": " LA Cameron", "9vmbzu": " LA Cameron", "9vmetn": " LA Calcasieu", "9vmvvn": " LA Allen", "9vms87": " LA Calcasieu", "9vmbz7": " LA Cameron", "9vmrrn": " LA Beauregard", "9vm608": " TX Orange", "9vm69d": " TX Orange", "9vmeyt": " LA Calcasieu", "9vmrn3": " LA Beauregard", "9vmcnb": " LA Cameron", "9vmz0p": " LA Beauregard", "9vmyw0": " LA Allen", "9vmyvx": " LA Allen", "9vmmg1": " LA Beauregard", "9vmz9f": " LA Beauregard", "9vmwph": " LA Beauregard", "9vmz1j": " LA Beauregard", "9vmkjk": " LA Calcasieu", "9vms1b": " LA Calcasieu", "9vmbz4": " LA Cameron", "9vmknx": " LA Calcasieu", "9vms47": " LA Calcasieu", "9vmf2m": " LA Cameron", "9vmf8f": " LA Cameron", "9vmmen": " TX Newton", "9vmywp": " LA Allen", "9vmxwf": " LA Beauregard", "9vmbzh": " LA Cameron", "9vm7sc": " LA Calcasieu", "9vmmgq": " LA Beauregard", "9vmcqj": " LA Cameron", "9vm7w2": " LA Calcasieu", "9vmddp": " LA Cameron", "9vmtt7": " LA Beauregard", "9vmdx6": " LA Cameron", "9vmqk2": " LA Beauregard", "9vmqmc": " LA Beauregard", "9vmycd": " LA Beauregard", "9vmy5c": " LA Allen", "9vmy53": " LA Allen", "9vmvgp": " LA Allen", "9vmxqj": " LA Beauregard", "9vmx6m": " LA Beauregard", "9vmxsv": " LA Beauregard", "9vmxsd": " LA Beauregard", "9vmxtd": " LA Beauregard", "9vmxkf": " LA Beauregard", "9vmxhr": " LA Beauregard", "9vmwux": " LA Beauregard", "9vmxht": " LA Beauregard", "9vmxjp": " LA Beauregard", "9vmwdt": " LA Beauregard", "9vmtgx": " LA Beauregard", "9vmtvt": " LA Beauregard", "9vmw1c": " LA Beauregard", "9vmw41": " LA Beauregard", "9vmye4": " LA Beauregard", "9vmvuk": " LA Allen", "9vmssu": " LA Calcasieu", "9vmxeh": " LA Beauregard", "9vmyg5": " LA Beauregard", "9vmvrd": " LA Allen", "9vmvjb": " LA Allen", "9vmt6f": " LA Calcasieu", "9vmevr": " LA Calcasieu", "9vmgqg": " LA Jefferson Davis", "9vmtc2": " LA Beauregard", "9vm9em": " LA Cameron", "9vmupy": " LA Jefferson Davis", "9vmyrs": " LA Allen", "9vmw7g": " LA Beauregard", "9vm9z1": " LA Cameron", "9vmfe1": " LA Cameron", "9vmsc1": " LA Calcasieu", "9vmmz6": " LA Beauregard", "9vmwqk": " LA Beauregard", "9vmfg0": " LA Cameron", "9vmznc": " LA Allen", "9vmdxz": " LA Cameron", "9vmgr1": " LA Jefferson Davis", "9vmfrm": " LA Cameron", "9vmej5": " LA Calcasieu", "9vmdm0": " LA Cameron", "9vm3qh": " LA Cameron", "9vm6gn": " TX Orange", "9vm54e": " TX Jefferson", "9vm5n1": " TX Orange", "9vm538": " TX Jefferson", "9vm18g": " TX Jefferson", "9vmh61": " TX Hardin", "9vm50d": " TX Jefferson", "9vm4bw": " TX Jefferson", "9vm74z": " TX Orange", "9vm566": " TX Jefferson", "9vm51z": " TX Jefferson", "9vm54j": " TX Jefferson", "9vm55q": " TX Orange", "9vm739": " TX Orange", "9vm73c": " TX Orange", "9vm5dw": " TX Orange", "9vm17b": " TX Jefferson", "9vm54r": " TX Jefferson", "9vmh3b": " TX Hardin", "9vmh39": " TX Hardin", "9vm54s": " TX Jefferson", "9vmh4j": " TX Hardin", "9vm753": " TX Orange", "9vm4y7": " TX Orange", "9vmjq1": " TX Jasper", "9vm554": " TX Jefferson", "9vmh4e": " TX Hardin", "9vm5f3": " TX Hardin", "9vm4fg": " TX Jefferson", "9vmk83": " TX Newton", "9vm4fm": " TX Jefferson", "9vm74q": " TX Orange", "9vm5ru": " TX Orange", "9vm54c": " TX Jefferson", "9vm1s4": " TX Jefferson", "9vm1eb": " TX Jefferson", "9vm7e8": " TX Orange", "9vmh2b": " TX Hardin", "9vmjph": " TX Jasper", "9vm58x": " TX Hardin", "9vm58e": " TX Jefferson", "9vm564": " TX Jefferson", "9vm529": " TX Jefferson", "9vm54v": " TX Jefferson", "9vm6b3": " TX Orange", "9vm4c0": " TX Jefferson", "9vm774": " TX Orange", "9vm74t": " TX Orange", "9vmh66": " TX Hardin", "9vmh82": " TX Hardin", "9vmk35": " TX Newton", "9vm5de": " TX Orange", "9vm5d8": " TX Orange", "9vmhh2": " TX Orange", "9vm17e": " TX Jefferson", "9vm51w": " TX Jefferson", "9vm51m": " TX Jefferson", "9vm517": " TX Jefferson", "9vm512": " TX Jefferson", "9vm513": " TX Jefferson", "9vmh1h": " TX Hardin", "9vm5s1": " TX Orange", "9vm551": " TX Jefferson", "9vm1y5": " TX Jefferson", "9vm544": " TX Jefferson", "9vmh0w": " TX Hardin", "9vmh02": " TX Hardin", "9vm0fs": " TX Jefferson", "9vm0fx": " TX Jefferson", "9vm4uj": " TX Jefferson", "9vmh2r": " TX Hardin", "9vm1d6": " TX Jefferson", "9vm70j": " TX Orange", "9vm56v": " TX Jefferson", "9vm6ct": " TX Orange", "9vmh5z": " TX Jasper", "9vm75n": " TX Orange", "9vm74f": " TX Orange", "9vm6fc": " TX Orange", "9vmher": " TX Jasper", "9vm1ks": " TX Jefferson", "9vm549": " TX Jefferson", "9vm74v": " TX Orange", "9vm536": " TX Jefferson", "9vm1u4": " TX Jefferson", "9vmk6g": " TX Newton", "9vm0gs": " TX Jefferson", "9vm74k": " TX Orange", "9vmhnr": " TX Jasper", "9vm70y": " TX Orange", "9vm54t": " TX Jefferson", "9vm1ty": " TX Jefferson", "9vm77m": " TX Orange", "9vmh7c": " TX Jasper", "9vm7e1": " TX Orange", "9vm565": " TX Jefferson", "9vm53c": " TX Jefferson", "9vm50e": " TX Jefferson", "9vm4fr": " TX Jefferson", "9vmhem": " TX Jasper", "9vm74u": " TX Orange", "9vmjm9": " TX Jasper", "9vm540": " TX Jefferson", "9vm53f": " TX Jefferson", "9vm0cu": " TX Jefferson", "9vmh0t": " TX Hardin", "9vm4vh": " TX Orange", "9vmk42": " TX Orange", "9vm743": " TX Orange", "9vm5dx": " TX Orange", "9vmh63": " TX Jasper", "9vm76d": " TX Orange", "9vm563": " TX Jefferson", "9vmh6k": " TX Hardin", "9vm51u": " TX Jefferson", "9vm53p": " TX Jefferson", "9vm4fy": " TX Jefferson", "9vm59s": " TX Hardin", "9vm702": " TX Orange", "9vmh38": " TX Hardin", "9vm78b": " TX Orange", "9vm4v8": " TX Orange", "9vm7gm": " TX Orange", "9vm73v": " TX Orange", "9vm16r": " TX Jefferson", "9vm4yg": " TX Orange", "9vm54g": " TX Jefferson", "9vmh30": " TX Hardin", "9vmk4k": " TX Newton", "9vm4ce": " TX Jefferson", "9vm4fq": " TX Jefferson", "9vm545": " TX Jefferson", "9vm76c": " TX Orange", "9vm4gp": " TX Jefferson", "9vmhtb": " TX Jasper", "9vm4gn": " TX Jefferson", "9vm6cr": " TX Orange", "9vm1d9": " TX Jefferson", "9vm7gp": " TX Orange", "9vm5ke": " TX Orange", "9vm770": " TX Orange", "9vm54f": " TX Jefferson", "9vm5eq": " TX Orange", "9vmk53": " TX Orange", "9vm77p": " TX Orange", "9vm5bb": " TX Hardin", "9vmh6t": " TX Jasper", "9vm4cw": " TX Jefferson", "9vm76b": " TX Orange", "9vm54x": " TX Jefferson", "9vm79t": " TX Orange", "9vm0vr": " TX Jefferson", "9vmh91": " TX Hardin", "9vm193": " TX Jefferson", "9vm56z": " TX Orange", "9vm5ft": " TX Orange", "9vm5fu": " TX Orange", "9vm5mk": " TX Orange", "9vm1yn": " TX Jefferson", "9vm4gm": " TX Jefferson", "9vmh4q": " TX Hardin", "9vm56c": " TX Jefferson", "9vm4fw": " TX Jefferson", "9vmhdm": " TX Hardin", "9vm1yh": " TX Jefferson", "9vm56d": " TX Jefferson", "9vm5x9": " TX Orange", "9vmh4p": " TX Hardin", "9vm7de": " TX Orange", "9vm773": " TX Orange", "9vm7d2": " TX Orange", "9vmh4d": " TX Jasper", "9vm5up": " TX Orange", "9vm5b8": " TX Hardin", "9vm5t1": " TX Orange", "9vm5fg": " TX Orange", "9vmk1n": " TX Newton", "9vm51v": " TX Jefferson", "9vm1mq": " TX Jefferson", "9vmh0m": " TX Hardin", "9vm4gj": " TX Jefferson", "9vm562": " TX Jefferson", "9vm550": " TX Jefferson", "9vmh40": " TX Hardin", "9vm5k8": " TX Orange", "9vm5mm": " TX Orange", "9vmk31": " TX Newton", "9vm5e7": " TX Orange", "9vm6bx": " TX Orange", "9vmh36": " TX Hardin", "9vmh3f": " TX Hardin", "9vm7b4": " TX Orange", "9vm4u2": " TX Jefferson", "9vm4u8": " TX Jefferson", "9vm139": " TX Jefferson", "9vm0yx": " TX Jefferson", "9vm547": " TX Jefferson", "9vm734": " TX Orange", "9vm1r6": " TX Jefferson", "9vm5h3": " TX Orange", "9vm7g7": " TX Orange", "9vm7gk": " TX Orange", "9vm58b": " TX Jefferson", "9vm53w": " TX Jefferson", "9vm1pc": " TX Jefferson", "9vm1m7": " TX Jefferson", "9vmhdd": " TX Hardin", "9vm6cg": " TX Orange", "9vmhph": " TX Jasper", "9vmk66": " TX Newton", "9vmhdf": " TX Jasper", "9vm4vx": " TX Orange", "9vmh28": " TX Hardin", "9vm706": " TX Orange", "9vm4fv": " TX Jefferson", "9vmpbj": " TX Tyler", "9vm1p4": " TX Jefferson", "9vm7d7": " TX Orange", "9vmh2k": " TX Hardin", "9vm758": " TX Orange", "9vmh8z": " TX Hardin", "9vm1jx": " TX Jefferson", "9vm7ed": " TX Orange", "9vm5sn": " TX Orange", "9vm5u3": " TX Orange", "9vm763": " TX Orange", "9vm569": " TX Jefferson", "9vm760": " TX Orange", "9vm0zr": " TX Jefferson", "9vm54n": " TX Jefferson", "9vmh8g": " TX Hardin", "9vm5s7": " TX Orange", "9vmh73": " TX Jasper", "9vm54b": " TX Jefferson", "9vm55v": " TX Orange", "9vm53j": " TX Jefferson", "9vm588": " TX Jefferson", "9vm57g": " TX Orange", "9vm1tb": " TX Jefferson", "9vm1pf": " TX Jefferson", "9vm1pk": " TX Jefferson", "9vm54h": " TX Jefferson", "9vm76t": " TX Orange", "9vm51j": " TX Jefferson", "9vm1kw": " TX Jefferson", "9vm1v2": " TX Jefferson", "9vm0bm": " TX Jefferson", "9vm1hd": " TX Jefferson", "9vm7e6": " TX Orange", "9vm70s": " TX Orange", "9vm5dm": " TX Hardin", "9vmh15": " TX Hardin", "9vm54m": " TX Jefferson", "9vm5vc": " TX Orange", "9vm17y": " TX Jefferson", "9vm6dr": " TX Orange", "9vm1k3": " TX Jefferson", "9vmh8u": " TX Hardin", "9vm5w0": " TX Orange", "9vm4tp": " TX Jefferson", "9vm559": " TX Jefferson", "9vm4g7": " TX Jefferson", "9vm5h5": " TX Orange", "9vm0c4": " TX Jefferson", "9vm74y": " TX Orange", "9vmhht": " TX Jasper", "9vm5jg": " TX Orange", "9vm51d": " TX Jefferson", "9vm769": " TX Orange", "9vm7g2": " TX Orange", "9vm5ef": " TX Orange", "9vm0gw": " TX Jefferson", "9vm0zz": " TX Jefferson", "9vm2b7": " TX Jefferson", "9vm5zt": " TX Orange", "9vmh4t": " TX Jasper", "9vm4yy": " TX Orange", "9vm57f": " TX Orange", "9vmh5k": " TX Jasper", "9vm4gg": " TX Jefferson", "9vmhdg": " TX Hardin", "9vm49x": " TX Jefferson", "9vm4c3": " TX Jefferson", "9vm4gu": " TX Jefferson", "9vm5z2": " TX Orange", "9vm519": " TX Jefferson", "9vm5kt": " TX Orange", "9vm5sz": " TX Orange", "9vm58z": " TX Hardin", "9vmh0u": " TX Hardin", "9vm58m": " TX Jefferson", "9vm75p": " TX Orange", "9vm5er": " TX Orange", "9vmh23": " TX Hardin", "9vmh0x": " TX Hardin", "9vm54p": " TX Jefferson", "9vm532": " TX Jefferson", "9vm7et": " TX Orange", "9vm77j": " TX Orange", "9vm2b9": " TX Jefferson", "9vm4fp": " TX Jefferson", "9vm1v6": " TX Jefferson", "9vmh4u": " TX Jasper", "9vm1nn": " TX Jefferson", "9vm79q": " TX Orange", "9vmh1m": " TX Hardin", "9vm5pq": " TX Orange", "9vmhh8": " TX Orange", "9vm5uw": " TX Orange", "9vm1k1": " TX Jefferson", "9vm12d": " TX Jefferson", "9vm165": " TX Jefferson", "9vm70u": " TX Orange", "9vm71h": " TX Orange", "9vm0g0": " TX Jefferson", "9vm5by": " TX Hardin", "9vm5bw": " TX Hardin", "9vm51x": " TX Jefferson", "9vmh2x": " TX Hardin", "9vmpsw": " TX Jasper", "9vmm1u": " TX Newton", "9vmhc4": " TX Hardin", "9vmrqg": " TX Newton", "9vmhft": " TX Jasper", "9vmjku": " TX Jasper", "9vmqk4": " TX Newton", "9vmjd2": " TX Hardin", "9vmrqx": " TX Newton", "9vmp2f": " TX Jasper", "9vmpmr": " TX Jasper", "9vmp1b": " TX Jasper", "9vmr8x": " TX Newton", "9vmnrs": " TX Jasper", "9vmj4k": " TX Hardin", "9vm4kn": " TX Jefferson", "9vmm5t": " TX Newton", "9vmp90": " TX Jasper", "9vmpgs": " TX Jasper", "9vmpfm": " TX Jasper", "9vmqsd": " TX Newton", "9vmqkn": " TX Newton", "9vmjzn": " TX Jasper", "9vmm0n": " TX Newton", "9vmmgj": " TX Newton", "9vmjhe": " TX Jasper", "9vmqfk": " TX Newton", "9vmhfm": " TX Hardin", "9vmq5s": " TX Newton", "9vmr84": " TX Newton", "9vmq3v": " TX Newton", "9vmq65": " TX Newton", "9vmq5n": " TX Newton", "9vmm3d": " TX Newton", "9vmjg1": " TX Jasper", "9vmj4w": " TX Hardin", "9vmj68": " TX Hardin", "9vm4xf": " TX Jefferson", "9vmq95": " TX Newton", "9vm4n2": " TX Jefferson", "9vmrb5": " TX Newton", "9vmj4b": " TX Jasper", "9vmpgg": " TX Jasper", "9vmjnz": " TX Jasper", "9vmm5x": " TX Newton", "9vmqvh": " TX Newton", "9vmmgp": " TX Newton", "9vmphu": " TX Jasper", "9vm495": " TX Jefferson", "9vmp1d": " TX Tyler", "9vmrh0": " TX Newton", "9vmjkk": " TX Jasper", "9vmnvy": " TX Jasper", "9vmm0j": " TX Newton", "9vmjju": " TX Jasper", "9vmj6t": " TX Hardin", "9vmjsk": " TX Jasper", "9vmjsq": " TX Jasper", "9vmnpu": " TX Newton", "9vmnps": " TX Jasper", "9vmmfn": " TX Newton", "9vmp2j": " TX Tyler", "9vmmcz": " TX Newton", "9vmpg6": " TX Jasper", "9vmrcc": " TX Newton", "9vmj90": " TX Hardin", "9vmrqv": " TX Newton", "9vm486": " TX Jefferson", "9vmqk0": " TX Newton", "9vm4nb": " TX Jefferson", "9vmr08": " TX Jasper", "9vmpru": " TX Jasper", "9vmj4c": " TX Jasper", "9vmj6r": " TX Hardin", "9vmjg3": " TX Jasper", "9vmj69": " TX Jasper", "9vmm66": " TX Newton", "9vmpve": " TX Jasper", "9vmqkt": " TX Newton", "9vmpur": " TX Jasper", "9vmncy": " TX Jasper", "9vmj8s": " TX Hardin", "9vmrsu": " TX Newton", "9vmqgd": " TX Newton", "9vmqt2": " TX Newton", "9vmnx0": " TX Jasper", "9vm4n9": " TX Jefferson", "9vmm7q": " TX Newton", "9vmj48": " TX Jasper", "9vmjwj": " TX Jasper", "9vmnnb": " TX Jasper", "9vmj1s": " TX Hardin", "9vmj1c": " TX Hardin", "9vmm5p": " TX Newton", "9vmmgn": " TX Newton", "9vmqd9": " TX Newton", "9vm62r": " TX Orange", "9vmm2k": " TX Newton", "9vmj86": " TX Hardin", "9vmqby": " TX Newton", "9vmr33": " TX Newton", "9vmrzx": " TX Newton", "9vmnzg": " TX Newton", "9vmjus": " TX Jasper", "9vmp23": " TX Tyler", "9vmrb4": " TX Jasper", "9vmjm6": " TX Jasper", "9vm1gp": " TX Jefferson", "9vmj62": " TX Hardin", "9vmput": " TX Jasper", "9vmrh5": " TX Newton", "9vm4s3": " TX Jefferson", "9vmj67": " TX Hardin", "9vmjf6": " TX Tyler", "9vmjbg": " TX Tyler", "9vmjby": " TX Tyler", "9vmq5p": " TX Newton", "9vm1fz": " TX Jefferson", "9vm4nw": " TX Jefferson", "9vmq9f": " TX Newton", "9vmpup": " TX Jasper", "9vmpuw": " TX Jasper", "9vmhfr": " TX Hardin", "9vm44r": " TX Jefferson", "9vmhbz": " TX Hardin", "9vmhv7": " TX Jasper", "9vmhcz": " TX Hardin", "9vmhfp": " TX Hardin", "9vmj2y": " TX Hardin", "9vmj6y": " TX Hardin", "9vmrv3": " TX Newton", "9vmm3b": " TX Newton", "9vm4qg": " TX Jefferson", "9vmjhf": " TX Jasper", "9vmmc1": " TX Newton", "9vmre3": " TX Newton", "9vmrg1": " TX Newton", "9vmqgm": " TX Newton", "9vmj47": " TX Hardin", "9vmqg1": " TX Newton", "9vm69s": " TX Orange", "9vm463": " TX Jefferson", "9vm465": " TX Jefferson", "9vmpz8": " TX Jasper", "9vmpm9": " TX Jasper", "9vmjg4": " TX Jasper", "9vm4nq": " TX Jefferson", "9vmmeh": " TX Newton", "9vmrb6": " TX Jasper", "9vmpzy": " TX Jasper", "9vmqej": " TX Newton", "9vmqvk": " TX Newton", "9vm683": " TX Orange", "9vmr96": " TX Newton", "9vmqv8": " TX Newton", "9vmj1q": " TX Hardin", "9vmj94": " TX Hardin", "9vmrbv": " TX Newton", "9vmpvh": " TX Jasper", "9vm43w": " TX Jefferson", "9vmn67": " TX Tyler", "9vmj4q": " TX Hardin", "9vm4q9": " TX Jefferson", "9vmrnh": " TX Newton", "9vmrnp": " TX Newton", "9vmnrm": " TX Jasper", "9vmpps": " TX Jasper", "9vm1cr": " TX Jefferson", "9vm4pm": " TX Jefferson", "9vmpdt": " TX Jasper", "9vm4ph": " TX Jefferson", "9vm4rp": " TX Jefferson", "9vmqdn": " TX Newton", "9vmrc5": " TX Newton", "9vmrgm": " TX Newton", "9vmnsd": " TX Jasper", "9vm1yw": " TX Jefferson", "9vmnbs": " TX Tyler", "9vmrcz": " TX Newton", "9vmrzh": " TX Newton", "9vm4hk": " TX Jefferson", "9vmrhy": " TX Newton", "9vmpvm": " TX Jasper", "9vm69u": " TX Orange", "9vm4kh": " TX Jefferson", "9vmq9u": " TX Newton", "9vmhfz": " TX Jasper", "9vmpu3": " TX Jasper", "9vmjqk": " TX Jasper", "9vmqfm": " TX Newton", "9vmqvz": " TX Newton", "9vm41j": " TX Jefferson", "9vm464": " TX Jefferson", "9vm43u": " TX Jefferson", "9vmq79": " TX Newton", "9vmnu7": " TX Jasper", "9vmnu6": " TX Jasper", "9vmjd6": " TX Hardin", "9vmm34": " TX Newton", "9vmpjq": " TX Jasper", "9vmp1k": " TX Tyler", "9vmpp7": " TX Jasper", "9vmn7p": " TX Jasper", "9vmjd5": " TX Hardin", "9vmn8e": " TX Tyler", "9vmrt6": " TX Newton", "9vmp25": " TX Tyler", "9vm4x3": " TX Jefferson", "9vmrkr": " TX Newton", "9vmpge": " TX Jasper", "9vmm4b": " TX Newton", "9vmn5w": " TX Jasper", "9vmhvm": " TX Jasper", "9vmnww": " TX Jasper", "9vmjj9": " TX Jasper", "9vm4t0": " TX Jefferson", "9vmpf9": " TX Jasper", "9vmr6r": " TX Newton", "9vmmf0": " TX Newton", "9vmpu5": " TX Jasper", "9vmm1c": " TX Newton", "9vmnz7": " TX Jasper", "9vmj35": " TX Hardin", "9vmj7r": " TX Jasper", "9vmn0g": " TX Tyler", "9vm686": " TX Orange", "9vmj6u": " TX Hardin", "9vmj5n": " TX Jasper", "9vmj51": " TX Jasper", "9vm4h3": " TX Jefferson", "9vmmfb": " TX Newton", "9vmp24": " TX Tyler", "9vmq67": " TX Newton", "9vmr13": " TX Newton", "9vmmek": " TX Newton", "9vmm0p": " TX Newton", "9vmrc7": " TX Newton", "9vm4ns": " TX Jefferson", "9vmm1z": " TX Newton", "9vmrq0": " TX Newton", "9vmhfy": " TX Jasper", "9vm4h5": " TX Jefferson", "9vmj6w": " TX Hardin", "9vmjdd": " TX Hardin", "9vmrjn": " TX Newton", "9vmqvs": " TX Newton", "9vmqsh": " TX Newton", "9vm1cp": " TX Jefferson", "9vmmd0": " TX Newton", "9vm459": " TX Jefferson", "9vm4rr": " TX Jefferson", "9vmnx4": " TX Jasper", "9vmpmg": " TX Jasper", "9vmppp": " TX Jasper", "9vm4n3": " TX Jefferson", "9vmhfd": " TX Hardin", "9vmp2n": " TX Tyler", "9vm4mn": " TX Jefferson", "9vmrvq": " TX Newton", "9vm4pk": " TX Jefferson", "9vm4j7": " TX Jefferson", "9vm4nv": " TX Jefferson", "9vmmf2": " TX Newton", "9vmje6": " TX Jasper", "9vmjsd": " TX Jasper", "9vmj4g": " TX Jasper", "9vmj4u": " TX Jasper", "9vmp3s": " TX Jasper", "9vmj6x": " TX Hardin", "9vmj41": " TX Hardin", "9vmhfv": " TX Jasper", "9vmj1m": " TX Hardin", "9vmqh5": " TX Newton", "9vmm6y": " TX Newton", "9vm4h8": " TX Jefferson", "9vmmup": " TX Newton", "9vmhum": " TX Jasper", "9vmm26": " TX Newton", "9vmnu4": " TX Jasper", "9vmn8g": " TX Tyler", "9vmm8g": " TX Newton", "9vmqtx": " TX Newton", "9vm4he": " TX Jefferson", "9vmhvs": " TX Jasper", "9vm68c": " TX Orange", "9vmnyr": " TX Jasper", "9vmm9g": " TX Newton", "9vmq9h": " TX Newton", "9vmrh7": " TX Newton", "9vm1uz": " TX Jefferson", "9vmp0v": " TX Tyler", "9vmp1p": " TX Sherman", "9vmpuk": " TX Jasper", "9vmpu7": " TX Jasper", "9vmq1m": " TX Newton", "9vmq1s": " TX Newton", "9vmp03": " TX Tyler", "9vmn4b": " TX Tyler", "9vm4nx": " TX Jefferson", "9vmrky": " TX Newton", "9vmre7": " TX Newton", "9vmrts": " TX Newton", "9vmjch": " TX Tyler", "9vm470": " TX Jefferson", "9vmns6": " TX Jasper", "9vmp1g": " TX Jasper", "9vmj6e": " TX Hardin", "9vmq90": " TX Newton", "9vmrj5": " TX Newton", "9vm4pr": " TX Jefferson", "9vm4qe": " TX Jefferson", "9vm69e": " TX Orange", "9vmj07": " TX Hardin", "9vm4j1": " TX Jefferson", "9vmj4r": " TX Hardin", "9vmq98": " TX Newton", "9vmq2u": " TX Newton", "9vmqse": " TX Newton", "9vmr11": " TX Newton", "9vmqd1": " TX Newton", "9vm4kz": " TX Jefferson", "9vm4tu": " TX Jefferson", "9vmr8b": " TX Newton", "9vmkf4": " TX Newton", "9vmjem": " TX Tyler", "9vmpmt": " TX Jasper", "9vm43s": " TX Jefferson", "9vm1bs": " TX Jefferson", "9vm43g": " TX Jefferson", "9vm1u6": " TX Jefferson", "9vm1sm": " TX Jefferson", "9vm1us": " TX Jefferson", "9vm4ws": " TX Orange", "9vmkce": " TX Newton", "9vm4ty": " TX Jefferson", "9vm1be": " TX Jefferson", "9vmqv9": " TX Newton", "9vm4ss": " TX Jefferson", "9vm5dh": " TX Hardin", "9vmkd6": " TX Newton", "9vm1gw": " TX Jefferson", "9vmq1p": " TX Newton", "9vmq2c": " TX Newton", "9vm56s": " TX Jefferson", "9vmrwt": " TX Newton", "9vmhnq": " TX Jasper", "9vm453": " TX Jefferson", "9vmhzb": " TX Newton", "9vm46g": " TX Jefferson", "9vm425": " TX Jefferson", "9vm77t": " TX Orange", "9vmk8y": " TX Newton", "9vmh85": " TX Hardin", "9vmhej": " TX Jasper", "9vm1bd": " TX Jefferson", "9vm4tv": " TX Jefferson", "9vm687": " TX Orange", "9vm5d6": " TX Hardin", "9vm4tg": " TX Jefferson", "9vmhzg": " TX Newton", "9vmm7e": " TX Newton", "9vm4sg": " TX Jefferson", "9vm4eq": " TX Jefferson", "9vm59h": " TX Hardin", "9vm1tv": " TX Jefferson", "9vmh43": " TX Hardin", "9vm5g5": " TX Orange", "9vmhv2": " TX Jasper", "9vmh4g": " TX Jasper", "9vm4d5": " TX Jefferson", "9vmh2w": " TX Hardin", "9vmh6m": " TX Hardin", "9vmh9f": " TX Hardin", "9vmjr1": " TX Jasper", "9vm0dw": " TX Jefferson", "9vm0uq": " TX Jefferson", "9vm1m2": " TX Jefferson", "9vm10z": " TX Jefferson", "9vm4yv": " TX Orange", "9vm5jp": " TX Orange", "9vm78p": " TX Orange", "9vm5w4": " TX Orange", "9vm4u0": " TX Jefferson", "9vm74j": " TX Orange", "9vmhpp": " TX Jasper", "9vm4em": " TX Jefferson", "9vm4g0": " TX Jefferson", "9vm53s": " TX Jefferson", "9vm7bk": " TX Orange", "9vm5pr": " TX Orange", "9vm73n": " TX Orange", "9vm7f9": " TX Orange", "9vmhr4": " TX Jasper", "9vm57b": " TX Orange", "9vmk5p": " TX Newton", "9vmh2g": " TX Hardin", "9vm5rv": " TX Orange", "9vmheq": " TX Jasper", "9vm5nx": " TX Orange", "9vm70w": " TX Orange", "9vm4gk": " TX Jefferson", "9vmq2d": " TX Newton", "9vm4x9": " TX Jefferson", "9vmnxx": " TX Jasper", "9vmhym": " TX Jasper", "9vmnnc": " TX Jasper", "9vmpgt": " TX Jasper", "9vmnvq": " TX Jasper", "9vmpj5": " TX Jasper", "9vmqg9": " TX Newton", "9vmjwd": " TX Jasper", "9vmppg": " TX Jasper", "9vm480": " TX Jefferson", "9vmj42": " TX Hardin", "9vmq2y": " TX Newton", "9vm4ed": " TX Jefferson", "9vmqcv": " TX Newton", "9vmpzx": " TX Jasper", "9vmnrr": " TX Jasper", "9vmpwe": " TX Jasper", "9vmjwt": " TX Jasper", "9vmnsk": " TX Jasper", "9vmhu5": " TX Jasper", "9vmrvd": " TX Newton", "9vm4kj": " TX Jefferson", "9vm1hh": " TX Jefferson", "9vm0ur": " TX Jefferson", "9vm0bg": " TX Jefferson", "9vm0bv": " TX Jefferson", "9vm0dz": " TX Jefferson", "9vm0bd": " TX Jefferson", "9vm2br": " TX Jefferson", "9vm2bb": " TX Jefferson", "9vm294": " TX Jefferson", "9vm4ug": " TX Orange", "9vm4x5": " TX Orange", "9vmp7p": " TX Jasper", "9vmpbt": " TX Jasper", "9vmpd1": " TX Jasper", "9vmpct": " TX Jasper", "9vmpcm": " TX Jasper", "9vmpbr": " TX Jasper", "9vmpby": " TX Jasper", "9vmnfz": " TX Jasper", "9vmpc7": " TX Jasper", "9vmpfj": " TX Jasper", "9vmpfp": " TX Jasper", "9vmpf5": " TX Jasper", "9vmpe4": " TX Jasper", "9vmpk9": " TX Jasper", "9vmpcn": " TX Jasper", "9vmp6e": " TX Jasper", "9vmpb4": " TX Jasper", "9vmpc1": " TX Jasper", "9vmp6r": " TX Jasper", "9vmpb8": " TX Jasper", "9vmpbq": " TX Tyler", "9vmph4": " TX Jasper", "9vmpc5": " TX Jasper", "9vmp9q": " TX Jasper", "9vmp6s": " TX Jasper", "9vmped": " TX Jasper", "9vmpbc": " TX Jasper", "9vmpbf": " TX Jasper", "9vmp4q": " TX Jasper", "9vmp4d": " TX Jasper", "9vmp46": " TX Jasper", "9vmp6z": " TX Jasper", "9vmphy": " TX Jasper", "9vmp9h": " TX Jasper", "9vmps9": " TX Jasper", "9vmnem": " TX Jasper", "9vmpb9": " TX Jasper", "9vmpb2": " TX Jasper", "9vmp9z": " TX Jasper", "9vmnuk": " TX Jasper", "9vm1c6": " TX Jefferson", "9vmr4u": " TX Newton", "9vm5r7": " TX Orange", "9vmhyq": " TX Jasper", "9vmjpy": " TX Newton", "9vm1pu": " TX Jefferson", "9vm4nt": " TX Jefferson", "9vm1yr": " TX Jefferson", "9vm4ng": " TX Jefferson", "9vm1yx": " TX Jefferson", "9vm4w5": " TX Jefferson", "9vm4tc": " TX Jefferson", "9vm4pn": " TX Jefferson", "9vm4q8": " TX Jefferson", "9vm4m6": " TX Jefferson", "9vm4q0": " TX Jefferson", "9vm4qd": " TX Jefferson", "9vm4rn": " TX Jefferson", "9vm4nc": " TX Jefferson", "9vm4p7": " TX Jefferson", "9vm0zq": " TX Jefferson", "9vm1yj": " TX Jefferson", "9vm1ys": " TX Jefferson", "9vm1y3": " TX Jefferson", "9vm1tr": " TX Jefferson", "9vm1vk": " TX Jefferson", "9vm4wh": " TX Jefferson", "9vm4w8": " TX Jefferson", "9vm4m5": " TX Jefferson", "9vm4nn": " TX Jefferson", "9vm4rs": " TX Jefferson", "9vm1yq": " TX Jefferson", "9vm4ne": " TX Jefferson", "9vm4mh": " TX Jefferson", "9vm4js": " TX Jefferson", "9vm4mm": " TX Jefferson", "9vm4mc": " TX Jefferson", "9vm4r7": " TX Jefferson", "9vm4nr": " TX Jefferson", "9vm4w4": " TX Jefferson", "9vm4mv": " TX Jefferson", "9vm4q3": " TX Jefferson", "9vm4me": " TX Jefferson", "9vm4mu": " TX Jefferson", "9vm4t3": " TX Jefferson", "9vm4mj": " TX Jefferson", "9vm4t1": " TX Jefferson", "9vm4nu": " TX Jefferson", "9vm4nz": " TX Jefferson", "9vm4qt": " TX Jefferson", "9vm4qu": " TX Jefferson", "9vm4r0": " TX Jefferson", "9vm4nd": " TX Jefferson", "9vm4p4": " TX Jefferson", "9vm1q1": " TX Jefferson", "9vmh01": " TX Hardin", "9vmhhn": " TX Jasper", "9vm50t": " TX Jefferson", "9vm766": " TX Orange", "9vm43r": " TX Jefferson", "9vmr5w": " TX Newton", "9vmm0h": " TX Newton", "9vmrux": " TX Newton", "9vmnsp": " TX Jasper", "9vmpyh": " TX Jasper", "9vm1cy": " TX Jefferson", "9vmpsp": " TX Jasper", "9vm1nc": " TX Jefferson", "9vm4sk": " TX Jefferson", "9vm53z": " TX Jefferson", "9vm590": " TX Jefferson", "9vm52x": " TX Jefferson", "9vm53n": " TX Jefferson", "9vm589": " TX Jefferson", "9vm52z": " TX Jefferson", "9vm5g6": " TX Orange", "9vm5ez": " TX Orange", "9vm5s2": " TX Orange", "9vm507": " TX Jefferson", "9vm51n": " TX Jefferson", "9vm53b": " TX Jefferson", "9vm51r": " TX Jefferson", "9vm46s": " TX Jefferson", "9vm55x": " TX Orange", "9vm4g5": " TX Jefferson", "9vm51f": " TX Jefferson", "9vm51y": " TX Jefferson", "9vm548": " TX Jefferson", "9vm54d": " TX Jefferson", "9vm54u": " TX Jefferson", "9vm54w": " TX Jefferson", "9vm56e": " TX Jefferson", "9vm50v": " TX Jefferson", "9vm537": " TX Jefferson", "9vm53e": " TX Jefferson", "9vm50f": " TX Jefferson", "9vm53u": " TX Jefferson", "9vm52v": " TX Jefferson", "9vm58u": " TX Jefferson", "9vm4fz": " TX Jefferson", "9vm4ge": " TX Jefferson", "9vm5bt": " TX Hardin", "9vm4zv": " TX Orange", "9vm504": " TX Jefferson", "9vm541": " TX Jefferson", "9vm4fh": " TX Jefferson", "9vm4km": " TX Jefferson", "9vmhe0": " TX Jasper", "9vm40j": " TX Jefferson", "9vm082": " TX Jefferson", "9vmnqf": " TX Jasper", "9vmrdy": " TX Newton", "9vm71d": " TX Orange", "9vm700": " TX Orange", "9vm4pw": " TX Jefferson", "9vm4qw": " TX Jefferson", "9vm0vt": " TX Jefferson", "9vm0yq": " TX Jefferson", "9vm0vy": " TX Jefferson", "9vm301": " TX Jefferson", "9vm2bn": " TX Jefferson", "9vm5qm": " TX Orange", "9vm59b": " TX Jefferson", "9vmpvs": " TX Jasper", "9vm5j2": " TX Orange", "9vm76w": " TX Orange", "9vm4n7": " TX Jefferson", "9vm5n5": " TX Orange", "9vm5qj": " TX Orange", "9vm796": " TX Orange", "9vm57c": " TX Orange", "9vm5kf": " TX Orange", "9vm4zd": " TX Orange", "9vm5t6": " TX Orange", "9vm72t": " TX Orange", "9vm5mq": " TX Orange", "9vm5z8": " TX Orange", "9vm5xj": " TX Orange", "9vm5b9": " TX Hardin", "9vmeyw": " LA Calcasieu", "9vmeye": " LA Calcasieu", "9vmcjz": " LA Cameron", "9vmdz2": " LA Cameron", "9vmsj4": " LA Calcasieu", "9vm3kf": " LA Cameron", "9vmwyh": " LA Beauregard", "9vmtkz": " LA Beauregard", "9vmvrn": " LA Allen", "9vmzr3": " LA Allen", "9vmytv": " LA Allen", "9vmuj2": " LA Jefferson Davis", "9vm7qq": " LA Calcasieu", "9vmgm8": " LA Calcasieu", "9vmg3e": " LA Calcasieu", "9vms5c": " LA Calcasieu", "9vmkqd": " LA Calcasieu", "9vmshf": " LA Calcasieu", "9vmsph": " LA Calcasieu", "9vm9s1": " LA Cameron", "9vm9qv": " LA Cameron", "9vm9ky": " LA Cameron", "9vm9gk": " LA Cameron", "9vm9kq": " LA Cameron", "9vm9eu": " LA Cameron", "9vm9kv": " LA Cameron", "9vm9kj": " LA Cameron", "9vmt1h": " LA Calcasieu", "9vmxkh": " LA Beauregard", "9vmxj9": " LA Beauregard", "9vmy67": " LA Beauregard", "9vmc76": " LA Cameron", "9vmckd": " LA Cameron", "9vmddw": " LA Cameron", "9vmfze": " LA Cameron", "9vm3kc": " LA Cameron", "9vmggy": " LA Calcasieu", "9vm3s7": " LA Cameron", "9vmvns": " LA Jefferson Davis", "9vmeqe": " LA Calcasieu", "9vmgbh": " LA Calcasieu", "9vmgby": " LA Calcasieu", "9vmg3y": " LA Calcasieu", "9vmety": " LA Calcasieu", "9vmezn": " LA Calcasieu", "9vmeqf": " LA Calcasieu", "9vmerw": " LA Calcasieu", "9vmeq5": " LA Calcasieu", "9vmeqw": " LA Calcasieu", "9vmgfp": " LA Calcasieu", "9vmu0e": " LA Calcasieu", "9vmtqs": " LA Beauregard", "9vmkmy": " LA Calcasieu", "9vms46": " LA Calcasieu", "9vme7j": " LA Calcasieu", "9vmgpd": " LA Jefferson Davis", "9vmup9": " LA Jefferson Davis", "9vmshw": " LA Calcasieu", "9vmvtd": " LA Allen", "9vmxtj": " LA Beauregard", "9vmxv8": " LA Vernon", "9vmv4h": " LA Allen", "9vmu4q": " LA Calcasieu", "9vmugw": " LA Jefferson Davis", "9vmugt": " LA Jefferson Davis", "9vm4g3": " TX Jefferson", "9vmpf3": " TX Jasper", "9vmp15": " TX Tyler", "9vm6fz": " TX Orange", "9vm6fw": " TX Orange", "9vm7fy": " TX Orange", "9vm7fv": " TX Orange", "9vmqsz": " TX Newton", "9vmr1t": " TX Newton", "9vmr1m": " TX Newton", "9vmr2j": " TX Newton", "9vmr24": " TX Newton", "9vmr26": " TX Newton", "9vmr27": " TX Newton", "9vmr21": " TX Newton", "9vmnsn": " TX Jasper", "9vmjy2": " TX Jasper", "9vmr5d": " TX Newton", "9vmpt9": " TX Jasper", "9vmjmz": " TX Jasper", "9vmn14": " TX Tyler", "9vm5f6": " TX Hardin", "9vmmzg": " LA Beauregard", "9vmswg": " LA Calcasieu", "9vm3sv": " LA Cameron", "9vmgdk": " LA Calcasieu", "9vmuv0": " LA Jefferson Davis", "9vmkxf": " LA Calcasieu", "9vm7rv": " LA Calcasieu", "9vmefx": " LA Calcasieu", "9vmgtf": " LA Jefferson Davis", "9vmsk8": " LA Calcasieu", "9vmeue": " LA Calcasieu", "9vmx00": " LA Beauregard", "9vmd92": " LA Cameron", "9vmsne": " LA Calcasieu", "9vmfdg": " LA Cameron", "9vmxwe": " LA Beauregard", "9vmxqt": " LA Beauregard", "9vmxhw": " LA Beauregard", "9vmx7e": " LA Beauregard", "9vmywq": " LA Allen", "9vmgbt": " LA Calcasieu", "9vmtmy": " LA Beauregard", "9vmww6": " LA Beauregard", "9vmyfh": " LA Beauregard", "9vmc8e": " LA Cameron", "9vmew0": " LA Calcasieu", "9vm9ug": " LA Cameron", "9vmve6": " LA Allen", "9vmeqb": " LA Calcasieu", "9vmxyh": " LA Vernon", "9vmemk": " LA Calcasieu", "9vmg8j": " LA Calcasieu", "9vm4z9": " TX Orange", "9vmhvp": " TX Jasper", "9vmmc9": " TX Newton", "9vm5bz": " TX Hardin", "9vmk90": " TX Newton", "9vm4mf": " TX Jefferson", "9vmntn": " TX Jasper", "9vm41q": " TX Jefferson", "9vm79p": " TX Orange", "9vmr74": " TX Newton", "9vm141": " TX Jefferson", "9vmhcp": " TX Hardin", "9vmn81": " TX Tyler", "9vm5sf": " TX Orange", "9vmjrg": " TX Newton", "9vmh0p": " TX Hardin", "9vmh8y": " TX Hardin", "9vmh8s": " TX Hardin", "9vmh08": " TX Hardin", "9vmh07": " TX Hardin", "9vmh0e": " TX Hardin", "9vmh9e": " TX Hardin", "9vmpuv": " TX Jasper", "9vm4mz": " TX Jefferson", "9vm4fx": " TX Jefferson", "9vmnr6": " TX Jasper", "9vmnr7": " TX Jasper", "9vmnr3": " TX Jasper", "9vm594": " TX Jefferson", "9vm56k": " TX Jefferson", "9vm4sd": " TX Jefferson", "9vm50k": " TX Jefferson", "9vm6bu": " TX Orange", "9vm6b7": " TX Orange", "9vm76r": " TX Orange", "9vm7ds": " TX Orange", "9vm5mp": " TX Orange", "9vm747": " TX Orange", "9vm5sq": " TX Orange", "9vm6bc": " TX Orange", "9vm5kg": " TX Orange", "9vm5ky": " TX Orange", "9vm5mr": " TX Orange", "9vm74s": " TX Orange", "9vmcbs": " LA Cameron", "9vm9rf": " LA Cameron", "9vmr6q": " TX Newton", "9vm54q": " TX Jefferson", "9vm432": " TX Jefferson", "9vm01j": " TX Cass", "9vm74r": " TX Orange", "9vmpuf": " TX Jasper", "9vm546": " TX Jefferson", "9vmh8q": " TX Hardin", "9vmh2z": " TX Hardin", "9vmh8w": " TX Hardin", "9vmh9j": " TX Hardin", "9vm5bd": " TX Hardin", "9vm1yp": " TX Jefferson", "9vm4fn": " TX Jefferson", "9vm567": " TX Jefferson", "9vm560": " TX Jefferson", "9vm4j4": " TX Jefferson", "9vm4n8": " TX Jefferson", "9vm4tf": " TX Jefferson", "9vm542": " TX Jefferson", "9vm50s": " TX Jefferson", "9vm4q7": " TX Jefferson", "9vm1ux": " TX Jefferson", "9vm4nm": " TX Jefferson", "9vm4j6": " TX Jefferson", "9vm483": " TX Jefferson", "9vm4dv": " TX Jefferson", "9vm4pj": " TX Jefferson", "9vm4hx": " TX Jefferson", "9vm53k": " TX Jefferson", "9vm4mx": " TX Jefferson", "9vm4hw": " TX Jefferson", "9vm561": " TX Jefferson", "9vm568": " TX Jefferson", "9vm4nj": " TX Jefferson", "9vm4jd": " TX Jefferson", "9vm4cy": " TX Jefferson", "9vm531": " TX Jefferson", "9vm4q2": " TX Jefferson", "9vm534": " TX Jefferson", "9vm4mp": " TX Jefferson", "9vmpvn": " TX Jasper", "9vmpvr": " TX Jasper", "9vmpvp": " TX Jasper", "9vmpvj": " TX Jasper", "9vmnrn": " TX Jasper", "9vmnrj": " TX Jasper", "9vmpug": " TX Jasper", "9vmpuz": " TX Jasper", "9vm4pq": " TX Jefferson", "9vm509": " TX Jefferson", "9vm4h7": " TX Jefferson", "9vm4td": " TX Jefferson", "9vm51e": " TX Jefferson", "9vm543": " TX Jefferson", "9vm4nf": " TX Jefferson", "9vm4bt": " TX Jefferson", "9vm1vy": " TX Jefferson", "9vm4bx": " TX Jefferson", "9vm4pp": " TX Jefferson", "9vm4hb": " TX Jefferson", "9vm50c": " TX Jefferson", "9vm1ym": " TX Jefferson", "9vm58s": " TX Jefferson", "9vm53g": " TX Jefferson", "9vm5k7": " TX Orange", "9vm6b5": " TX Orange", "9vm5mn": " TX Orange", "9vm5ks": " TX Orange", "9vm5u8": " TX Orange", "9vm5sd": " TX Orange", "9vm5kr": " TX Orange", "9vm7bm": " TX Orange", "9vm5s9": " TX Orange", "9vm5t2": " TX Orange", "9vm6bg": " TX Orange", "9vm76s": " TX Orange", "9vm5kz": " TX Orange", "9vm76z": " TX Orange", "9vm5mj": " TX Orange", "9vm6b9": " TX Orange", "9vmpu9": " TX Jasper", "9vm4qf": " TX Jefferson", "9vm4h1": " TX Jefferson", "9vmpuu": " TX Jasper", "9vm1gf": " TX Jefferson", "9vm74w": " TX Orange", "9vm56h": " TX Jefferson", "9vm511": " TX Jefferson", "9vm76e": " TX Orange", "9vm6gp": " TX Orange", "9vm4ye": " TX Orange", "9vm68w": " TX Orange", "9vmp8g": " TX Jasper", "9vm761": " TX Orange", "9vmh17": " TX Hardin", "9vm1yt": " TX Jefferson", "9vm4xc": " TX Jefferson", "9vm74c": " TX Orange", "9vm54y": " TX Jefferson", "9vm54k": " TX Jefferson", "9vm539": " TX Jefferson", "9vmpcx": " TX Jasper", "9vmp82": " TX Jasper", "9vmmfd": " TX Newton", "9vmpnz": " TX Jasper", "9vmq2f": " TX Newton", "9vm0v5": " TX Jefferson", "9vmp8f": " TX Jasper", "9vmreq": " TX Newton", "9vmp0u": " TX Tyler", "9vmpd7": " TX Jasper", "9vmfq0": " LA Cameron", "9vmjdw": " TX Tyler", "9vmjd9": " TX Hardin", "9vm1cu": " TX Jefferson", "9vmdwk": " LA Cameron", "9vmexy": " LA Calcasieu", "9vm51g": " TX Jefferson", "9vmc3q": " LA Cameron", "9vmcmb": " LA Cameron", "9vmc6m": " LA Cameron", "9vmcev": " LA Cameron", "9vmde7": " LA Cameron", "9vm37g": " LA Cameron", "9vm7wx": " LA Calcasieu", "9vmg2n": " LA Calcasieu", "9vm935": " LA Cameron", "9vmenc": " LA Calcasieu", "9vmc97": " LA Cameron", "9vmspz": " LA Calcasieu", "9vmgm1": " LA Calcasieu", "9vmedu": " LA Calcasieu", "9vmt3u": " LA Calcasieu", "9vmewv": " LA Calcasieu", "9vmgb7": " LA Calcasieu", "9vms41": " LA Calcasieu", "9vmdek": " LA Cameron", "9vmtwy": " LA Beauregard", "9vmeqv": " LA Calcasieu", "9vmgbw": " LA Calcasieu", "9vmgbx": " LA Calcasieu", "9vm36x": " LA Cameron", "9vmfb0": " LA Cameron", "9vm9qz": " LA Cameron", "9vmggr": " LA Calcasieu", "9vmdyy": " LA Cameron", "9vmgbn": " LA Calcasieu", "9vmk40": " TX Orange", "9vm7b0": " TX Orange", "9vm6bd": " TX Orange", "9vmheh": " TX Jasper", "9vm735": " TX Orange", "9vm7dm": " TX Orange", "9vmh03": " TX Hardin", "9vmjbv": " TX Tyler", "9vmh9n": " TX Hardin", "9vmjmc": " TX Jasper", "9vm5kv": " TX Orange", "9vm5zf": " TX Orange", "9vm5ku": " TX Orange", "9vmdd8": " LA Cameron", "9vm9mn": " LA Cameron", "9vmeem": " LA Calcasieu", "9vmetb": " LA Calcasieu", "9vmqzz": " LA Beauregard", "9vmxvh": " LA Vernon", "9vmvdu": " LA Allen", "9vmjjy": " TX Jasper", "9vm4s7": " TX Jefferson", "9vmhed": " TX Jasper", "9vm5zv": " TX Orange", "9vmk6k": " TX Newton", "9vm51s": " TX Jefferson", "9vm6be": " TX Orange", "9vmh0k": " TX Hardin", "9vmrd8": " TX Newton", "9vm5sj": " TX Orange", "9vm0zk": " TX Jefferson", "9vm5mh": " TX Orange", "9vmet9": " LA Calcasieu", "9vmg2p": " LA Calcasieu", "9vmsqg": " LA Calcasieu", "9vmygh": " LA Beauregard", "9vmt9b": " LA Beauregard", "9vmetf": " LA Calcasieu", "9vmc7s": " LA Cameron", "9vmtnx": " LA Beauregard", "9vmgm3": " LA Calcasieu", "9vmgvx": " LA Jefferson Davis", "9vmwns": " LA Beauregard", "9vmt9t": " LA Beauregard", "9vmzvr": " LA Vernon", "9vmw67": " LA Beauregard", "9vmkkt": " LA Calcasieu", "9vmewh": " LA Calcasieu", "9vmxkx": " LA Beauregard", "9vmezv": " LA Calcasieu", "9vmequ": " LA Calcasieu", "9vmxw9": " LA Beauregard", "9vmegz": " LA Calcasieu", "9vmeg8": " LA Calcasieu", "9vmspt": " LA Calcasieu", "9vmerv": " LA Calcasieu", "9vmet6": " LA Calcasieu", "9vms4b": " LA Calcasieu", "9vm7y7": " LA Calcasieu", "9vmvxy": " LA Allen", "9vmeny": " LA Calcasieu", "9vmx7y": " LA Beauregard", "9vmu1f": " LA Calcasieu", "9vmu10": " LA Calcasieu", "9vmetg": " LA Calcasieu", "9vmu60": " LA Calcasieu", "9vmegm": " LA Calcasieu", "9vmt3b": " LA Calcasieu", "9vmskn": " LA Calcasieu", "9vmxs8": " LA Beauregard", "9vmrp3": " LA Beauregard", "9vmt1v": " LA Calcasieu", "9vmgbg": " LA Calcasieu", "9vmsmb": " LA Calcasieu", "9vmsw7": " LA Calcasieu", "9vmwwk": " LA Beauregard", "9vmex9": " LA Calcasieu", "9vmgcp": " LA Calcasieu", "9vmsqk": " LA Calcasieu", "9vmerq": " LA Calcasieu", "9vmeqp": " LA Calcasieu", "9vmew5": " LA Calcasieu", "9vmexu": " LA Calcasieu", "9vmeep": " LA Calcasieu", "9vmexe": " LA Calcasieu", "9vmeff": " LA Calcasieu", "9vmvrp": " LA Allen", "9vmeqn": " LA Calcasieu", "9vmeyj": " LA Calcasieu", "9vmevf": " LA Calcasieu", "9vmekz": " LA Calcasieu", "9vmexm": " LA Calcasieu", "9vmwy6": " LA Beauregard", "9vmu3c": " LA Calcasieu", "9vmkkx": " LA Calcasieu", "9vmxw3": " LA Beauregard", "9vmemy": " LA Calcasieu", "9vms56": " LA Calcasieu", "9vmy69": " LA Beauregard", "9vmex8": " LA Calcasieu", "9vmxmh": " LA Beauregard", "9vm7sb": " LA Calcasieu", "9vmxg2": " LA Vernon", "9vmxt2": " LA Beauregard", "9vmeg7": " LA Calcasieu", "9vmrpt": " LA Beauregard", "9vmvrm": " LA Allen", "9vmeg5": " LA Calcasieu", "9vmxkn": " LA Beauregard", "9vmsrm": " LA Calcasieu", "9vmqzr": " LA Beauregard", "9vmgzy": " LA Jefferson Davis", "9vmdes": " LA Cameron", "9vmegt": " LA Calcasieu", "9vmewk": " LA Calcasieu", "9vmxkr": " LA Beauregard", "9vmdwz": " LA Cameron", "9vmt35": " LA Calcasieu", "9vmxb8": " LA Vernon", "9vm7y9": " LA Calcasieu", "9vmezz": " LA Calcasieu", "9vmsxp": " LA Calcasieu", "9vmup8": " LA Jefferson Davis", "9vmxkz": " LA Beauregard", "9vmsw6": " LA Calcasieu", "9vmt1w": " LA Calcasieu", "9vmu02": " LA Calcasieu", "9vms55": " LA Calcasieu", "9vm7ye": " LA Calcasieu", "9vmsq0": " LA Calcasieu", "9vmgt6": " LA Jefferson Davis", "9vmeej": " LA Calcasieu", "9vms58": " LA Calcasieu", "9vmsrb": " LA Calcasieu", "9vmvqc": " LA Allen", "9vmxtk": " LA Beauregard", "9vmsh6": " LA Calcasieu", "9vmtnq": " LA Beauregard", "9vmsqm": " LA Calcasieu", "9vmtym": " LA Beauregard", "9vmt3c": " LA Calcasieu", "9vmsfm": " LA Calcasieu", "9vmezt": " LA Calcasieu", "9vmew1": " LA Calcasieu", "9vmedv": " LA Calcasieu", "9vmxq5": " LA Beauregard", "9vmez2": " LA Calcasieu", "9vmyd8": " LA Beauregard", "9vmeg4": " LA Calcasieu", "9vmsx2": " LA Calcasieu", "9vmz7t": " LA Beauregard", "9vmuby": " LA Jefferson Davis", "9vmsxj": " LA Calcasieu", "9vmrp2": " LA Beauregard", "9vmdyz": " LA Calcasieu", "9vmupc": " LA Jefferson Davis", "9vmstb": " LA Calcasieu", "9vmg81": " LA Calcasieu", "9vmew9": " LA Calcasieu", "9vmu50": " LA Calcasieu", "9vmz53": " LA Beauregard", "9vmgke": " LA Calcasieu", "9vmqzx": " LA Beauregard", "9vmxjk": " LA Beauregard", "9vms5b": " LA Calcasieu", "9vmsn9": " LA Calcasieu", "9vmqzh": " LA Beauregard", "9vmeu2": " LA Calcasieu", "9vm7yb": " LA Calcasieu", "9vmgzw": " LA Jefferson Davis", "9vmpud": " TX Jasper", "9vmr6x": " TX Newton", "9vmpu0": " TX Jasper", "9vm4nk": " TX Jefferson", "9vm4hd": " TX Jefferson", "9vmqus": " TX Newton", "9vm5sr": " TX Orange", "9vm76x": " TX Orange", "9vmk3b": " TX Newton", "9vmk6s": " TX Newton", "9vmm16": " TX Newton", "9vmpv5": " TX Jasper", "9vmnqd": " TX Jasper", "9vmhyk": " TX Jasper", "9vm707": " TX Orange", "9vm50y": " TX Jefferson", "9vm58c": " TX Jefferson", "9vm4cz": " TX Jefferson", "9vm4ch": " TX Jefferson", "9vmxv7": " LA Vernon", "9vmxf4": " LA Vernon", "9vmum1": " LA Jefferson Davis", "9vms5w": " LA Calcasieu", "9vmuh6": " LA Jefferson Davis", "9vmu8x": " LA Calcasieu", "9vmstc": " LA Calcasieu", "9vmsws": " LA Calcasieu", "9vmv0b": " LA Jefferson Davis", "9vmyt2": " LA Allen", "9vmx2n": " LA Beauregard", "9vmxwb": " LA Beauregard", "9vmw6m": " LA Beauregard", "9vmeun": " LA Calcasieu", "9vmz5r": " LA Beauregard", "9vmud1": " LA Calcasieu", "9vms71": " LA Calcasieu", "9vmezd": " LA Calcasieu", "9vmsf7": " LA Calcasieu", "9vmx44": " LA Beauregard", "9vmgre": " LA Jefferson Davis", "9vmwy2": " LA Beauregard", "9vmz1p": " LA Beauregard", "9vmv22": " LA Beauregard", "9vmz82": " LA Beauregard", "9vm5nm": " TX Orange", "9vmg2q": " LA Calcasieu", "9vmfcq": " LA Calcasieu", "9vm4m1": " TX Jefferson", "9vm51b": " TX Jefferson", "9vmnx3": " TX Jasper", "9vm74p": " TX Orange", "9vmk6e": " TX Newton", "9vmhc5": " TX Hardin", "9vmh90": " TX Hardin", "9vm4f7": " TX Jefferson", "9vmnpy": " TX Newton", "9vmjjt": " TX Jasper", "9vm5zg": " TX Orange", "9vmpy5": " TX Jasper", "9vm4eu": " TX Jefferson", "9vm4sh": " TX Jefferson", "9vm4eg": " TX Jefferson", "9vm4ev": " TX Jefferson", "9vm47n": " TX Jefferson", "9vm4kw": " TX Jefferson", "9vmrd2": " TX Newton", "9vm71u": " TX Orange", "9vmre4": " TX Newton", "9vm5kx": " TX Orange"}