{"9wbk8q": " UT Millard", "9wb9mn": " UT Wayne", "9wb8cg": " UT Garfield", "9wb13e": " UT Beaver", "9wbgzp": " UT Emery", "9wb2zb": " UT Garfield", "9wbncw": " UT Millard", "9wb9m1": " UT Wayne", "9wb9mj": " UT Wayne", "9wbbey": " UT Garfield", "9wbbu2": " UT Garfield", "9wbrqv": " UT Sanpete", "9wbqpk": " UT Sanpete", "9wb9m9": " UT Wayne", "9wb8ye": " UT Garfield", "9wbmuh": " UT Sevier", "9wbn68": " UT Millard", "9wb8k1": " UT Garfield", "9wb8m5": " UT Garfield", "9wbpus": " UT Millard", "9wb0fr": " UT Garfield", "9wb8q6": " UT Garfield", "9wby0k": " UT Sanpete", "9wb0dt": " UT Garfield", "9wb9cd": " UT Wayne", "9wbr3y": " UT Millard", "9wbbe6": " UT Garfield", "9wb8ur": " UT Garfield", "9wb6sq": " UT Piute", "9wb13j": " UT Beaver", "9wb182": " UT Beaver", "9wbg66": " UT Sevier", "9wbsh9": " UT Sevier", "9wbwpf": " UT Sanpete", "9wb8jt": " UT Garfield", "9wbfzd": " UT Wayne", "9wbtyv": " UT Sevier", "9wbyxq": " UT Emery", "9wbwr0": " UT Sanpete", "9wbumj": " UT Emery", "9wbu5d": " UT Emery", "9wbb75": " UT Garfield", "9wb8tj": " UT Garfield", "9wbpmj": " UT Millard", "9wb8kf": " UT Garfield", "9wbbd6": " UT Garfield", "9wbb6n": " UT Garfield", "9wbbgc": " UT Garfield", "9wb09n": " UT Garfield", "9wb1d9": " UT Beaver", "9wb8wt": " UT Garfield", "9wb6kz": " UT Piute", "9wby20": " UT Sanpete", "9wb13v": " UT Beaver", "9wb13z": " UT Beaver", "9wb10r": " UT Beaver", "9wbzpg": " UT Emery", "9wb9fq": " UT Wayne", "9wbfvf": " UT Wayne", "9wbpvr": " UT Millard", "9wburv": " UT Emery", "9wbbrd": " UT Garfield", "9wbn5f": " UT Millard", "9wbgxs": " UT Emery", "9wbrv9": " UT Sanpete", "9wbqx6": " UT Sanpete", "9wbw8x": " UT Sanpete", "9wb3y6": " UT Piute", "9wbc4f": " UT Wayne", "9wb119": " UT Beaver", "9wbbfn": " UT Garfield", "9wbr71": " UT Millard", "9wb161": " UT Piute", "9wbxdb": " UT Sanpete", "9wbw8p": " UT Sanpete", "9wbyxg": " UT Emery", "9wbu1f": " UT Sevier", "9wbsn6": " UT Sevier", "9wbcuf": " UT Wayne", "9wbb7r": " UT Garfield", "9wbb7n": " UT Garfield", "9wb9jv": " UT Wayne", "9wb9jz": " UT Wayne", "9wb0cw": " UT Garfield", "9wbuvp": " UT Emery", "9wb0bf": " UT Garfield", "9wb8nn": " UT Garfield", "9wby37": " UT Sanpete", "9wbnm6": " UT Millard", "9wb9b8": " UT Wayne", "9wb9ch": " UT Wayne", "9wbd03": " UT Wayne", "9wbd06": " UT Wayne", "9wb0fp": " UT Garfield", "9wbcsw": " UT Wayne", "9wb8sp": " UT Garfield", "9wb8v4": " UT Garfield", "9wbqmk": " UT Sanpete", "9wbuns": " UT Emery", "9wb18c": " UT Beaver", "9wbuxy": " UT Emery", "9wbpv5": " UT Millard", "9wbr77": " UT Sanpete", "9wbuq4": " UT Emery", "9wbx6m": " UT Sanpete", "9wb096": " UT Garfield", "9wbqv9": " UT Sanpete", "9wbrj9": " UT Sanpete", "9wbbk0": " UT Garfield", "9wbrww": " UT Sanpete", "9wb8jy": " UT Garfield", "9wbfq2": " UT Wayne", "9wbbeh": " UT Garfield", "9wb09t": " UT Garfield", "9wbb6f": " UT Garfield", "9wb0dv": " UT Garfield", "9wbd47": " UT Wayne", "9wbwqc": " UT Sanpete", "9wbsk8": " UT Sevier", "9wbwrm": " UT Sanpete", "9wbse4": " UT Sevier", "9wbrns": " UT Sanpete", "9wbrnv": " UT Sanpete", "9wbrny": " UT Sanpete", "9wbmvu": " UT Sevier", "9wbpu8": " UT Millard", "9wb8tc": " UT Garfield", "9wb9dp": " UT Wayne", "9wb8w7": " UT Garfield", "9wb08u": " UT Garfield", "9wb16w": " UT Beaver", "9wb9w4": " UT Wayne", "9wb9qm": " UT Wayne", "9wb0dn": " UT Garfield", "9wb0dh": " UT Garfield", "9wb0dj": " UT Garfield", "9wb9q1": " UT Wayne", "9wb08e": " UT Garfield", "9wbw8k": " UT Sanpete", "9wbqxx": " UT Sanpete", "9wbqzf": " UT Sanpete", "9wbqyz": " UT Sanpete", "9wbqxt": " UT Sanpete", "9wbqxm": " UT Sanpete", "9wby2t": " UT Sanpete", "9wbrj8": " UT Sanpete", "9wbup8": " UT Emery", "9wbwxb": " UT Sanpete", "9wby2j": " UT Sanpete", "9wbrtb": " UT Sanpete", "9wbwny": " UT Sanpete", "9wbsjf": " UT Sevier", "9wbnmj": " UT Millard", "9wby1s": " UT Sanpete", "9wby2p": " UT Sanpete", "9wbcvs": " UT Wayne", "9wb19y": " UT Beaver", "9wbu5r": " UT Sevier", "9wb6ut": " UT Piute", "9wb6k6": " UT Piute", "9wb8kk": " UT Garfield", "9wbr9f": " UT Millard", "9wb3xz": " UT Wayne", "9wb98j": " UT Wayne", "9wbqgw": " UT Sanpete", "9wbgdb": " UT Sevier", "9wbr3f": " UT Millard", "9wb0fk": " UT Garfield", "9wbnm9": " UT Millard", "9wbwpg": " UT Sanpete", "9wbbfk": " UT Garfield", "9wb18b": " UT Beaver", "9wbuxv": " UT Emery", "9wbux2": " UT Emery", "9wbfzz": " UT Wayne", "9wbgeh": " UT Sevier", "9wbgm2": " UT Emery", "9wbgdr": " UT Sevier", "9wb8ut": " UT Garfield", "9wbre1": " UT Millard", "9wb5gd": " UT Sevier", "9wb9nh": " UT Wayne", "9wbc4q": " UT Wayne", "9wbgjh": " UT Emery", "9wb0cf": " UT Garfield", "9wb0f2": " UT Garfield", "9wb9c6": " UT Wayne", "9wb6kr": " UT Piute", "9wb10j": " UT Beaver", "9wb7m1": " UT Sevier", "9wbd4q": " UT Wayne", "9wbbd0": " UT Garfield", "9wb9j6": " UT Wayne", "9wb9qr": " UT Wayne", "9wbr8w": " UT Millard", "9wbpg5": " UT Millard", "9wb6gt": " UT Piute", "9wbpeg": " UT Millard", "9wb189": " UT Beaver", "9wbdkt": " UT Wayne", "9wbdk5": " UT Wayne", "9wbx7w": " UT Sanpete", "9wbx7t": " UT Sanpete", "9wbxdn": " UT Sanpete", "9wbmuz": " UT Sevier", "9wbj4n": " UT Millard", "9wbj4t": " UT Millard", "9wbrqb": " UT Sanpete", "9wbuth": " UT Emery", "9wbqvb": " UT Sanpete", "9wb14b": " UT Piute", "9wb12j": " UT Beaver", "9wb10s": " UT Beaver", "9wb146": " UT Piute", "9wb9hk": " UT Wayne", "9wb9jd": " UT Wayne", "9wbd4m": " UT Wayne", "9wbd15": " UT Wayne", "9wb11p": " UT Beaver", "9wb977": " UT Wayne", "9wbp00": " UT Millard", "9wbuxm": " UT Emery", "9wb130": " UT Beaver", "9wbgym": " UT Emery", "9wbgvc": " UT Emery", "9wbuju": " UT Emery", "9wbypw": " UT Emery", "9wbtbz": " UT Sevier", "9wbch7": " UT Wayne", "9wbfp3": " UT Wayne", "9wb14z": " UT Piute", "9wbu5p": " UT Sevier", "9wby0v": " UT Sanpete", "9wb10e": " UT Beaver", "9wbu6c": " UT Sevier", "9wbfnh": " UT Wayne", "9wbcrd": " UT Wayne", "9wbbdm": " UT Garfield", "9wbpv7": " UT Millard", "9wbu94": " UT Sevier", "9wbgmc": " UT Emery", "9wbqr2": " UT Sanpete", "9wbqx8": " UT Sanpete", "9wbwx0": " UT Sanpete", "9wbqr0": " UT Sanpete", "9wb2jg": " UT Garfield", "9wbru1": " UT Sanpete", "9wbrum": " UT Juab", "9wb6pm": " UT Wayne", "9wb3y9": " UT Piute", "9wb6w1": " UT Piute", "9wbbdr": " UT Garfield", "9wbptq": " UT Millard", "9wbwr4": " UT Sanpete", "9wby32": " UT Sanpete", "9wbqtt": " UT Sanpete", "9wb9vu": " UT Wayne", "9wb9m4": " UT Wayne", "9wb6nt": " UT Piute", "9wbn6j": " UT Millard", "9wbb60": " UT Garfield", "9wb0fw": " UT Garfield", "9wbsqs": " UT Sevier", "9wb9hr": " UT Wayne", "9wbevt": " UT Sevier", "9wbqj4": " UT Sevier", "9wb8t5": " UT Garfield", "9wbptp": " UT Millard", "9wb11j": " UT Beaver", "9wbrth": " UT Sanpete", "9wbjvk": " UT Millard", "9wbsnp": " UT Sevier", "9wb3zj": " UT Wayne", "9wbgv8": " UT Emery", "9wbuy3": " UT Emery", "9wb035": " UT Garfield", "9wbqjj": " UT Sanpete", "9wbuq1": " UT Emery", "9wbwp7": " UT Sanpete", "9wbeur": " UT Sevier", "9wb8we": " UT Garfield", "9wbuq0": " UT Emery", "9wbc6m": " UT Wayne", "9wb131": " UT Beaver", "9wb9dm": " UT Wayne", "9wbg64": " UT Emery", "9wbg5p": " UT Sevier", "9wb0bp": " UT Beaver", "9wbqz0": " UT Sanpete", "9wb100": " UT Beaver", "9wbpuh": " UT Millard", "9wbrqx": " UT Sanpete", "9wb19b": " UT Beaver", "9wbbd1": " UT Garfield", "9wbb6s": " UT Garfield", "9wb8sf": " UT Garfield", "9wbd16": " UT Wayne", "9wbd0u": " UT Wayne", "9wbgp6": " UT Emery", "9wbujs": " UT Emery", "9wbur0": " UT Emery", "9wb8jz": " UT Garfield", "9wbmyn": " UT Sevier", "9wb10m": " UT Beaver", "9wb10z": " UT Beaver", "9wbqqp": " UT Sevier", "9wbsmg": " UT Sevier", "9wbsmb": " UT Sevier", "9wbp9g": " UT Millard", "9wb9n5": " UT Wayne", "9wbg6u": " UT Sevier", "9wbx6e": " UT Sanpete", "9wb8md": " UT Garfield", "9wbux9": " UT Emery", "9wbwru": " UT Sanpete", "9wbqn3": " UT Sevier", "9wbd23": " UT Wayne", "9wb8su": " UT Garfield", "9wb186": " UT Beaver", "9wb9k3": " UT Wayne", "9wb347": " UT Piute", "9wbb3g": " UT Garfield", "9wbcj1": " UT Wayne", "9wbb6q": " UT Garfield", "9wb9jb": " UT Garfield", "9wbqvr": " UT Sanpete", "9wbgpz": " UT Emery", "9wbx7v": " UT Sanpete", "9wb9gp": " UT Wayne", "9wbuxb": " UT Emery", "9wbrpd": " UT Sanpete", "9wbrfw": " UT Millard", "9wbfms": " UT Wayne", "9wbctx": " UT Wayne", "9wbsh3": " UT Sevier", "9wbn10": " UT Millard", "9wbur9": " UT Emery", "9wbmyp": " UT Sevier", "9wb10k": " UT Beaver", "9wb107": " UT Beaver", "9wb9qd": " UT Wayne", "9wbxd8": " UT Sanpete", "9wbc5j": " UT Wayne", "9wbuj8": " UT Emery", "9wbws3": " UT Sanpete", "9wbs7v": " UT Sevier", "9wb6gk": " UT Piute", "9wbqbd": " UT Millard", "9wb190": " UT Beaver", "9wb9bk": " UT Wayne", "9wb13s": " UT Beaver", "9wbtkn": " UT Sevier", "9wbjfx": " UT Millard", "9wbum2": " UT Emery", "9wbpkt": " UT Millard", "9wbwpb": " UT Sevier", "9wbj25": " UT Millard", "9wbbf8": " UT Garfield", "9wbbf3": " UT Garfield", "9wbbf9": " UT Garfield", "9wbevw": " UT Sevier", "9wbevz": " UT Sevier", "9wb18d": " UT Beaver", "9wbu71": " UT Sevier", "9wbb74": " UT Garfield", "9wbsht": " UT Sevier", "9wb9dw": " UT Wayne", "9wbsnw": " UT Sevier", "9wbrfx": " UT Juab", "9wbqp1": " UT Sevier", "9wb2js": " UT Garfield", "9wb8km": " UT Garfield", "9wbb9e": " UT Garfield", "9wb8ws": " UT Garfield", "9wb6gv": " UT Piute", "9wbsv8": " UT Sevier", "9wbtcp": " UT Sevier", "9wbwpu": " UT Sanpete", "9wby21": " UT Sanpete", "9wbwrk": " UT Sanpete", "9wbcnj": " UT Wayne", "9wbb9x": " UT Garfield", "9wbpvs": " UT Millard", "9wbb7h": " UT Garfield", "9wbcjy": " UT Wayne", "9wbvpf": " UT Emery", "9wbgqe": " UT Emery", "9wbctj": " UT Wayne", "9wbpkx": " UT Millard", "9wbqx9": " UT Sanpete", "9wbbfr": " UT Garfield", "9wbuze": " UT Emery", "9wbjuy": " UT Millard", "9wbpve": " UT Millard", "9wbgpg": " UT Emery", "9wb9ks": " UT Wayne", "9wbx7e": " UT Sanpete", "9wbbfz": " UT Garfield", "9wbvze": " UT Emery", "9wbgxy": " UT Emery", "9wbrnu": " UT Sanpete", "9wbyrk": " UT Emery", "9wbcu3": " UT Wayne", "9wbyry": " UT Emery", "9wbcgk": " UT Wayne", "9wbqz8": " UT Sanpete", "9wbupu": " UT Emery", "9wbnmm": " UT Millard", "9wb5jd": " UT Piute", "9wbpgz": " UT Millard", "9wbfmn": " UT Wayne", "9wb9w8": " UT Wayne", "9wb9jr": " UT Wayne", "9wburc": " UT Emery", "9wbftx": " UT Wayne", "9wbx7y": " UT Sanpete", "9wbpsz": " UT Millard", "9wb9kx": " UT Wayne", "9wb9j1": " UT Wayne", "9wbyxt": " UT Emery", "9wbpgw": " UT Millard", "9wbyzs": " UT Emery", "9wbcte": " UT Wayne", "9wbdn5": " UT Wayne", "9wb9m3": " UT Wayne", "9wb9h9": " UT Garfield", "9wbmyq": " UT Sevier", "9wbc19": " UT Garfield", "9wbfr5": " UT Wayne", "9wbknp": " UT Sevier", "9wbbem": " UT Garfield", "9wbcu9": " UT Wayne", "9wbr35": " UT Millard", "9wbpdv": " UT Millard", "9wb9jh": " UT Wayne", "9wbfmx": " UT Wayne", "9wbx9d": " UT Sanpete", "9wbb6w": " UT Garfield", "9wbdru": " UT Wayne", "9wbfty": " UT Wayne", "9wb8yn": " UT Garfield", "9wbvpt": " UT Emery", "9wbpsk": " UT Millard", "9wbc7p": " UT Wayne", "9wbqpm": " UT Sanpete", "9wbj9r": " UT Millard", "9wbnmq": " UT Millard", "9wbfh0": " UT Wayne", "9wb0fh": " UT Garfield", "9wb6th": " UT Piute", "9wbne6": " UT Millard", "9wbc6p": " UT Wayne", "9wbp8b": " UT Millard", "9wbux0": " UT Emery", "9wbcx2": " UT Wayne", "9wbqxb": " UT Sanpete", "9wb16q": " UT Beaver", "9wbgn4": " UT Emery", "9wbd5w": " UT Wayne", "9wb9wd": " UT Wayne", "9wbpd1": " UT Millard", "9wbbgy": " UT Garfield", "9wbbdw": " UT Garfield", "9wb8y7": " UT Garfield", "9wbqck": " UT Millard", "9wb8kq": " UT Garfield", "9wbb9d": " UT Garfield", "9wbz56": " UT Emery", "9wbgzr": " UT Emery", "9wb1f5": " UT Beaver", "9wbej6": " UT Sevier", "9wbsdy": " UT Sevier", "9wb6wf": " UT Piute", "9wb6x4": " UT Wayne", "9wbsej": " UT Sevier", "9wbz3x": " UT Sanpete", "9wbtr6": " UT Sevier", "9wbh7n": " UT Millard", "9wb47g": " UT Piute", "9wbh55": " UT Millard", "9wbhp9": " UT Sevier", "9wbdes": " UT Wayne", "9wb1bm": " UT Beaver", "9wbjeq": " UT Millard", "9wbt66": " UT Sevier", "9wb4mf": " UT Piute", "9wb4k1": " UT Beaver", "9wbmdn": " UT Millard", "9wb6bx": " UT Piute", "9wbe39": " UT Sevier", "9wbyym": " UT Emery", "9wbzxs": " UT Carbon", "9wb3ee": " UT Piute", "9wb3eg": " UT Piute", "9wbk4n": " UT Sevier", "9wbk4p": " UT Sevier", "9wb7g7": " UT Sevier", "9wb5jv": " UT Sevier", "9wb5nq": " UT Sevier", "9wb8b8": " UT Garfield", "9wb915": " UT Wayne", "9wbwbc": " UT Sanpete", "9wbx1r": " UT Sanpete", "9wbtgd": " UT Sevier", "9wb2g6": " UT Garfield", "9wb2sq": " UT Garfield", "9wb2ex": " UT Garfield", "9wb2ew": " UT Garfield", "9wb2rx": " UT Garfield", "9wb2tu": " UT Garfield", "9wbsu7": " UT Sevier", "9wbwf0": " UT Sanpete", "9wbsvh": " UT Sevier", "9wbswu": " UT Sevier", "9wb870": " UT Garfield", "9wbmkv": " UT Sevier", "9wb777": " UT Sevier", "9wb8rn": " UT Garfield", "9wb8qy": " UT Garfield", "9wb1g8": " UT Piute", "9wb92b": " UT Wayne", "9wbmv3": " UT Sevier", "9wb93p": " UT Wayne", "9wbxtv": " UT Sanpete", "9wb40r": " UT Beaver", "9wb43q": " UT Beaver", "9wbwwd": " UT Sanpete", "9wbwk6": " UT Sanpete", "9wbtp5": " UT Sevier", "9wb98g": " UT Wayne", "9wbjqt": " UT Millard", "9wbdmv": " UT Wayne", "9wbyut": " UT Emery", "9wbwnd": " UT Sanpete", "9wbzhd": " UT Emery", "9wbyuz": " UT Emery", "9wbr1v": " UT Millard", "9wb1st": " UT Piute", "9wbm92": " UT Sevier", "9wb6d0": " UT Piute", "9wbt4q": " UT Sevier", "9wbbtg": " UT Garfield", "9wbctq": " UT Wayne", "9wbjq3": " UT Millard", "9wb8p8": " UT Garfield", "9wb2bw": " UT Garfield", "9wbt73": " UT Sevier", "9wb45v": " UT Piute", "9wbwsh": " UT Sanpete", "9wbjxd": " UT Millard", "9wbpwq": " UT Millard", "9wb4ur": " UT Piute", "9wb7vy": " UT Sevier", "9wb7vv": " UT Sevier", "9wbcff": " UT Wayne", "9wbttb": " UT Sevier", "9wbwkq": " UT Sanpete", "9wb4yh": " UT Piute", "9wbssk": " UT Sevier", "9wbskr": " UT Sevier", "9wbz95": " UT Sanpete", "9wbz8m": " UT Sanpete", "9wb3td": " UT Piute", "9wb4s5": " UT Piute", "9wbbbm": " UT Garfield", "9wbm98": " UT Sevier", "9wb1ff": " UT Beaver", "9wbb9z": " UT Garfield", "9wb5j7": " UT Sevier", "9wb57h": " UT Sevier", "9wb49c": " UT Piute", "9wbkhn": " UT Sevier", "9wbkhw": " UT Sevier", "9wb1y3": " UT Piute", "9wb78v": " UT Sevier", "9wb789": " UT Sevier", "9wb17p": " UT Beaver", "9wbdjg": " UT Wayne", "9wb9vv": " UT Wayne", "9wbdjb": " UT Wayne", "9wbys8": " UT Emery", "9wbyu2": " UT Emery", "9wbyfe": " UT Sanpete", "9wb5dz": " UT Sevier", "9wb1b2": " UT Beaver", "9wb1g0": " UT Beaver", "9wb69y": " UT Piute", "9wb1g4": " UT Beaver", "9wb69v": " UT Piute", "9wbdhf": " UT Wayne", "9wbhmj": " UT Millard", "9wb44m": " UT Beaver", "9wb8dk": " UT Garfield", "9wbbb3": " UT Garfield", "9wbdxe": " UT Wayne", "9wb7uk": " UT Sevier", "9wb4d9": " UT Piute", "9wbh1v": " UT Millard", "9wb2yh": " UT Garfield", "9wb2vw": " UT Garfield", "9wbvc7": " UT Sevier", "9wb2ww": " UT Garfield", "9wb63w": " UT Piute", "9wbyhb": " UT Emery", "9wb3j2": " UT Garfield", "9wbqdn": " UT Millard", "9wbxk6": " UT Sanpete", "9wb7w4": " UT Sevier", "9wbexz": " UT Sevier", "9wb59r": " UT Sevier", "9wbys3": " UT Emery", "9wb1hc": " UT Piute", "9wbwkp": " UT Sanpete", "9wbc8n": " UT Wayne", "9wb0ww": " UT Garfield", "9wb31c": " UT Piute", "9wbext": " UT Sevier", "9wbyk1": " UT Emery", "9wbzk6": " UT Emery", "9wbzkm": " UT Emery", "9wb7w1": " UT Sevier", "9wb2vj": " UT Garfield", "9wb2ec": " UT Garfield", "9wbmx7": " UT Sevier", "9wbjtz": " UT Millard", "9wbzmm": " UT Emery", "9wbyev": " UT Emery", "9wbwvc": " UT Sanpete", "9wbkgg": " UT Sevier", "9wbwy1": " UT Sanpete", "9wbmr2": " UT Sevier", "9wbd86": " UT Wayne", "9wbd81": " UT Wayne", "9wb9y9": " UT Wayne", "9wbd9q": " UT Wayne", "9wbhb2": " UT Millard", "9wbdht": " UT Wayne", "9wb95m": " UT Wayne", "9wbsvk": " UT Sevier", "9wbc0j": " UT Wayne", "9wb33r": " UT Piute", "9wbyp5": " UT Emery", "9wbkzr": " UT Sevier", "9wbdz3": " UT Wayne", "9wbwnt": " UT Sanpete", "9wby67": " UT Sanpete", "9wbzf2": " UT Sanpete", "9wb43s": " UT Beaver", "9wbwyj": " UT Sanpete", "9wb7m4": " UT Sevier", "9wbjxp": " UT Millard", "9wb852": " UT Garfield", "9wbykt": " UT Emery", "9wbuuc": " UT Emery", "9wbxxm": " UT Sanpete", "9wb9nf": " UT Wayne", "9wb7xj": " UT Sevier", "9wbs1h": " UT Sevier", "9wbkpc": " UT Sevier", "9wb40y": " UT Beaver", "9wb41n": " UT Beaver", "9wbcb5": " UT Wayne", "9wb8z0": " UT Garfield", "9wb8ys": " UT Wayne", "9wbpy7": " UT Millard", "9wbe3g": " UT Sevier", "9wbvfq": " UT Sevier", "9wb6mr": " UT Piute", "9wbdem": " UT Wayne", "9wb407": " UT Beaver", "9wbe5g": " UT Sevier", "9wb40e": " UT Beaver", "9wb47e": " UT Piute", "9wbkje": " UT Sevier", "9wb74g": " UT Sevier", "9wbkgu": " UT Sevier", "9wbjxv": " UT Millard", "9wbv26": " UT Sevier", "9wbs1r": " UT Sevier", "9wbkpt": " UT Sevier", "9wbece": " UT Sevier", "9wb5zy": " UT Sevier", "9wbvh6": " UT Emery", "9wbt5n": " UT Sevier", "9wbqex": " UT Sanpete", "9wbhdx": " UT Millard", "9wbt11": " UT Sevier", "9wbxq2": " UT Sanpete", "9wbz7f": " UT Emery", "9wbz76": " UT Emery", "9wbe0y": " UT Sevier", "9wbjwk": " UT Millard", "9wb1f2": " UT Beaver", "9wbz30": " UT Sanpete", "9wb0gs": " UT Garfield", "9wb0er": " UT Garfield", "9wbjqm": " UT Millard", "9wbk75": " UT Sevier", "9wbygg": " UT Emery", "9wb995": " UT Wayne", "9wbdyb": " UT Wayne", "9wb071": " UT Garfield", "9wb0hx": " UT Garfield", "9wb0hr": " UT Garfield", "9wbs2j": " UT Sevier", "9wbh0g": " UT Millard", "9wbtev": " UT Sevier", "9wbh0f": " UT Millard", "9wb1hv": " UT Piute", "9wbfdr": " UT Wayne", "9wbfbd": " UT Wayne", "9wb31h": " UT Piute", "9wbdd6": " UT Wayne", "9wbd78": " UT Wayne", "9wbf8q": " UT Wayne", "9wb4s9": " UT Piute", "9wb4e8": " UT Piute", "9wb46q": " UT Piute", "9wb47j": " UT Piute", "9wb1uz": " UT Piute", "9wbjre": " UT Millard", "9wb6g0": " UT Piute", "9wbxjz": " UT Sanpete", "9wbxnp": " UT Sanpete", "9wbhwd": " UT Sevier", "9wb0yw": " UT Garfield", "9wbskz": " UT Sevier", "9wb0xn": " UT Garfield", "9wb900": " UT Garfield", "9wb0xm": " UT Garfield", "9wb7qs": " UT Sevier", "9wb7tu": " UT Sevier", "9wb8kd": " UT Garfield", "9wb7qm": " UT Sevier", "9wb7q7": " UT Sevier", "9wb4gs": " UT Piute", "9wb5g5": " UT Sevier", "9wb3qc": " UT Piute", "9wbs1d": " UT Sevier", "9wb89j": " UT Garfield", "9wbzs7": " UT Emery", "9wbe10": " UT Wayne", "9wbqfc": " UT Millard", "9wbcfh": " UT Wayne", "9wb4sg": " UT Piute", "9wb0vb": " UT Garfield", "9wbxvh": " UT Sanpete", "9wbxvs": " UT Sanpete", "9wbpmh": " UT Millard", "9wbcuz": " UT Wayne", "9wbcrp": " UT Wayne", "9wbcdt": " UT Wayne", "9wbmnj": " UT Sevier", "9wbktk": " UT Sevier", "9wbvxh": " UT Emery", "9wbt5e": " UT Sevier", "9wbjyf": " UT Millard", "9wbhhy": " UT Millard", "9wbyzr": " UT Emery", "9wbdt6": " UT Wayne", "9wb6qu": " UT Wayne", "9wbktu": " UT Sevier", "9wbtcc": " UT Sevier", "9wb92s": " UT Wayne", "9wb98f": " UT Wayne", "9wb926": " UT Wayne", "9wbmby": " UT Millard", "9wbjr5": " UT Millard", "9wbehg": " UT Sevier", "9wb2kc": " UT Garfield", "9wbk1j": " UT Sevier", "9wb7sv": " UT Sevier", "9wbnfx": " UT Millard", "9wbn11": " UT Millard", "9wb5bv": " UT Sevier", "9wbhmn": " UT Millard", "9wbz26": " UT Sanpete", "9wbk5d": " UT Sevier", "9wbcgq": " UT Wayne", "9wbjqs": " UT Millard", "9wb0tx": " UT Garfield", "9wb0gu": " UT Garfield", "9wbttm": " UT Sevier", "9wbwe5": " UT Sanpete", "9wb7u3": " UT Sevier", "9wb7jq": " UT Sevier", "9wbnvr": " UT Millard", "9wbnv6": " UT Millard", "9wbntm": " UT Millard", "9wbntp": " UT Millard", "9wb9zj": " UT Wayne", "9wbbpj": " UT Garfield", "9wb7gx": " UT Sevier", "9wb8x7": " UT Garfield", "9wb1q3": " UT Piute", "9wb1jh": " UT Piute", "9wb0uq": " UT Garfield", "9wb1sp": " UT Piute", "9wb1gw": " UT Piute", "9wb3md": " UT Piute", "9wbzf6": " UT Sanpete", "9wbzjx": " UT Emery", "9wbzmt": " UT Emery", "9wbzcs": " UT Sanpete", "9wb2p0": " UT Garfield", "9wbw7w": " UT Sanpete", "9wb5mx": " UT Sevier", "9wbu2p": " UT Sevier", "9wbtfv": " UT Sevier", "9wb57q": " UT Sevier", "9wbwh5": " UT Sanpete", "9wbk4k": " UT Sevier", "9wbzrd": " UT Carbon", "9wb7sm": " UT Sevier", "9wbvn3": " UT Emery", "9wbt7d": " UT Sevier", "9wbuge": " UT Emery", "9wb322": " UT Piute", "9wbc3q": " UT Wayne", "9wbq0n": " UT Millard", "9wbybb": " UT Sanpete", "9wbs33": " UT Sevier", "9wbse7": " UT Sevier", "9wb6f1": " UT Piute", "9wbh7g": " UT Millard", "9wb50r": " UT Sevier", "9wbtrf": " UT Sevier", "9wbtu8": " UT Sevier", "9wbtt6": " UT Sevier", "9wbv32": " UT Sevier", "9wbf1f": " UT Wayne", "9wbwmw": " UT Sanpete", "9wbs88": " UT Sevier", "9wbkxu": " UT Sevier", "9wbe1h": " UT Sevier", "9wb185": " UT Beaver", "9wbjqp": " UT Millard", "9wb4se": " UT Piute", "9wbhc7": " UT Millard", "9wb827": " UT Garfield", "9wb308": " UT Garfield", "9wbstf": " UT Sevier", "9wbv3n": " UT Sevier", "9wb17s": " UT Piute", "9wbjr7": " UT Millard", "9wb1m5": " UT Piute", "9wbk4j": " UT Sevier", "9wbh6b": " UT Millard", "9wbt65": " UT Sevier", "9wb4wb": " UT Piute", "9wbk9s": " UT Sevier", "9wbxm6": " UT Sanpete", "9wbxy1": " UT Sanpete", "9wb0n8": " UT Garfield", "9wbxm3": " UT Sanpete", "9wbxyd": " UT Sanpete", "9wb1u6": " UT Piute", "9wb2qe": " UT Garfield", "9wb0xh": " UT Garfield", "9wb5t9": " UT Sevier", "9wbyfq": " UT Sanpete", "9wbz06": " UT Sanpete", "9wbxpb": " UT Sanpete", "9wb7s7": " UT Sevier", "9wbker": " UT Sevier", "9wbwmn": " UT Sanpete", "9wb25u": " UT Garfield", "9wbwqm": " UT Sanpete", "9wby1b": " UT Sevier", "9wbkr6": " UT Sevier", "9wb851": " UT Garfield", "9wbz37": " UT Sanpete", "9wbz2v": " UT Sanpete", "9wbzmj": " UT Emery", "9wbzdc": " UT Sanpete", "9wbhjg": " UT Sevier", "9wb2r1": " UT Garfield", "9wb2py": " UT Garfield", "9wb8z3": " UT Garfield", "9wbe7j": " UT Sevier", "9wb1c7": " UT Beaver", "9wbht0": " UT Millard", "9wbhtj": " UT Millard", "9wbsgy": " UT Sevier", "9wb8x5": " UT Garfield", "9wbe5m": " UT Sevier", "9wbr0d": " UT Millard", "9wb4hh": " UT Piute", "9wb1gp": " UT Beaver", "9wbsww": " UT Sevier", "9wbh76": " UT Millard", "9wb5y3": " UT Sevier", "9wbq99": " UT Millard", "9wb81f": " UT Garfield", "9wb18e": " UT Beaver", "9wbzvp": " UT Emery", "9wbyew": " UT Sanpete", "9wbq6k": " UT Millard", "9wbydt": " UT Sanpete", "9wbyf2": " UT Sanpete", "9wbh83": " UT Millard", "9wb2mk": " UT Garfield", "9wb2b7": " UT Garfield", "9wbyvn": " UT Emery", "9wb7xs": " UT Sevier", "9wbebu": " UT Sevier", "9wbs1f": " UT Sevier", "9wbx4w": " UT Sanpete", "9wbz2r": " UT Sanpete", "9wbesf": " UT Sevier", "9wb9s8": " UT Garfield", "9wb838": " UT Garfield", "9wbkhk": " UT Sevier", "9wbkhd": " UT Sevier", "9wbt6c": " UT Sevier", "9wbtu7": " UT Sevier", "9wbd95": " UT Piute", "9wbdb8": " UT Wayne", "9wb2wr": " UT Garfield", "9wb3n3": " UT Piute", "9wb2e2": " UT Garfield", "9wbcyc": " UT Wayne", "9wbdxs": " UT Wayne", "9wb7gd": " UT Sevier", "9wbwqr": " UT Sanpete", "9wbjw5": " UT Millard", "9wb1ct": " UT Beaver", "9wb2hp": " UT Garfield", "9wb5j9": " UT Piute", "9wb4g4": " UT Piute", "9wbb3m": " UT Garfield", "9wbzzk": " UT Carbon", "9wb4gy": " UT Piute", "9wb4t3": " UT Piute", "9wb5hb": " UT Piute", "9wb3rg": " UT Wayne", "9wbb3r": " UT Garfield", "9wbb1k": " UT Garfield", "9wbu17": " UT Sevier", "9wbe0u": " UT Sevier", "9wbenx": " UT Sevier", "9wb610": " UT Piute", "9wbenq": " UT Sevier", "9wb4mh": " UT Piute", "9wb4k7": " UT Piute", "9wb46b": " UT Beaver", "9wb5w5": " UT Sevier", "9wbmtg": " UT Sevier", "9wbr61": " UT Millard", "9wb7ek": " UT Sevier", "9wb7es": " UT Sevier", "9wbkxh": " UT Sevier", "9wb0z3": " UT Garfield", "9wb8rt": " UT Garfield", "9wb1kt": " UT Piute", "9wbe1r": " UT Sevier", "9wb7tj": " UT Sevier", "9wb7sy": " UT Sevier", "9wbdby": " UT Wayne", "9wbddd": " UT Wayne", "9wb3vt": " UT Piute", "9wbdcr": " UT Wayne", "9wbuef": " UT Emery", "9wbuu3": " UT Emery", "9wb62j": " UT Piute", "9wbc8z": " UT Wayne", "9wb8jb": " UT Garfield", "9wb9pm": " UT Wayne", "9wb9pz": " UT Wayne", "9wb76t": " UT Sevier", "9wbz7s": " UT Emery", "9wbsrz": " UT Sevier", "9wb335": " UT Piute", "9wbzgv": " UT Emery", "9wbbm4": " UT Garfield", "9wbq10": " UT Millard", "9wb5pz": " UT Sevier", "9wb57t": " UT Piute", "9wbnxu": " UT Millard", "9wbxfq": " UT Sanpete", "9wb4pj": " UT Piute", "9wb57y": " UT Sevier", "9wbjss": " UT Millard", "9wbput": " UT Millard", "9wb60z": " UT Piute", "9wb69g": " UT Piute", "9wbv9b": " UT Sevier", "9wbbsu": " UT Garfield", "9wbws6": " UT Sanpete", "9wb2we": " UT Garfield", "9wbtqw": " UT Sevier", "9wb27v": " UT Garfield", "9wb18w": " UT Beaver", "9wb5y1": " UT Sevier", "9wb66g": " UT Piute", "9wb81e": " UT Garfield", "9wb2r5": " UT Garfield", "9wb38q": " UT Piute", "9wb96r": " UT Wayne", "9wbyeb": " UT Emery", "9wbmhr": " UT Sevier", "9wbdew": " UT Wayne", "9wb5mp": " UT Sevier", "9wb2g3": " UT Garfield", "9wbyqj": " UT Emery", "9wb3mc": " UT Piute", "9wbh3r": " UT Millard", "9wbybk": " UT Sanpete", "9wbwzf": " UT Emery", "9wb7gh": " UT Sevier", "9wbp59": " UT Millard", "9wbyee": " UT Emery", "9wb419": " UT Beaver", "9wbv2z": " UT Sevier", "9wbv87": " UT Sevier", "9wb8r1": " UT Garfield", "9wb4wr": " UT Piute", "9wb4zg": " UT Piute", "9wbxzh": " UT Sanpete", "9wb0q3": " UT Garfield", "9wbcmd": " UT Wayne", "9wb770": " UT Sevier", "9wbmbj": " UT Millard", "9wb8rg": " UT Garfield", "9wb8zk": " UT Garfield", "9wbb0g": " UT Garfield", "9wbttf": " UT Sevier", "9wb8pt": " UT Garfield", "9wb2gr": " UT Garfield", "9wbht8": " UT Millard", "9wbny6": " UT Millard", "9wbdn7": " UT Wayne", "9wbphf": " UT Millard", "9wb4c3": " UT Piute", "9wbtv5": " UT Sevier", "9wbv3z": " UT Sevier", "9wb1qz": " UT Piute", "9wb7sz": " UT Sevier", "9wbznv": " UT Emery", "9wbmwu": " UT Sevier", "9wbd6w": " UT Wayne", "9wbv2e": " UT Sevier", "9wbeq2": " UT Sevier", "9wbewh": " UT Sevier", "9wbnz2": " UT Millard", "9wbpnj": " UT Millard", "9wbndn": " UT Millard", "9wbd2m": " UT Wayne", "9wbyx5": " UT Emery", "9wb8zp": " UT Garfield", "9wb4ru": " UT Piute", "9wbkr0": " UT Sevier", "9wbv2h": " UT Sevier", "9wbe53": " UT Wayne", "9wbezk": " UT Sevier", "9wbzzt": " UT Carbon", "9wbz50": " UT Sanpete", "9wbzyr": " UT Emery", "9wbdzd": " UT Wayne", "9wbxr7": " UT Sanpete", "9wbk01": " UT Sevier", "9wbvkm": " UT Emery", "9wbvkr": " UT Emery", "9wbsx5": " UT Sevier", "9wbz8p": " UT Sanpete", "9wbxuv": " UT Sanpete", "9wbxv6": " UT Sanpete", "9wbxur": " UT Sanpete", "9wbdb4": " UT Wayne", "9wbme6": " UT Sevier", "9wbkzw": " UT Sevier", "9wber8": " UT Sevier", "9wbh4x": " UT Millard", "9wbct6": " UT Wayne", "9wbyrh": " UT Emery", "9wbyer": " UT Emery", "9wbys4": " UT Emery", "9wbymv": " UT Emery", "9wby94": " UT Sanpete", "9wbwxv": " UT Sanpete", "9wbjsn": " UT Millard", "9wbjs7": " UT Millard", "9wb79d": " UT Sevier", "9wb5hp": " UT Sevier", "9wb57v": " UT Sevier", "9wb5d0": " UT Sevier", "9wbc9w": " UT Wayne", "9wbc90": " UT Wayne", "9wb4cr": " UT Piute", "9wbe3c": " UT Sevier", "9wb6zw": " UT Piute", "9wbpr6": " UT Millard", "9wbztz": " UT Emery", "9wby70": " UT Sanpete", "9wbk0p": " UT Sevier", "9wbry0": " UT Sanpete", "9wb6bm": " UT Piute", "9wbxxx": " UT Sanpete", "9wbkzc": " UT Sevier", "9wbdx1": " UT Wayne", "9wbsu8": " UT Sevier", "9wb9wu": " UT Wayne", "9wbepx": " UT Sevier", "9wb4e2": " UT Piute", "9wb3x8": " UT Wayne", "9wbwgw": " UT Sanpete", "9wb2es": " UT Garfield", "9wb19s": " UT Beaver", "9wb3q7": " UT Piute", "9wb39k": " UT Piute", "9wb3t2": " UT Piute", "9wb3w2": " UT Piute", "9wb3qp": " UT Piute", "9wb39y": " UT Piute", "9wb39q": " UT Piute", "9wbenj": " UT Sevier", "9wbeqe": " UT Sevier", "9wbhf8": " UT Millard", "9wbxz7": " UT Sanpete", "9wbdu0": " UT Wayne", "9wbdue": " UT Wayne", "9wbdex": " UT Wayne", "9wbu3r": " UT Sevier", "9wbdgb": " UT Wayne", "9wbm7p": " UT Sevier", "9wbeds": " UT Sevier", "9wbedv": " UT Sevier", "9wbu0y": " UT Sevier", "9wbz7t": " UT Sanpete", "9wbwfz": " UT Sanpete", "9wbxk4": " UT Sanpete", "9wbe2v": " UT Sevier", "9wbxv7": " UT Sanpete", "9wbg0e": " UT Sevier", "9wb5fu": " UT Sevier", "9wbt13": " UT Sevier", "9wbsd9": " UT Sevier", "9wbybh": " UT Sanpete", "9wbscu": " UT Sevier", "9wbeph": " UT Sevier", "9wb4jm": " UT Piute", "9wb9s2": " UT Wayne", "9wbudp": " UT Sevier", "9wbke8": " UT Sevier", "9wbkes": " UT Sevier", "9wbk7z": " UT Sevier", "9wb4we": " UT Piute", "9wb4qc": " UT Piute", "9wb4dq": " UT Piute", "9wbcmv": " UT Wayne", "9wbsdr": " UT Sevier", "9wbe8j": " UT Sevier", "9wb5ye": " UT Sevier", "9wbt3h": " UT Sevier", "9wbsdx": " UT Sevier", "9wb430": " UT Beaver", "9wbs4f": " UT Sevier", "9wb9yj": " UT Wayne", "9wbr06": " UT Millard", "9wbkdm": " UT Sevier", "9wbcv8": " UT Wayne", "9wb5cm": " UT Sevier", "9wb5f3": " UT Sevier", "9wbz3y": " UT Sanpete", "9wbb2p": " UT Garfield", "9wbhm5": " UT Millard", "9wb3sr": " UT Piute", "9wbzdw": " UT Sanpete", "9wbdg8": " UT Wayne", "9wb5wq": " UT Sevier", "9wbnrg": " UT Millard", "9wb81u": " UT Garfield", "9wb9rb": " UT Wayne", "9wby44": " UT Sanpete", "9wb6vk": " UT Piute", "9wb8hb": " UT Garfield", "9wb1ee": " UT Piute", "9wb3ru": " UT Wayne", "9wb1cv": " UT Beaver", "9wbwwq": " UT Sanpete", "9wbxv4": " UT Sanpete", "9wby1w": " UT Sanpete", "9wbx4n": " UT Sanpete", "9wbwj9": " UT Sevier", "9wb1ds": " UT Beaver", "9wbcsr": " UT Wayne", "9wb8xk": " UT Garfield", "9wbj7e": " UT Millard", "9wbsdf": " UT Sevier", "9wbe2t": " UT Sevier", "9wbe2w": " UT Sevier", "9wbq32": " UT Millard", "9wbjr1": " UT Millard", "9wbjxm": " UT Millard", "9wbpxw": " UT Millard", "9wb90u": " UT Wayne", "9wb917": " UT Wayne", "9wbxh3": " UT Sanpete", "9wbyb3": " UT Sanpete", "9wbyb1": " UT Sanpete", "9wb1dz": " UT Beaver", "9wbse1": " UT Sevier", "9wb6y3": " UT Piute", "9wbhby": " UT Millard", "9wb06b": " UT Garfield", "9wb8nv": " UT Garfield", "9wb82x": " UT Garfield", "9wb88c": " UT Garfield", "9wbxx5": " UT Sanpete", "9wbkzn": " UT Sevier", "9wbdv5": " UT Wayne", "9wb0e3": " UT Garfield", "9wb3bz": " UT Piute", "9wbhez": " UT Millard", "9wb3cw": " UT Piute", "9wb8h8": " UT Garfield", "9wbdr3": " UT Wayne", "9wbdnj": " UT Wayne", "9wb4kn": " UT Piute", "9wb7gv": " UT Sevier", "9wbdzq": " UT Wayne", "9wbmf5": " UT Millard", "9wbynr": " UT Emery", "9wb187": " UT Beaver", "9wbe3h": " UT Sevier", "9wb31w": " UT Garfield", "9wbdsh": " UT Wayne", "9wbwxp": " UT Sanpete", "9wbx7c": " UT Sanpete", "9wbw82": " UT Sanpete", "9wbkx4": " UT Sevier", "9wb36t": " UT Piute", "9wbex6": " UT Sevier", "9wb4c7": " UT Piute", "9wb45j": " UT Beaver", "9wbf02": " UT Wayne", "9wb2dx": " UT Garfield", "9wbscr": " UT Sevier", "9wb4cp": " UT Piute", "9wbz4c": " UT Sanpete", "9wbsrg": " UT Sevier", "9wb4k6": " UT Piute", "9wbjtb": " UT Millard", "9wbjt5": " UT Millard", "9wbtxe": " UT Sevier", "9wbdmg": " UT Wayne", "9wb074": " UT Garfield", "9wb0k7": " UT Garfield", "9wbdt5": " UT Wayne", "9wb0s9": " UT Garfield", "9wbzbj": " UT Sanpete", "9wbzbv": " UT Sanpete", "9wbswg": " UT Sevier", "9wb8xt": " UT Garfield", "9wbzbh": " UT Sanpete", "9wbj00": " UT Millard", "9wb5wv": " UT Sevier", "9wb7c1": " UT Sevier", "9wbxnr": " UT Sanpete", "9wbs61": " UT Sevier", "9wbhet": " UT Millard", "9wb989": " UT Wayne", "9wb2fq": " UT Garfield", "9wbkh8": " UT Sevier", "9wb7uw": " UT Sevier", "9wb732": " UT Sevier", "9wb1f7": " UT Beaver", "9wb19v": " UT Beaver", "9wbb5f": " UT Garfield", "9wbycs": " UT Sanpete", "9wbzgd": " UT Emery", "9wb5wr": " UT Sevier", "9wbwxt": " UT Sanpete", "9wbh5d": " UT Millard", "9wbbhk": " UT Garfield", "9wb4u9": " UT Piute", "9wbqdh": " UT Millard", "9wbzvj": " UT Emery", "9wbhh2": " UT Sevier", "9wb7k4": " UT Sevier", "9wbq2q": " UT Millard", "9wb0jw": " UT Garfield", "9wb837": " UT Garfield", "9wbhv5": " UT Millard", "9wb80v": " UT Garfield", "9wb81p": " UT Garfield", "9wbkeg": " UT Sevier", "9wbm86": " UT Millard", "9wbb56": " UT Garfield", "9wbyz2": " UT Emery", "9wb405": " UT Beaver", "9wb80n": " UT Garfield", "9wbwnr": " UT Sanpete", "9wbekd": " UT Sevier", "9wbq66": " UT Millard", "9wbuv9": " UT Emery", "9wbudg": " UT Sevier", "9wbsgx": " UT Sevier", "9wb82v": " UT Garfield", "9wbtfu": " UT Sevier", "9wbmb4": " UT Millard", "9wbjq9": " UT Millard", "9wbdwp": " UT Wayne", "9wbdyc": " UT Wayne", "9wb4ff": " UT Piute", "9wby3v": " UT Sanpete", "9wby1r": " UT Sanpete", "9wb1ur": " UT Piute", "9wbk31": " UT Sevier", "9wb7cq": " UT Sevier", "9wbxpx": " UT Sanpete", "9wbyz9": " UT Carbon", "9wbxts": " UT Sanpete", "9wbu3s": " UT Sevier", "9wbzec": " UT Emery", "9wbxxb": " UT Sanpete", "9wbpx6": " UT Millard", "9wbspv": " UT Sevier", "9wb25y": " UT Garfield", "9wbnjz": " UT Millard", "9wbeek": " UT Sevier", "9wbxx2": " UT Sanpete", "9wbv24": " UT Sevier", "9wbv21": " UT Sevier", "9wbg1w": " UT Sevier", "9wb0zu": " UT Garfield", "9wb0xe": " UT Garfield", "9wbed8": " UT Sevier", "9wb5y0": " UT Sevier", "9wb5ud": " UT Sevier", "9wbz6z": " UT Sanpete", "9wbmpg": " UT Sevier", "9wb87d": " UT Garfield", "9wbwtf": " UT Sanpete", "9wbtvt": " UT Sevier", "9wbjzw": " UT Millard", "9wb1w2": " UT Piute", "9wbh9r": " UT Millard", "9wbhd3": " UT Millard", "9wbh9k": " UT Millard", "9wbhf4": " UT Millard", "9wbkrq": " UT Sevier", "9wb448": " UT Beaver", "9wbkfb": " UT Sevier", "9wb7v4": " UT Sevier", "9wbyyc": " UT Emery", "9wbyyr": " UT Emery", "9wb33c": " UT Piute", "9wbktm": " UT Sevier", "9wbkt5": " UT Sevier", "9wb8rv": " UT Garfield", "9wb1r5": " UT Piute", "9wb1je": " UT Piute", "9wb1r7": " UT Piute", "9wb7mj": " UT Sevier", "9wbsnu": " UT Sevier", "9wbsny": " UT Sevier", "9wbkwy": " UT Sevier", "9wbqcf": " UT Millard", "9wbxu9": " UT Sanpete", "9wbpyp": " UT Millard", "9wbzd5": " UT Sanpete", "9wb7n4": " UT Sevier", "9wb7nn": " UT Sevier", "9wb7ju": " UT Sevier", "9wb7jf": " UT Sevier", "9wb77s": " UT Sevier", "9wb77g": " UT Sevier", "9wb7wf": " UT Sevier", "9wbkxq": " UT Sevier", "9wbx5h": " UT Sanpete", "9wbee5": " UT Sevier", "9wbg43": " UT Wayne", "9wbwzv": " UT Sanpete", "9wbz0k": " UT Sanpete", "9wbxwz": " UT Sanpete", "9wbxpy": " UT Sanpete", "9wb457": " UT Beaver", "9wb1cg": " UT Beaver", "9wbbn9": " UT Garfield", "9wb66u": " UT Piute", "9wb6e0": " UT Piute", "9wbzbe": " UT Sanpete", "9wbwc1": " UT Sanpete", "9wbzb4": " UT Sanpete", "9wbgf0": " UT Sevier", "9wby4b": " UT Sevier", "9wbhes": " UT Millard", "9wbhsd": " UT Millard", "9wbhs4": " UT Millard", "9wbxxr": " UT Sanpete", "9wbmcj": " UT Millard", "9wb5et": " UT Sevier", "9wbxqf": " UT Sanpete", "9wbxhc": " UT Sanpete", "9wbq36": " UT Millard", "9wbq34": " UT Millard", "9wbdyt": " UT Wayne", "9wb20d": " UT Garfield", "9wbds3": " UT Wayne", "9wbh2n": " UT Millard", "9wbxvr": " UT Sanpete", "9wbgcv": " UT Sevier", "9wb4cn": " UT Piute", "9wbvdb": " UT Sevier", "9wbvds": " UT Sevier", "9wbv5m": " UT Sevier", "9wb40z": " UT Beaver", "9wb5g9": " UT Sevier", "9wb329": " UT Piute", "9wbz45": " UT Sanpete", "9wb3bf": " UT Piute", "9wb243": " UT Garfield", "9wb7mz": " UT Sevier", "9wbswr": " UT Sevier", "9wbpvu": " UT Millard", "9wbu1x": " UT Sevier", "9wbmvf": " UT Sevier", "9wbv90": " UT Sevier", "9wbq2j": " UT Millard", "9wb2tp": " UT Garfield", "9wbhm4": " UT Millard", "9wbxvw": " UT Sanpete", "9wby8q": " UT Sanpete", "9wbprq": " UT Millard", "9wbq7h": " UT Sanpete", "9wbkxj": " UT Sevier", "9wb4kj": " UT Piute", "9wb3hx": " UT Piute", "9wbdfn": " UT Wayne", "9wbykf": " UT Emery", "9wbpzk": " UT Juab", "9wb4hu": " UT Piute", "9wbz96": " UT Sanpete", "9wb6hw": " UT Piute", "9wb18h": " UT Beaver", "9wbf7s": " UT Wayne", "9wb48j": " UT Beaver", "9wbxnv": " UT Sanpete", "9wb62z": " UT Piute", "9wb0ff": " UT Garfield", "9wbhxu": " UT Sevier", "9wbqdw": " UT Millard", "9wbzee": " UT Emery", "9wb72j": " UT Sevier", "9wby9v": " UT Sanpete", "9wbtx8": " UT Sevier", "9wbd7x": " UT Wayne", "9wbd7p": " UT Wayne", "9wbde2": " UT Wayne", "9wbq37": " UT Millard", "9wb32b": " UT Piute", "9wbxrj": " UT Sanpete", "9wbxre": " UT Sanpete", "9wb95g": " UT Wayne", "9wb9h7": " UT Wayne", "9wbqt3": " UT Sanpete", "9wbqe5": " UT Millard", "9wbjrv": " UT Sevier", "9wbkh5": " UT Sevier", "9wbm2j": " UT Sevier", "9wbphe": " UT Millard", "9wbb8u": " UT Garfield", "9wb1eq": " UT Piute", "9wb7gs": " UT Sevier", "9wbz35": " UT Sanpete", "9wbsf3": " UT Sevier", "9wbd76": " UT Wayne", "9wbqcq": " UT Millard", "9wbzjg": " UT Emery", "9wb5qr": " UT Sevier", "9wb589": " UT Sevier", "9wbcu7": " UT Wayne", "9wbjnr": " UT Millard", "9wb0vs": " UT Garfield", "9wbmmw": " UT Sevier", "9wb1j9": " UT Piute", "9wb82n": " UT Garfield", "9wb82q": " UT Garfield", "9wb2x9": " UT Garfield", "9wb2x4": " UT Garfield", "9wbef8": " UT Sevier", "9wb1c6": " UT Beaver", "9wbwuc": " UT Sanpete", "9wb993": " UT Wayne", "9wbnxq": " UT Millard", "9wbz7w": " UT Emery", "9wb4fq": " UT Piute", "9wbwvw": " UT Sanpete", "9wbwu1": " UT Sanpete", "9wb9r6": " UT Wayne", "9wbxrh": " UT Sanpete", "9wbzet": " UT Emery", "9wbr57": " UT Millard", "9wb1hn": " UT Piute", "9wbpye": " UT Millard", "9wbe3f": " UT Sevier", "9wbz8j": " UT Sanpete", "9wb7sj": " UT Sevier", "9wb77w": " UT Sevier", "9wbjwv": " UT Millard", "9wb5c0": " UT Sevier", "9wbzq5": " UT Emery", "9wbm91": " UT Sevier", "9wbe1k": " UT Sevier", "9wb397": " UT Piute", "9wbeke": " UT Sevier", "9wb4qf": " UT Piute", "9wb6cz": " UT Piute", "9wbx7s": " UT Sanpete", "9wbx7f": " UT Sanpete", "9wbxmc": " UT Sanpete", "9wbxmt": " UT Sanpete", "9wbxqh": " UT Sanpete", "9wbk4z": " UT Sevier", "9wbrvc": " UT Sanpete", "9wbmcq": " UT Millard", "9wbjs3": " UT Millard", "9wbnm7": " UT Millard", "9wb54u": " UT Sevier", "9wbt6d": " UT Sevier", "9wb568": " UT Piute", "9wb4bz": " UT Piute", "9wb0g1": " UT Garfield", "9wb05k": " UT Garfield", "9wb043": " UT Garfield", "9wbegx": " UT Sevier", "9wbz6c": " UT Sanpete", "9wb1uq": " UT Piute", "9wbwhf": " UT Sanpete", "9wb4wp": " UT Piute", "9wb5td": " UT Sevier", "9wb6cj": " UT Piute", "9wbjxu": " UT Millard", "9wbbvn": " UT Garfield", "9wbw9b": " UT Sanpete", "9wb393": " UT Piute", "9wbfbw": " UT Wayne", "9wbycw": " UT Sanpete", "9wb8jj": " UT Garfield", "9wbtjt": " UT Sevier", "9wbjhj": " UT Millard", "9wbexn": " UT Sevier", "9wbbc0": " UT Garfield", "9wbbc4": " UT Garfield", "9wbepz": " UT Sevier", "9wbf4s": " UT Wayne", "9wb1c1": " UT Beaver", "9wbxhv": " UT Sanpete", "9wbw15": " UT Sanpete", "9wb93w": " UT Wayne", "9wb3r5": " UT Wayne", "9wbppt": " UT Millard", "9wbfve": " UT Wayne", "9wbmdk": " UT Sevier", "9wb6ez": " UT Piute", "9wbxqd": " UT Sanpete", "9wb4fr": " UT Piute", "9wbh7e": " UT Millard", "9wbxqz": " UT Sanpete", "9wbwtd": " UT Sanpete", "9wbhhm": " UT Millard", "9wb688": " UT Piute", "9wb4hj": " UT Piute", "9wbm03": " UT Sevier", "9wb7qe": " UT Sevier", "9wbke6": " UT Sevier", "9wbtfn": " UT Sevier", "9wbtyw": " UT Sevier", "9wbuc2": " UT Sevier", "9wbyc3": " UT Sanpete", "9wbjey": " UT Millard", "9wbvj7": " UT Emery", "9wb7hq": " UT Sevier", "9wbjjs": " UT Millard", "9wbc7s": " UT Wayne", "9wbhmp": " UT Millard", "9wb94q": " UT Wayne", "9wbvrz": " UT Emery", "9wbvzg": " UT Emery", "9wbh7u": " UT Millard", "9wb71u": " UT Sevier", "9wb7b8": " UT Sevier", "9wbk10": " UT Sevier", "9wb78s": " UT Sevier", "9wb74t": " UT Sevier", "9wb71x": " UT Sevier", "9wb799": " UT Sevier", "9wb7s3": " UT Sevier", "9wbvwt": " UT Emery", "9wbdyq": " UT Wayne", "9wb7yh": " UT Sevier", "9wbstb": " UT Sevier", "9wbdyw": " UT Wayne", "9wbg21": " UT Sevier", "9wbx52": " UT Sanpete", "9wb5zj": " UT Sevier", "9wbhg5": " UT Millard", "9wbhfg": " UT Millard", "9wbwwt": " UT Sanpete", "9wbs4w": " UT Sevier", "9wbjt3": " UT Millard", "9wbjxj": " UT Millard", "9wb20v": " UT Garfield", "9wb24j": " UT Garfield", "9wb21s": " UT Garfield", "9wb1bd": " UT Beaver", "9wb566": " UT Sevier", "9wb5un": " UT Sevier", "9wb2jx": " UT Garfield", "9wb3vc": " UT Piute", "9wb464": " UT Beaver", "9wb2m2": " UT Garfield", "9wb0wg": " UT Garfield", "9wb6df": " UT Piute", "9wb560": " UT Sevier", "9wb73e": " UT Sevier", "9wbhq7": " UT Millard", "9wbkth": " UT Sevier", "9wbtp0": " UT Sevier", "9wbmpu": " UT Sevier", "9wbm7g": " UT Sevier", "9wbtds": " UT Sevier", "9wbz58": " UT Emery", "9wbpqb": " UT Millard", "9wb0v9": " UT Garfield", "9wb58b": " UT Sevier", "9wbv2s": " UT Sevier", "9wb0xz": " UT Garfield", "9wb2b1": " UT Garfield", "9wbcgw": " UT Wayne", "9wbe6c": " UT Sevier", "9wbe35": " UT Sevier", "9wbe49": " UT Wayne", "9wbwkx": " UT Sanpete", "9wbs46": " UT Sevier", "9wbdwz": " UT Wayne", "9wbyj5": " UT Emery", "9wbxy6": " UT Sanpete", "9wbxzt": " UT Sanpete", "9wbw8e": " UT Sanpete", "9wbwss": " UT Sanpete", "9wbm0f": " UT Sevier", "9wbk0d": " UT Sevier", "9wb3mg": " UT Piute", "9wb3jx": " UT Piute", "9wb3qh": " UT Piute", "9wb76e": " UT Sevier", "9wbm3h": " UT Sevier", "9wbwcg": " UT Sanpete", "9wbtjn": " UT Sevier", "9wbwjh": " UT Sanpete", "9wbb8r": " UT Garfield", "9wbqcp": " UT Millard", "9wbqbw": " UT Millard", "9wb3rj": " UT Wayne", "9wbjuk": " UT Millard", "9wbm5j": " UT Sevier", "9wb56k": " UT Sevier", "9wbbxb": " UT Garfield", "9wbw7q": " UT Sanpete", "9wb5c6": " UT Sevier", "9wb2k3": " UT Garfield", "9wbsrw": " UT Sevier", "9wbz7u": " UT Emery", "9wbzb2": " UT Sanpete", "9wbz2g": " UT Sanpete", "9wbjt6": " UT Millard", "9wb4hx": " UT Piute", "9wb22d": " UT Garfield", "9wb0p7": " UT Garfield", "9wbhe0": " UT Millard", "9wbjhe": " UT Millard", "9wbv61": " UT Sevier", "9wb650": " UT Piute", "9wbsyp": " UT Sevier", "9wbxj2": " UT Sanpete", "9wbz6f": " UT Sanpete", "9wbkbe": " UT Sevier", "9wbwdb": " UT Sanpete", "9wbzje": " UT Emery", "9wbgbm": " UT Sevier", "9wbw7f": " UT Sanpete", "9wbzv4": " UT Emery", "9wb5ym": " UT Sevier", "9wbpvv": " UT Millard", "9wbv0v": " UT Sevier", "9wbk1u": " UT Sevier", "9wb1s0": " UT Piute", "9wb1kw": " UT Piute", "9wbt1z": " UT Sevier", "9wbpgx": " UT Millard", "9wb7nt": " UT Sevier", "9wbb96": " UT Garfield", "9wb54e": " UT Sevier", "9wb5sp": " UT Sevier", "9wbtmy": " UT Sevier", "9wbt4u": " UT Sevier", "9wb7pm": " UT Sevier", "9wbu8d": " UT Sevier", "9wbnqr": " UT Millard", "9wbuf8": " UT Sevier", "9wb547": " UT Piute", "9wb7pj": " UT Sevier", "9wb5zm": " UT Sevier", "9wb1yt": " UT Piute", "9wb3qv": " UT Piute", "9wbexj": " UT Sevier", "9wbzc9": " UT Sanpete", "9wbw6v": " UT Sanpete", "9wbzd3": " UT Sanpete", "9wbytz": " UT Emery", "9wbzgg": " UT Emery", "9wb1ud": " UT Piute", "9wbw6f": " UT Sanpete", "9wbw5e": " UT Sanpete", "9wb3s5": " UT Piute", "9wb37d": " UT Piute", "9wb1fv": " UT Beaver", "9wb904": " UT Wayne", "9wbpyf": " UT Millard", "9wbe7b": " UT Sevier", "9wbehz": " UT Sevier", "9wbk96": " UT Sevier", "9wbx4c": " UT Sanpete", "9wbekf": " UT Sevier", "9wbjnq": " UT Millard", "9wbfd8": " UT Wayne", "9wbf3z": " UT Wayne", "9wbgb0": " UT Sevier", "9wbkec": " UT Sevier", "9wbxuz": " UT Sanpete", "9wbd8g": " UT Wayne", "9wb3y0": " UT Piute", "9wb3te": " UT Piute", "9wbhj0": " UT Sevier", "9wb6w4": " UT Piute", "9wbptz": " UT Millard", "9wbd2f": " UT Wayne", "9wbxjr": " UT Sanpete", "9wbhvg": " UT Millard", "9wbz7d": " UT Emery", "9wbjn5": " UT Millard", "9wb5cd": " UT Sevier", "9wbph1": " UT Millard", "9wbc0h": " UT Wayne", "9wbhhh": " UT Millard", "9wb914": " UT Garfield", "9wb8cq": " UT Garfield", "9wb89r": " UT Garfield", "9wbe6k": " UT Sevier", "9wbe6m": " UT Sevier", "9wbe6s": " UT Sevier", "9wbku9": " UT Sevier", "9wb8gy": " UT Garfield", "9wbymq": " UT Emery", "9wbz93": " UT Emery", "9wbxqk": " UT Sanpete", "9wbq19": " UT Millard", "9wbmbg": " UT Millard", "9wbxxd": " UT Sanpete", "9wb83k": " UT Garfield", "9wb333": " UT Piute", "9wbtv2": " UT Sevier", "9wb510": " UT Piute", "9wbfg7": " UT Wayne", "9wb6h6": " UT Piute", "9wbswt": " UT Sevier", "9wbtv9": " UT Sevier", "9wbjdf": " UT Millard", "9wbh7c": " UT Millard", "9wbtsw": " UT Sevier", "9wbu2r": " UT Sevier", "9wb6jb": " UT Piute", "9wb0wy": " UT Garfield", "9wbex3": " UT Sevier", "9wbzvz": " UT Emery", "9wbkzm": " UT Sevier", "9wbmbm": " UT Millard", "9wbnnb": " UT Millard", "9wbmwy": " UT Sevier", "9wbn7e": " UT Millard", "9wbnm3": " UT Millard", "9wbjz6": " UT Millard", "9wbcqk": " UT Wayne", "9wbs0v": " UT Sevier", "9wbthq": " UT Sevier", "9wb4f0": " UT Piute", "9wb5j3": " UT Piute", "9wbmvx": " UT Sevier", "9wb1w6": " UT Piute", "9wb1wb": " UT Piute", "9wb7qv": " UT Sevier", "9wbbuq": " UT Garfield", "9wbb8w": " UT Garfield", "9wb2ev": " UT Garfield", "9wb44j": " UT Beaver", "9wb2my": " UT Garfield", "9wbekb": " UT Sevier", "9wbw4e": " UT Sanpete", "9wb9sq": " UT Wayne", "9wb2g4": " UT Garfield", "9wb3sh": " UT Piute", "9wbdvp": " UT Wayne", "9wb152": " UT Piute", "9wb9e9": " UT Wayne", "9wb3f0": " UT Piute", "9wb56x": " UT Sevier", "9wbe86": " UT Sevier", "9wb5gr": " UT Sevier", "9wbfs2": " UT Wayne", "9wb2z2": " UT Garfield", "9wbhjm": " UT Sevier", "9wbt12": " UT Sevier", "9wbee6": " UT Sevier", "9wbwhq": " UT Sanpete", "9wbwhs": " UT Sanpete", "9wbu3x": " UT Sevier", "9wbde5": " UT Wayne", "9wbcbs": " UT Wayne", "9wb5rc": " UT Sevier", "9wb5pw": " UT Sevier", "9wb7rx": " UT Sevier", "9wb7rj": " UT Sevier", "9wbke4": " UT Sevier", "9wbkdb": " UT Sevier", "9wb1us": " UT Piute", "9wb55w": " UT Sevier", "9wbpwj": " UT Millard", "9wbmpk": " UT Sevier", "9wbkxy": " UT Sevier", "9wbxs2": " UT Sanpete", "9wbuu9": " UT Emery", "9wbdhw": " UT Wayne", "9wbpys": " UT Millard", "9wb9ng": " UT Wayne", "9wbep8": " UT Wayne", "9wb8wu": " UT Garfield", "9wbkst": " UT Sevier", "9wbqg1": " UT Sanpete", "9wbhpf": " UT Sevier", "9wbq9t": " UT Millard", "9wbptv": " UT Millard", "9wbwgz": " UT Sanpete", "9wbt2q": " UT Sevier", "9wb51d": " UT Piute", "9wbk46": " UT Sevier", "9wbdvk": " UT Wayne", "9wbmd3": " UT Sevier", "9wb5br": " UT Millard", "9wbq42": " UT Millard", "9wb54q": " UT Sevier", "9wb7u8": " UT Sevier", "9wbh1r": " UT Millard", "9wbmys": " UT Sevier", "9wbhwq": " UT Sevier", "9wbzg2": " UT Sanpete", "9wbzgn": " UT Sanpete", "9wbzfu": " UT Sanpete", "9wbdtq": " UT Wayne", "9wbeej": " UT Sevier", "9wb77n": " UT Sevier", "9wb77r": " UT Sevier", "9wb4v2": " UT Piute", "9wbzsr": " UT Emery", "9wbkdh": " UT Sevier", "9wbz8z": " UT Sanpete", "9wb9e4": " UT Wayne", "9wbdd9": " UT Wayne", "9wbdd7": " UT Wayne", "9wbep4": " UT Sevier", "9wb0xx": " UT Garfield", "9wbd7e": " UT Wayne", "9wb8nu": " UT Garfield", "9wb2ft": " UT Garfield", "9wbtx1": " UT Sevier", "9wb2by": " UT Garfield", "9wbzv8": " UT Emery", "9wb1c2": " UT Beaver", "9wbq09": " UT Millard", "9wb9yr": " UT Wayne", "9wbk5v": " UT Sevier", "9wbsvz": " UT Sevier", "9wbm8r": " UT Millard", "9wbmcm": " UT Millard", "9wb3u2": " UT Piute", "9wbe88": " UT Sevier", "9wbukk": " UT Emery", "9wb3fp": " UT Piute", "9wbj01": " UT Millard", "9wbxxs": " UT Sanpete", "9wbz8v": " UT Sanpete", "9wbddg": " UT Wayne", "9wb7my": " UT Sevier", "9wb8bs": " UT Garfield", "9wb8gq": " UT Garfield", "9wbep6": " UT Wayne", "9wb8ew": " UT Garfield", "9wb6dx": " UT Piute", "9wbhqd": " UT Sevier", "9wbksv": " UT Sevier", "9wb8u4": " UT Garfield", "9wbm2y": " UT Sevier", "9wbgs8": " UT Emery", "9wb8e2": " UT Garfield", "9wbh5c": " UT Millard", "9wbh5b": " UT Sevier", "9wbmte": " UT Sevier", "9wb1rf": " UT Garfield", "9wb1pt": " UT Piute", "9wb0zr": " UT Garfield", "9wbpts": " UT Millard", "9wb1em": " UT Piute", "9wb8h4": " UT Garfield", "9wbptu": " UT Millard", "9wbhhq": " UT Millard", "9wbs0p": " UT Sevier", "9wbs28": " UT Sevier", "9wb54n": " UT Sevier", "9wbkt3": " UT Sevier", "9wbpwn": " UT Millard", "9wb443": " UT Beaver", "9wbq1p": " UT Millard", "9wb9r7": " UT Wayne", "9wbfbp": " UT Wayne", "9wbu03": " UT Sevier", "9wbu08": " UT Sevier", "9wbq9z": " UT Millard", "9wbr31": " UT Millard", "9wb88j": " UT Garfield", "9wb86k": " UT Garfield", "9wbdgt": " UT Wayne", "9wby8t": " UT Sanpete", "9wb2sy": " UT Garfield", "9wbe28": " UT Sevier", "9wbj7f": " UT Millard", "9wbu23": " UT Sevier", "9wbdn0": " UT Wayne", "9wbsvu": " UT Sevier", "9wbdyj": " UT Wayne", "9wb5nh": " UT Sevier", "9wb74x": " UT Sevier", "9wb5kk": " UT Sevier", "9wbkvw": " UT Sevier", "9wbyh7": " UT Emery", "9wbkvz": " UT Sevier", "9wb9gv": " UT Wayne", "9wb91t": " UT Garfield", "9wbu11": " UT Sevier", "9wbuct": " UT Sevier", "9wbufc": " UT Sevier", "9wbszs": " UT Sevier", "9wbmws": " UT Sevier", "9wbmrx": " UT Sevier", "9wbkqc": " UT Sevier", "9wbmwj": " UT Sevier", "9wbty6": " UT Sevier", "9wbse0": " UT Sevier", "9wbmxh": " UT Sevier", "9wbejf": " UT Wayne", "9wb9tn": " UT Wayne", "9wb5kp": " UT Sevier", "9wb3d1": " UT Piute", "9wbqwp": " UT Sanpete", "9wb78z": " UT Sevier", "9wbccz": " UT Wayne", "9wb310": " UT Garfield", "9wbf27": " UT Wayne", "9wbjm2": " UT Millard", "9wbecm": " UT Sevier", "9wb55u": " UT Sevier", "9wb5hm": " UT Sevier", "9wbk78": " UT Sevier", "9wbs4b": " UT Sevier", "9wb71v": " UT Sevier", "9wb8pr": " UT Garfield", "9wb41b": " UT Beaver", "9wbr30": " UT Millard", "9wbq6n": " UT Millard", "9wbpp8": " UT Millard", "9wbr2z": " UT Millard", "9wbmp0": " UT Sevier", "9wb7ds": " UT Sevier", "9wbh7m": " UT Millard", "9wbdup": " UT Wayne", "9wbze3": " UT Sanpete", "9wbze9": " UT Emery", "9wbz8k": " UT Sanpete", "9wb50u": " UT Sevier", "9wb73q": " UT Sevier", "9wbefk": " UT Sevier", "9wbeeq": " UT Sevier", "9wb5t8": " UT Sevier", "9wbrmr": " UT Sanpete", "9wb4cz": " UT Piute", "9wbk9y": " UT Sevier", "9wb60v": " UT Piute", "9wb6kd": " UT Piute", "9wbdds": " UT Wayne", "9wb438": " UT Beaver", "9wb79g": " UT Sevier", "9wb53p": " UT Piute", "9wb52v": " UT Sevier", "9wbjqw": " UT Millard", "9wbdj5": " UT Wayne", "9wbjqq": " UT Millard", "9wbkzk": " UT Sevier", "9wby8s": " UT Sanpete", "9wb5t6": " UT Sevier", "9wbe5w": " UT Sevier", "9wbu1h": " UT Sevier", "9wb4f3": " UT Piute", "9wb7ep": " UT Sevier", "9wbkun": " UT Sevier", "9wbkgy": " UT Sevier", "9wbe6b": " UT Sevier", "9wbjwm": " UT Millard", "9wbyfh": " UT Sanpete", "9wbycd": " UT Sanpete", "9wbjg3": " UT Millard", "9wb2p8": " UT Garfield", "9wbx4b": " UT Sanpete", "9wbx1b": " UT Sanpete", "9wb5kx": " UT Sevier", "9wb5u4": " UT Sevier", "9wb7r2": " UT Sevier", "9wb5fk": " UT Sevier", "9wbwp0": " UT Sevier", "9wbykn": " UT Emery", "9wbtyx": " UT Sevier", "9wbz6p": " UT Sanpete", "9wb68x": " UT Piute", "9wb6bf": " UT Piute", "9wbkx7": " UT Sevier", "9wb1p1": " UT Piute", "9wb94s": " UT Wayne", "9wb946": " UT Wayne", "9wbr4p": " UT Millard", "9wb52s": " UT Sevier", "9wbxuy": " UT Sanpete", "9wbtxn": " UT Sevier", "9wbetd": " UT Sevier", "9wbecc": " UT Sevier", "9wbxrb": " UT Sanpete", "9wbzwt": " UT Emery", "9wb0m3": " UT Garfield", "9wbwfw": " UT Sanpete", "9wb4du": " UT Piute", "9wbmrw": " UT Sevier", "9wbjpx": " UT Sevier", "9wberf": " UT Sevier", "9wbgfb": " UT Sevier", "9wber9": " UT Sevier", "9wbr18": " UT Millard", "9wb78w": " UT Sevier", "9wb3r1": " UT Wayne", "9wbm4f": " UT Sevier", "9wbfky": " UT Wayne", "9wbcnn": " UT Wayne", "9wbz86": " UT Sanpete", "9wb18j": " UT Beaver", "9wb6sn": " UT Piute", "9wb1sq": " UT Piute", "9wb6vp": " UT Piute", "9wbxq4": " UT Sanpete", "9wbbt6": " UT Garfield", "9wb47n": " UT Piute", "9wbv9j": " UT Sevier", "9wbw6w": " UT Sanpete", "9wbyth": " UT Emery", "9wbxrn": " UT Sanpete", "9wbw5y": " UT Sanpete", "9wbvgz": " UT Emery", "9wbd6t": " UT Wayne", "9wbq7s": " UT Sanpete", "9wbpvg": " UT Millard", "9wbtgu": " UT Sevier", "9wbs32": " UT Sevier", "9wbeks": " UT Sevier", "9wbekm": " UT Sevier", "9wbdbf": " UT Wayne", "9wbc91": " UT Wayne", "9wbq1k": " UT Millard", "9wbq24": " UT Millard", "9wbppw": " UT Millard", "9wbtjs": " UT Sevier", "9wbc34": " UT Wayne", "9wbsv2": " UT Sevier", "9wbdk0": " UT Wayne", "9wb9vx": " UT Wayne", "9wb4g5": " UT Piute", "9wbbuz": " UT Garfield", "9wbwtr": " UT Sanpete", "9wb2xg": " UT Garfield", "9wbeh5": " UT Sevier", "9wbwsc": " UT Sanpete", "9wbmn2": " UT Sevier", "9wbk7c": " UT Sevier", "9wbe30": " UT Sevier", "9wbbhm": " UT Garfield", "9wbdpy": " UT Wayne", "9wb4g1": " UT Piute", "9wbkfy": " UT Sevier", "9wbyg3": " UT Sanpete", "9wb330": " UT Piute", "9wbwqt": " UT Sanpete", "9wbwfq": " UT Sanpete", "9wbysh": " UT Emery", "9wbt9z": " UT Sevier", "9wbtf1": " UT Sevier", "9wbt2v": " UT Sevier", "9wb8xz": " UT Garfield", "9wbbbh": " UT Garfield", "9wbysp": " UT Emery", "9wbmxp": " UT Sevier", "9wb68g": " UT Piute", "9wbzqj": " UT Emery", "9wbm1f": " UT Sevier", "9wb1c9": " UT Beaver", "9wbsxm": " UT Sevier", "9wbdnk": " UT Wayne", "9wbhgn": " UT Millard", "9wbhvj": " UT Millard", "9wbkxb": " UT Sevier", "9wbzcc": " UT Sanpete", "9wbzc7": " UT Sanpete", "9wbz2h": " UT Sanpete", "9wbm3n": " UT Sevier", "9wbkxs": " UT Sevier", "9wbs29": " UT Sevier", "9wbqg7": " UT Sanpete", "9wb431": " UT Beaver", "9wbxqg": " UT Sanpete", "9wb3ch": " UT Piute", "9wb4p5": " UT Piute", "9wb7e9": " UT Sevier", "9wbkc5": " UT Sevier", "9wb2bp": " UT Garfield", "9wb8pc": " UT Garfield", "9wb2xk": " UT Garfield", "9wbcj0": " UT Garfield", "9wbbvq": " UT Garfield", "9wbeg2": " UT Sevier", "9wbe9k": " UT Sevier", "9wbseq": " UT Sevier", "9wbtm4": " UT Sevier", "9wb4y3": " UT Piute", "9wbkz7": " UT Sevier", "9wb9z3": " UT Wayne", "9wb9zk": " UT Wayne", "9wb9z6": " UT Wayne", "9wbdvh": " UT Wayne", "9wbjzr": " UT Millard", "9wbjzb": " UT Millard", "9wbe26": " UT Sevier", "9wbjzf": " UT Millard", "9wbjxt": " UT Millard", "9wb45k": " UT Beaver", "9wbxkj": " UT Sanpete", "9wbgt5": " UT Emery", "9wb77m": " UT Sevier", "9wb4qb": " UT Piute", "9wbs5r": " UT Sevier", "9wbb2k": " UT Garfield", "9wb4tv": " UT Piute", "9wbxq3": " UT Sanpete", "9wby49": " UT Sevier", "9wb7v9": " UT Sevier", "9wbzhg": " UT Emery", "9wbk58": " UT Sevier", "9wbxpd": " UT Sanpete", "9wbv1m": " UT Sevier", "9wb0sz": " UT Garfield", "9wbhsx": " UT Millard", "9wb607": " UT Piute", "9wbhtb": " UT Millard", "9wbbj2": " UT Garfield", "9wbgbs": " UT Sevier", "9wb78u": " UT Sevier", "9wbvuy": " UT Emery", "9wbyg7": " UT Sanpete", "9wbdu4": " UT Wayne", "9wbcgn": " UT Wayne", "9wb6ht": " UT Piute", "9wbyeu": " UT Emery", "9wbvff": " UT Sevier", "9wb2q1": " UT Garfield", "9wbh01": " UT Millard", "9wbsbp": " UT Sevier", "9wbmxn": " UT Sevier", "9wbze4": " UT Sanpete", "9wb3nc": " UT Piute", "9wbbcf": " UT Garfield", "9wbvgp": " UT Sevier", "9wbmjk": " UT Sevier", "9wby8g": " UT Sanpete", "9wb76p": " UT Sevier", "9wbz9d": " UT Sanpete", "9wbk1e": " UT Sevier", "9wb4w3": " UT Piute", "9wb5d3": " UT Sevier", "9wbjqd": " UT Millard", "9wbq6d": " UT Millard", "9wbwn3": " UT Sevier", "9wbk6s": " UT Sevier", "9wb4sf": " UT Piute", "9wb7hc": " UT Sevier", "9wbetw": " UT Sevier", "9wbdtn": " UT Wayne", "9wbew3": " UT Sevier", "9wbdsz": " UT Wayne", "9wb4sp": " UT Piute", "9wbrtw": " UT Sanpete", "9wb8fw": " UT Garfield", "9wb4cy": " UT Piute", "9wbekg": " UT Sevier", "9wb9vq": " UT Wayne", "9wbsx8": " UT Sevier", "9wbz8d": " UT Sanpete", "9wb7ru": " UT Sevier", "9wbe2x": " UT Sevier", "9wbcc5": " UT Wayne", "9wbwsk": " UT Sanpete", "9wb4bu": " UT Piute", "9wbzv3": " UT Emery", "9wbdk8": " UT Wayne", "9wb59b": " UT Sevier", "9wbztv": " UT Emery", "9wb8x2": " UT Garfield", "9wbz22": " UT Sanpete", "9wbhjp": " UT Millard", "9wbhk9": " UT Millard", "9wbhkv": " UT Millard", "9wbegh": " UT Sevier", "9wb2zt": " UT Garfield", "9wbt2e": " UT Sevier", "9wb4ck": " UT Piute", "9wbm60": " UT Sevier", "9wbd9f": " UT Wayne", "9wbuf3": " UT Sevier", "9wbmwc": " UT Sevier", "9wbdj3": " UT Wayne", "9wb661": " UT Piute", "9wb40k": " UT Beaver", "9wbdsp": " UT Wayne", "9wbjxb": " UT Millard", "9wbjxk": " UT Millard", "9wb469": " UT Beaver", "9wb1fw": " UT Beaver", "9wbwc0": " UT Sanpete", "9wbwwf": " UT Sanpete", "9wb9ph": " UT Wayne", "9wb44e": " UT Beaver", "9wb38u": " UT Piute", "9wbsb6": " UT Sevier", "9wbsek": " UT Sevier", "9wbf42": " UT Wayne", "9wbtbd": " UT Sevier", "9wb4sd": " UT Piute", "9wbej3": " UT Wayne", "9wbs59": " UT Sevier", "9wb96h": " UT Wayne", "9wbwvy": " UT Sanpete", "9wbwu6": " UT Sanpete", "9wb314": " UT Piute", "9wb69x": " UT Piute", "9wbrkn": " UT Sanpete", "9wb406": " UT Beaver", "9wb9zr": " UT Wayne", "9wbkep": " UT Sevier", "9wbkeq": " UT Sevier", "9wbmh4": " UT Sevier", "9wbkgs": " UT Sevier", "9wbm5f": " UT Sevier", "9wbww1": " UT Sanpete", "9wb17b": " UT Piute", "9wbz64": " UT Sanpete", "9wbj4j": " UT Millard", "9wbugq": " UT Sevier", "9wbjhb": " UT Millard", "9wb4eb": " UT Piute", "9wbxzb": " UT Sanpete", "9wbvu6": " UT Emery", "9wbf6y": " UT Wayne", "9wbk7q": " UT Sevier", "9wbk5t": " UT Sevier", "9wb7gg": " UT Sevier", "9wbeu2": " UT Sevier", "9wbt70": " UT Sevier", "9wbexy": " UT Sevier", "9wbv4j": " UT Sevier", "9wbtsc": " UT Sevier", "9wbbr3": " UT Garfield", "9wbz6b": " UT Sanpete", "9wbjt9": " UT Millard", "9wb40v": " UT Beaver", "9wbcrn": " UT Wayne", "9wbh7z": " UT Millard", "9wb855": " UT Garfield", "9wb1w9": " UT Piute", "9wb6qg": " UT Piute", "9wbywv": " UT Emery", "9wb92m": " UT Wayne", "9wb555": " UT Sevier", "9wb1cs": " UT Beaver", "9wbdd3": " UT Wayne", "9wbet9": " UT Sevier", "9wbqqr": " UT Sanpete", "9wbzzn": " UT Emery", "9wbu15": " UT Sevier", "9wbcgv": " UT Wayne", "9wbecb": " UT Sevier", "9wbp4k": " UT Millard", "9wbs4c": " UT Sevier", "9wb4zt": " UT Piute", "9wbw3q": " UT Sanpete", "9wbz6k": " UT Sanpete", "9wbxz6": " UT Sanpete", "9wbwvm": " UT Sanpete", "9wb4yu": " UT Piute", "9wbtzk": " UT Sevier", "9wbjn6": " UT Millard", "9wb7uj": " UT Sevier", "9wbjqb": " UT Millard", "9wbjtf": " UT Millard", "9wb544": " UT Piute", "9wbwh6": " UT Sanpete", "9wb7ew": " UT Sevier", "9wbnr7": " UT Millard", "9wb853": " UT Garfield", "9wbsy0": " UT Sevier", "9wbcsp": " UT Wayne", "9wbe6w": " UT Sevier", "9wbed3": " UT Sevier", "9wbtu2": " UT Sevier", "9wbtu0": " UT Sevier", "9wbzxq": " UT Carbon", "9wbnxm": " UT Millard", "9wbnmn": " UT Millard", "9wbnxk": " UT Millard", "9wb9u4": " UT Wayne", "9wbvdm": " UT Sevier", "9wb2q8": " UT Garfield", "9wb97j": " UT Wayne", "9wbww6": " UT Sanpete", "9wbvgu": " UT Emery", "9wbpwc": " UT Millard", "9wbex2": " UT Sevier", "9wb8e3": " UT Garfield", "9wbybm": " UT Sanpete", "9wbxsx": " UT Sanpete", "9wbq44": " UT Millard", "9wbqng": " UT Sevier", "9wbkcf": " UT Sevier", "9wbm8w": " UT Millard", "9wbmc1": " UT Millard", "9wb55s": " UT Sevier", "9wby9k": " UT Sanpete", "9wb28d": " UT Garfield", "9wb6d9": " UT Piute", "9wb2dk": " UT Garfield", "9wb6bn": " UT Piute", "9wbe5d": " UT Sevier", "9wbq8z": " UT Millard", "9wb1bu": " UT Beaver", "9wbu7p": " UT Sevier", "9wbyb7": " UT Sanpete", "9wbepg": " UT Sevier", "9wb6z0": " UT Piute", "9wbs8s": " UT Sevier", "9wbhdw": " UT Millard", "9wb7c5": " UT Sevier", "9wb0xb": " UT Garfield", "9wbxsz": " UT Sanpete", "9wb7ms": " UT Sevier", "9wbwjr": " UT Sanpete", "9wbybg": " UT Sanpete", "9wbheh": " UT Millard", "9wbyff": " UT Sanpete", "9wby9y": " UT Sanpete", "9wby6g": " UT Sanpete", "9wby7k": " UT Sanpete", "9wbpxk": " UT Millard", "9wbxmf": " UT Sanpete", "9wbdqp": " UT Wayne", "9wbbuk": " UT Garfield", "9wbsvy": " UT Sevier", "9wbvvr": " UT Emery", "9wbes5": " UT Sevier", "9wbes4": " UT Sevier", "9wbesk": " UT Sevier", "9wbkzj": " UT Sevier", "9wb1w7": " UT Piute", "9wbk35": " UT Sevier", "9wbjem": " UT Millard", "9wbxsp": " UT Sanpete", "9wb86t": " UT Garfield", "9wb86s": " UT Garfield", "9wb2z8": " UT Garfield", "9wbc05": " UT Wayne", "9wb34u": " UT Piute", "9wb9r4": " UT Wayne", "9wb9qf": " UT Wayne", "9wb1gn": " UT Beaver", "9wb4p0": " UT Piute", "9wb43v": " UT Beaver", "9wb487": " UT Beaver", "9wb48e": " UT Beaver", "9wbdwy": " UT Wayne", "9wb6gm": " UT Piute", "9wb6cq": " UT Piute", "9wb6cm": " UT Piute", "9wb6cy": " UT Piute", "9wb6cx": " UT Piute", "9wben5": " UT Sevier", "9wb77x": " UT Sevier", "9wb7wc": " UT Sevier", "9wbees": " UT Sevier", "9wb5c2": " UT Sevier", "9wb59x": " UT Sevier", "9wb7gk": " UT Sevier", "9wb7uh": " UT Sevier", "9wbs4n": " UT Sevier", "9wbse5": " UT Sevier", "9wbs8t": " UT Sevier", "9wbs8m": " UT Sevier", "9wbmh3": " UT Sevier", "9wbmh7": " UT Sevier", "9wbmsn": " UT Sevier", "9wbmy6": " UT Sevier", "9wbmy7": " UT Sevier", "9wbynu": " UT Emery", "9wbyq2": " UT Emery", "9wbyqx": " UT Emery", "9wbqd1": " UT Millard", "9wbwcf": " UT Sanpete", "9wbx1c": " UT Sanpete", "9wbxrs": " UT Sanpete", "9wbzeb": " UT Emery", "9wbz92": " UT Sanpete", "9wb49p": " UT Piute", "9wbcw7": " UT Wayne", "9wb606": " UT Piute", "9wbxvp": " UT Sanpete", "9wbkrv": " UT Sevier", "9wbf2p": " UT Wayne", "9wbwd0": " UT Sanpete", "9wbfep": " UT Wayne", "9wbh5x": " UT Millard", "9wbf81": " UT Wayne", "9wbk4q": " UT Sevier", "9wbdnv": " UT Wayne", "9wb5xn": " UT Sevier", "9wb2g7": " UT Garfield", "9wbk93": " UT Sevier", "9wbmky": " UT Sevier", "9wb707": " UT Sevier", "9wbxtz": " UT Sanpete", "9wbdqm": " UT Wayne", "9wb4uc": " UT Piute", "9wbnm8": " UT Millard", "9wb9u1": " UT Wayne", "9wbdqk": " UT Wayne", "9wbdh0": " UT Wayne", "9wbhkk": " UT Millard", "9wb9xg": " UT Wayne", "9wb9xb": " UT Wayne", "9wbjv1": " UT Millard", "9wb68d": " UT Piute", "9wb1fy": " UT Beaver", "9wbdw7": " UT Wayne", "9wbykx": " UT Emery", "9wb9rr": " UT Wayne", "9wbdj4": " UT Wayne", "9wb61r": " UT Piute", "9wb9ve": " UT Wayne", "9wbdmq": " UT Wayne", "9wbh61": " UT Millard", "9wbmw3": " UT Sevier", "9wb5hf": " UT Piute", "9wbcu4": " UT Wayne", "9wb576": " UT Sevier", "9wbcuh": " UT Wayne", "9wbfcz": " UT Wayne", "9wbfcu": " UT Wayne", "9wbyr4": " UT Emery", "9wbzse": " UT Emery", "9wbdtb": " UT Wayne", "9wbjsc": " UT Millard", "9wbdrn": " UT Wayne", "9wbh53": " UT Millard", "9wbb2f": " UT Garfield", "9wb1hy": " UT Piute", "9wb1jj": " UT Piute", "9wbdxw": " UT Wayne", "9wbdwh": " UT Wayne", "9wbh1c": " UT Millard", "9wbdqt": " UT Wayne", "9wb9wg": " UT Wayne", "9wbff6": " UT Piute", "9wbh9f": " UT Millard", "9wb73j": " UT Sevier", "9wbdjs": " UT Wayne", "9wbh4f": " UT Sevier", "9wb9pe": " UT Wayne", "9wb9ps": " UT Wayne", "9wb3gh": " UT Piute", "9wb9nu": " UT Wayne", "9wb3fk": " UT Piute", "9wbf8n": " UT Wayne", "9wbf8t": " UT Wayne", "9wb1f6": " UT Beaver", "9wb4w0": " UT Piute", "9wberr": " UT Sevier", "9wb58y": " UT Sevier", "9wb738": " UT Sevier", "9wb9qv": " UT Wayne", "9wbmw7": " UT Sevier", "9wb8pz": " UT Garfield", "9wbym1": " UT Emery", "9wbkqr": " UT Sevier", "9wb4x1": " UT Piute", "9wb6b5": " UT Piute", "9wb66j": " UT Piute", "9wb6cg": " UT Piute", "9wb8xm": " UT Garfield", "9wb5cf": " UT Sevier", "9wbdrq": " UT Wayne", "9wbk0h": " UT Sevier", "9wbyqu": " UT Emery", "9wbxug": " UT Sanpete", "9wbxuu": " UT Sanpete", "9wbh46": " UT Millard", "9wbwxu": " UT Sanpete", "9wbjes": " UT Millard", "9wbh32": " UT Millard", "9wbc03": " UT Garfield", "9wb35n": " UT Piute", "9wb71r": " UT Sevier", "9wbdxj": " UT Wayne", "9wbej2": " UT Wayne", "9wb57z": " UT Sevier", "9wb5gm": " UT Sevier", "9wbsf2": " UT Sevier", "9wbcgs": " UT Wayne", "9wb9rt": " UT Wayne", "9wb4us": " UT Piute", "9wbb3h": " UT Garfield", "9wb44p": " UT Beaver", "9wbg50": " UT Wayne", "9wbj7t": " UT Millard", "9wbdyz": " UT Wayne", "9wbdzn": " UT Wayne", "9wbc0z": " UT Wayne", "9wbf2j": " UT Wayne", "9wb553": " UT Piute", "9wbnwy": " UT Millard", "9wbh79": " UT Millard", "9wb4nz": " UT Piute", "9wb5t1": " UT Sevier", "9wbdr5": " UT Wayne", "9wbf8k": " UT Wayne", "9wb7dc": " UT Sevier", "9wbufe": " UT Sevier", "9wb7cf": " UT Sevier", "9wbc2j": " UT Wayne", "9wbze6": " UT Emery", "9wb1qq": " UT Piute", "9wbhfe": " UT Millard", "9wbhfu": " UT Millard", "9wb8ru": " UT Garfield", "9wb1qf": " UT Piute", "9wbsxb": " UT Sevier", "9wbk90": " UT Sevier", "9wb7wg": " UT Sevier", "9wbbbx": " UT Garfield", "9wb6d3": " UT Piute", "9wbvhn": " UT Emery", "9wb8zy": " UT Garfield", "9wb63x": " UT Piute", "9wb66n": " UT Piute", "9wbrbh": " UT Juab", "9wbde8": " UT Wayne", "9wbd7w": " UT Wayne", "9wb70y": " UT Sevier", "9wbv96": " UT Sevier", "9wb18q": " UT Beaver", "9wbx5k": " UT Sanpete", "9wbxkw": " UT Sanpete", "9wbx6b": " UT Sanpete", "9wbw4x": " UT Sanpete", "9wbsqz": " UT Sevier", "9wbyms": " UT Emery", "9wb6b9": " UT Piute", "9wb71h": " UT Sevier", "9wb7bf": " UT Sevier", "9wb7bc": " UT Sevier", "9wbb3j": " UT Garfield", "9wb4y2": " UT Piute", "9wb7e1": " UT Sevier", "9wbf83": " UT Wayne", "9wb6en": " UT Piute", "9wb4y4": " UT Piute", "9wb4vg": " UT Piute", "9wb9rp": " UT Wayne", "9wbffn": " UT Wayne", "9wbnqz": " UT Millard", "9wbh6z": " UT Millard", "9wbwdd": " UT Sanpete", "9wbmwm": " UT Sevier", "9wbbwn": " UT Garfield", "9wbmwk": " UT Sevier", "9wbv62": " UT Sevier", "9wb76s": " UT Sevier", "9wbx50": " UT Sanpete", "9wbx7b": " UT Sanpete", "9wbudq": " UT Sevier", "9wb9v6": " UT Wayne", "9wbf8x": " UT Wayne", "9wbnnk": " UT Millard", "9wb1yz": " UT Piute", "9wb4nb": " UT Piute", "9wbfbk": " UT Wayne", "9wb4yr": " UT Piute", "9wbmr8": " UT Sevier", "9wbpzq": " UT Juab", "9wbv5t": " UT Emery", "9wb9tu": " UT Wayne", "9wbcbe": " UT Wayne", "9wbk97": " UT Sevier", "9wb8zv": " UT Garfield", "9wbccr": " UT Wayne", "9wbfem": " UT Wayne", "9wbdzz": " UT Wayne", "9wbdqe": " UT Wayne", "9wb1b0": " UT Beaver", "9wbbst": " UT Garfield", "9wbyqf": " UT Emery", "9wbdrm": " UT Wayne", "9wb50k": " UT Sevier", "9wb1cy": " UT Beaver", "9wb7e0": " UT Sevier", "9wbdxb": " UT Wayne", "9wb7dx": " UT Sevier", "9wb5mq": " UT Sevier", "9wbk9k": " UT Sevier", "9wbbvp": " UT Garfield", "9wb50n": " UT Sevier", "9wbwgh": " UT Sanpete", "9wb55f": " UT Piute", "9wb9r0": " UT Wayne", "9wbfcg": " UT Wayne", "9wbh36": " UT Millard", "9wbjpd": " UT Sevier", "9wb7b2": " UT Sevier", "9wbh6s": " UT Millard", "9wbwfp": " UT Sanpete", "9wbjrs": " UT Millard", "9wbdry": " UT Wayne", "9wbdvu": " UT Wayne", "9wb9zy": " UT Wayne", "9wbdxy": " UT Wayne", "9wb63d": " UT Piute", "9wb4ds": " UT Piute", "9wbdkc": " UT Wayne", "9wb5n8": " UT Piute", "9wbkex": " UT Sevier", "9wb66e": " UT Piute", "9wbju0": " UT Millard", "9wb7f3": " UT Sevier", "9wbdje": " UT Wayne", "9wbdjm": " UT Wayne", "9wb8qv": " UT Garfield", "9wb5e1": " UT Sevier", "9wb6cc": " UT Piute", "9wb4zh": " UT Piute", "9wbdrw": " UT Wayne", "9wbkdp": " UT Sevier", "9wbtcm": " UT Sanpete", "9wb9rh": " UT Wayne", "9wb69n": " UT Piute", "9wbnyb": " UT Millard", "9wbjsh": " UT Millard", "9wbjev": " UT Millard", "9wbd7q": " UT Wayne", "9wb7b9": " UT Sevier", "9wb78x": " UT Sevier", "9wbmwe": " UT Sevier", "9wb5wn": " UT Sevier", "9wbmwv": " UT Sevier", "9wb5tf": " UT Sevier", "9wbx69": " UT Sanpete", "9wbjm9": " UT Millard", "9wbjn7": " UT Millard", "9wbejh": " UT Sevier", "9wbhk8": " UT Millard", "9wbpyh": " UT Millard", "9wbjx1": " UT Millard", "9wbjrq": " UT Millard", "9wbjrj": " UT Millard", "9wbmp4": " UT Sevier", "9wb76r": " UT Sevier", "9wb64q": " UT Piute", "9wb3f1": " UT Piute", "9wbhd4": " UT Millard", "9wbh3y": " UT Millard", "9wb7d3": " UT Sevier", "9wbjrk": " UT Millard", "9wbtxq": " UT Sevier", "9wbtxx": " UT Sevier", "9wbtzb": " UT Sevier", "9wb45d": " UT Beaver", "9wb9pn": " UT Wayne", "9wbc06": " UT Wayne", "9wbbv9": " UT Garfield", "9wbb9r": " UT Garfield", "9wbv8h": " UT Sevier", "9wbv80": " UT Sevier", "9wbc56": " UT Wayne", "9wbye0": " UT Sanpete", "9wbwxy": " UT Sanpete", "9wbye9": " UT Emery", "9wbzh9": " UT Emery", "9wbbve": " UT Garfield", "9wb6vh": " UT Piute", "9wbpyt": " UT Millard", "9wbzxv": " UT Emery", "9wbk08": " UT Sevier", "9wbc07": " UT Wayne", "9wb5j4": " UT Piute", "9wbb8m": " UT Garfield", "9wbfcy": " UT Wayne", "9wbwbb": " UT Sanpete", "9wbypz": " UT Emery", "9wbk0g": " UT Sevier", "9wbds8": " UT Wayne", "9wbvuz": " UT Emery", "9wbyqw": " UT Emery", "9wbyqc": " UT Emery", "9wb35h": " UT Piute", "9wb8vy": " UT Garfield", "9wbynw": " UT Emery", "9wb9t1": " UT Wayne", "9wbypr": " UT Emery", "9wbynm": " UT Emery", "9wbqz2": " UT Sanpete", "9wb4tz": " UT Piute", "9wbmwt": " UT Sevier", "9wb865": " UT Garfield", "9wb3pp": " UT Wayne", "9wbe9m": " UT Sevier", "9wbv01": " UT Sevier", "9wb28w": " UT Garfield", "9wbsk3": " UT Sevier", "9wbzdk": " UT Sanpete", "9wbz3r": " UT Sanpete", "9wbe6h": " UT Sevier", "9wb6fx": " UT Piute", "9wbjmm": " UT Millard", "9wb6b3": " UT Piute", "9wbe1j": " UT Sevier", "9wbe1q": " UT Sevier", "9wbe1n": " UT Sevier", "9wbdzf": " UT Wayne", "9wbvsu": " UT Emery", "9wbyr5": " UT Emery", "9wbjq2": " UT Millard", "9wb3c9": " UT Piute", "9wbb05": " UT Garfield", "9wb79h": " UT Sevier", "9wb80e": " UT Garfield", "9wbyh8": " UT Emery", "9wbv2t": " UT Sevier", "9wb6ft": " UT Piute", "9wbeet": " UT Sevier", "9wbjy6": " UT Millard", "9wbz53": " UT Emery", "9wb1j0": " UT Garfield", "9wbxq6": " UT Sanpete", "9wbnpq": " UT Millard", "9wbtuv": " UT Sevier", "9wb357": " UT Piute", "9wb82m": " UT Garfield", "9wb5ce": " UT Sevier", "9wbpv8": " UT Millard", "9wb0qv": " UT Garfield", "9wbven": " UT Sevier", "9wbby2": " UT Garfield", "9wbvsg": " UT Emery", "9wbb94": " UT Garfield", "9wbe1m": " UT Sevier", "9wb4fc": " UT Piute", "9wbf09": " UT Wayne", "9wbxtx": " UT Sanpete", "9wbze8": " UT Emery", "9wbzs4": " UT Emery", "9wbzeg": " UT Emery", "9wbwg0": " UT Sanpete", "9wbzrf": " UT Emery", "9wbzmq": " UT Emery", "9wbcme": " UT Wayne", "9wbxxf": " UT Sanpete", "9wb2rt": " UT Garfield", "9wb822": " UT Garfield", "9wb2zh": " UT Garfield", "9wb2yw": " UT Garfield", "9wbxxj": " UT Sanpete", "9wbdet": " UT Wayne", "9wbzn9": " UT Emery", "9wbstz": " UT Sevier", "9wb2qp": " UT Garfield", "9wb2mz": " UT Garfield", "9wbtjw": " UT Sevier", "9wbrjw": " UT Sanpete", "9wbkgx": " UT Sevier", "9wbmrf": " UT Sevier", "9wbt0q": " UT Sevier", "9wb9b4": " UT Wayne", "9wb9bt": " UT Wayne", "9wb4e7": " UT Piute", "9wbj9x": " UT Millard", "9wbcnp": " UT Wayne", "9wbx6w": " UT Sanpete", "9wbtdw": " UT Sevier", "9wb6fd": " UT Piute", "9wbe32": " UT Sevier", "9wb6c2": " UT Piute", "9wbbf2": " UT Garfield", "9wbc4e": " UT Wayne", "9wb8sj": " UT Garfield", "9wbwx4": " UT Sanpete", "9wbedz": " UT Sevier", "9wbe65": " UT Sevier", "9wbk98": " UT Sevier", "9wbrbk": " UT Juab", "9wbpsy": " UT Millard", "9wbpsw": " UT Millard", "9wbpmf": " UT Millard", "9wbu07": " UT Sevier", "9wbhxg": " UT Sevier", "9wbm9p": " UT Millard", "9wbmcc": " UT Millard", "9wbeye": " UT Sevier", "9wb7fz": " UT Sevier", "9wbymy": " UT Emery", "9wb44b": " UT Beaver", "9wb77p": " UT Sevier", "9wbnus": " UT Millard", "9wbtq5": " UT Sevier", "9wbtwb": " UT Sevier", "9wbtxy": " UT Sevier", "9wbsrt": " UT Sevier", "9wbdj7": " UT Wayne", "9wbypk": " UT Emery", "9wb5zh": " UT Sevier", "9wbk04": " UT Sevier", "9wbjee": " UT Millard", "9wb4fk": " UT Piute", "9wb0xd": " UT Garfield", "9wb4vv": " UT Piute", "9wb46g": " UT Piute", "9wb4sj": " UT Piute", "9wbhn6": " UT Sevier", "9wb4fv": " UT Piute", "9wbf1r": " UT Wayne", "9wb8vw": " UT Garfield", "9wb4tq": " UT Piute", "9wb4fx": " UT Piute", "9wbk99": " UT Sevier", "9wbk9d": " UT Sevier", "9wbk92": " UT Sevier", "9wbmym": " UT Sevier", "9wbk3p": " UT Sevier", "9wb8yp": " UT Garfield", "9wbx7j": " UT Sanpete", "9wbqxq": " UT Sanpete", "9wbx18": " UT Sanpete", "9wbq4j": " UT Millard", "9wbhfb": " UT Millard", "9wbh44": " UT Millard", "9wbp44": " UT Millard", "9wb5ys": " UT Sevier", "9wb9r3": " UT Wayne", "9wbcv9": " UT Wayne", "9wbxdw": " UT Sanpete", "9wbyb0": " UT Sanpete", "9wbz42": " UT Sanpete", "9wb3cc": " UT Piute", "9wbvp0": " UT Emery", "9wbwyr": " UT Sanpete", "9wbrnt": " UT Sanpete", "9wb9vj": " UT Wayne", "9wb4tu": " UT Piute", "9wb5w4": " UT Sevier", "9wbs1j": " UT Sevier", "9wbt7x": " UT Sevier", "9wbjet": " UT Millard", "9wbmw2": " UT Sevier", "9wb2gb": " UT Garfield", "9wbvkq": " UT Emery", "9wbmyk": " UT Sevier", "9wb7n5": " UT Sevier", "9wbd7r": " UT Wayne", "9wb4tt": " UT Piute", "9wbwd1": " UT Sanpete", "9wbj4p": " UT Millard", "9wbqxd": " UT Sanpete", "9wb1j7": " UT Piute", "9wbyxu": " UT Emery", "9wbr2b": " UT Millard", "9wbkuj": " UT Sevier", "9wbmk3": " UT Sevier", "9wbvkt": " UT Emery", "9wbjsj": " UT Millard", "9wbk3k": " UT Sevier", "9wb1w3": " UT Piute", "9wbqz9": " UT Sanpete", "9wbk9f": " UT Sevier"}